Workbook
Name ALOS_Factor_Options: 'M2 BOR & Tradeoff analysis'!$N$20:$N$24
Name Average_ALOS_Options: 'M2 BOR & Tradeoff analysis'!$N$8:$N$12
Name Bed_Expansion_Rate_Options: 'M2 BOR & Tradeoff analysis'!$N$3:$N$6
Name Elderly_Population_Growth_Adjust_Options: 'M2 BOR & Tradeoff analysis'!$N$14:$N$18
Name Govt_Policy_Factor_Options: 'M2 BOR & Tradeoff analysis'!$N$26:$N$27

Sheet Overview
B1: Singapore Public Healthcare Sustainability 2026–2035 | L1: IS 602 · G2 Group 6
B2: Motivation: Singapore is ageing fast, 1 in 4 Singaporeans aged 65+ by 2030 Rising healthcare demand and increased costs. Can Singapore's public healthcare system remain sustainable through 2035 and what will affect it?
B3: Our approach: A 4-module spreadsheet model covering demographics, hospital capacity, healthcare costs and financing sustainability
A4: Prepared by: Akshaya Vijayakumar Sivakami · Carina Faith Peh Xin Yi · Cher In Teo · Serene Cheng · Xiong Yu
B5: KEY METRICS AT A GLANCE by 2035
B6: Elderly Dependency Ratio Aged 65 and above | E6: Bed Occupancy Rate | H6: Projected Government Healthcare Cost | K6: Financing Deficit
B7: ='M1 Demand Driver'!AF30/100 -> 0.4094669 | E7: ='M2 BOR & Tradeoff analysis'!G37 -> 0.74213922 | H7: SGD Billion | I7: ='M3 Healthcare Costs'!K19 -> 14104.814 | K7: SGD Billion | L7: ='M4 Financing Gap and OOP'!P26 -> 951.47416
B8: significant increase from 11% in 2005 KEY DEMAND DRIVER | E8: within 85% threshold | H8: up from SGD 7.5B in 2025 | K8: deficit from 2031 — 8.6% of budget
B10: NAVIGATION (Click on sheet name to enter)
B11: SHEET NAME | E11: DESCRIPTION
B12: Influence Diagram | E12: Visual map of how all model variables connect and interact across modules
B13: Blackbox | E13: Full model overview — inputs, processes and outputs
B14: M1 Population | E14: Mortality & fertility rates projections 2026–2035
B15: M1 Demand Driver | E15: Projected age-band population and elderly dependency ratio
B16: M2 HAR | E16: Age-specific hospital admission rates used to forecast bed demand
B17: M2 Beds | E17: Annual acute bed expansion projections
B18: M2 BOR & Tradeoff Analysis | E18: Projected Bed Occupancy Rate (BOR)
B19: M2 Sensitivity Analysis | E19: Sensitivity analysis: impact of expansion rate, ALOS & policy factors on BOR
B20: M3 Healthcare Budget | E20: Government healthcare operating expenditure projections 2026–2035
B21: M3 Healthcare Costs | E21: Cost per admission for government and total projected healthcare expenditure with medical inflation
B22: M3 Sensitivity Analysis | E22: One-way and two-way sensitivity: inflation rate vs elderly cost multiplier
... B27: Data | E27: Source datasets

Sheet Influence Diagram
A1: Influence Diagram
A21: Legend

Sheet Blackbox
A1: Blackbox
A3: Input | K3: Output
A5: Decisions (Controllable) | K5: Performance measures
A6: Beds in public acute hospital | K6: Financing gap (surplus or deficit)
A7: Weighted avg govt subsidy rate | K7: Healthcare as % of household income (Burden status)
A8: Government operating healthcare expenditure
A9: Acute inpatient subsidies
A11: Parameters (Uncontrollable) | K11: Consequence variables
A12: Age-specific fertility rates | K12: Projected govt funded annual hospital costs
A13: Age-specific mortality rates | K13: Total out of pocket expenditure
A14: Hospital admission rate | K14: Govt operating expenditure on hospital budget
A15: Medical inflation rate | K15: Total hospital bed-day demand
A16: Healthcare CPI | K16: Bed Occupancy Rate
A17: Annual household income
A18: No. of residents household

Sheet M1 Population
A1: Average Mortality and Survival Rates (based on rates fom 2021 - 2025) | E1: Age-specific Fertility Rates (per thousand residents) Projected (using rates from 2015 - 2025)
A2: Data Series | B2: Avg Mortality Rate | C2: Avg Survival Rate
A3: Under 1 Year | B3: =AVERAGE($R52:$V52) -> 2.02 | C3: =1-(B3/1000) -> 0.99798 | E3: Data Series | F3: 2026 | G3: 2027 | H3: 2028 | I3: 2029 | J3: 2030 | K3: 2031 | L3: 2032 | M3: 2033 | N3: 2034 | O3: 2035
A4: 1 - 4 Years | B4: =AVERAGE($R53:$V53) -> 0.1 | C4: =1-(B4/1000) -> 0.9999 | E4: 15 - 19 Years | F4: {=GROWTH($P14:$Z14, $P$13:$Z$13, F$3)} -> 1.7031888 | G4: {=GROWTH($P14:$Z14, $P$13:$Z$13, G$3)} -> 1.6234625 | H4: {=GROWTH($P14:$Z14, $P$13:$Z$13, H$3)} -> 1.5474683 | I4: {=GROWTH($P14:$Z14, $P$13:$Z$13, I$3)} -> 1.4750313 | J4: {=GROWTH($P14:$Z14, $P$13:$Z$13, J$3)} -> 1.4059851 | K4: {=GROWTH($P14:$Z14, $P$13:$Z$13, K$3)} -> 1.340171 | L4: {=GROWTH($P14:$Z14, $P$13:$Z$13, L$3)} -> 1.2774376 | M4: {=GROWTH($P14:$Z14, $P$13:$Z$13, M$3)} -> 1.2176408 | ... O4: {=GROWTH($P14:$Z14, $P$13:$Z$13, O$3)} -> 1.1063134
A5: 5 - 9 Years | B5: =AVERAGE($R54:$V54) -> 0.1 | C5: =1-(B5/1000) -> 0.9999 | E5: 20 - 24 Years | F5: {=GROWTH($P15:$Z15, $P$13:$Z$13, F$3)} -> 8.3187496 | G5: {=GROWTH($P15:$Z15, $P$13:$Z$13, G$3)} -> 7.7580791 | H5: {=GROWTH($P15:$Z15, $P$13:$Z$13, H$3)} -> 7.2351969 | I5: {=GROWTH($P15:$Z15, $P$13:$Z$13, I$3)} -> 6.7475562 | J5: {=GROWTH($P15:$Z15, $P$13:$Z$13, J$3)} -> 6.2927817 | K5: {=GROWTH($P15:$Z15, $P$13:$Z$13, K$3)} -> 5.8686582 | L5: {=GROWTH($P15:$Z15, $P$13:$Z$13, L$3)} -> 5.47312 | M5: {=GROWTH($P15:$Z15, $P$13:$Z$13, M$3)} -> 5.1042404 | ... O5: {=GROWTH($P15:$Z15, $P$13:$Z$13, O$3)} -> 4.4393913
A6: 10 - 14 Years | B6: =AVERAGE($R55:$V55) -> 0.12 | C6: =1-(B6/1000) -> 0.99988 | E6: 25 - 29 Years | F6: {=GROWTH($P16:$Z16, $P$13:$Z$13, F$3)} -> 38.022728 | G6: {=GROWTH($P16:$Z16, $P$13:$Z$13, G$3)} -> 35.919573 | H6: {=GROWTH($P16:$Z16, $P$13:$Z$13, H$3)} -> 33.932749 | I6: {=GROWTH($P16:$Z16, $P$13:$Z$13, I$3)} -> 32.055823 | J6: {=GROWTH($P16:$Z16, $P$13:$Z$13, J$3)} -> 30.282716 | K6: {=GROWTH($P16:$Z16, $P$13:$Z$13, K$3)} -> 28.607684 | L6: {=GROWTH($P16:$Z16, $P$13:$Z$13, L$3)} -> 27.025304 | M6: {=GROWTH($P16:$Z16, $P$13:$Z$13, M$3)} -> 25.53045 | ... O6: {=GROWTH($P16:$Z16, $P$13:$Z$13, O$3)} -> 22.784224
A7: 15 - 19 Years | B7: =AVERAGE($R56:$V56) -> 0.22 | C7: =1-(B7/1000) -> 0.99978 | E7: 30 - 34 Years | F7: {=GROWTH($P17:$Z17, $P$13:$Z$13, F$3)} -> 74.141049 | G7: {=GROWTH($P17:$Z17, $P$13:$Z$13, G$3)} -> 72.065164 | H7: {=GROWTH($P17:$Z17, $P$13:$Z$13, H$3)} -> 70.047401 | I7: {=GROWTH($P17:$Z17, $P$13:$Z$13, I$3)} -> 68.086134 | J7: {=GROWTH($P17:$Z17, $P$13:$Z$13, J$3)} -> 66.17978 | K7: {=GROWTH($P17:$Z17, $P$13:$Z$13, K$3)} -> 64.326803 | L7: {=GROWTH($P17:$Z17, $P$13:$Z$13, L$3)} -> 62.525708 | M7: {=GROWTH($P17:$Z17, $P$13:$Z$13, M$3)} -> 60.775042 | ... O7: {=GROWTH($P17:$Z17, $P$13:$Z$13, O$3)} -> 57.419388
A8: 20 - 24 Years | B8: =AVERAGE($R57:$V57) -> 0.24 | C8: =1-(B8/1000) -> 0.99976 | E8: 35 - 39 Years | F8: {=GROWTH($P18:$Z18, $P$13:$Z$13, F$3)} -> 48.525004 | G8: {=GROWTH($P18:$Z18, $P$13:$Z$13, G$3)} -> 48.394502 | H8: {=GROWTH($P18:$Z18, $P$13:$Z$13, H$3)} -> 48.264352 | I8: {=GROWTH($P18:$Z18, $P$13:$Z$13, I$3)} -> 48.134552 | J8: {=GROWTH($P18:$Z18, $P$13:$Z$13, J$3)} -> 48.0051 | K8: {=GROWTH($P18:$Z18, $P$13:$Z$13, K$3)} -> 47.875997 | L8: {=GROWTH($P18:$Z18, $P$13:$Z$13, L$3)} -> 47.747241 | M8: {=GROWTH($P18:$Z18, $P$13:$Z$13, M$3)} -> 47.618831 | ... O8: {=GROWTH($P18:$Z18, $P$13:$Z$13, O$3)} -> 47.363047
A9: 25 - 29 Years | B9: =AVERAGE($R58:$V58) -> 0.3 | C9: =1-(B9/1000) -> 0.9997 | E9: 40 - 44 Years | F9: {=GROWTH($P19:$Z19, $P$13:$Z$13, F$3)} -> 10.223882 | G9: {=GROWTH($P19:$Z19, $P$13:$Z$13, G$3)} -> 10.355573 | H9: {=GROWTH($P19:$Z19, $P$13:$Z$13, H$3)} -> 10.48896 | I9: {=GROWTH($P19:$Z19, $P$13:$Z$13, I$3)} -> 10.624066 | J9: {=GROWTH($P19:$Z19, $P$13:$Z$13, J$3)} -> 10.760911 | K9: {=GROWTH($P19:$Z19, $P$13:$Z$13, K$3)} -> 10.89952 | L9: {=GROWTH($P19:$Z19, $P$13:$Z$13, L$3)} -> 11.039914 | M9: {=GROWTH($P19:$Z19, $P$13:$Z$13, M$3)} -> 11.182116 | ... O9: {=GROWTH($P19:$Z19, $P$13:$Z$13, O$3)} -> 11.472039
A10: 30 - 34 Years | B10: =AVERAGE($R59:$V59) -> 0.36 | C10: =1-(B10/1000) -> 0.99964 | E10: 45 - 49 Years | F10: {=GROWTH($P20:$Z20, $P$13:$Z$13, F$3)} -> 0.56881686 | G10: {=GROWTH($P20:$Z20, $P$13:$Z$13, G$3)} -> 0.59158904 | H10: {=GROWTH($P20:$Z20, $P$13:$Z$13, H$3)} -> 0.61527288 | I10: {=GROWTH($P20:$Z20, $P$13:$Z$13, I$3)} -> 0.63990489 | J10: {=GROWTH($P20:$Z20, $P$13:$Z$13, J$3)} -> 0.66552303 | K10: {=GROWTH($P20:$Z20, $P$13:$Z$13, K$3)} -> 0.69216677 | L10: {=GROWTH($P20:$Z20, $P$13:$Z$13, L$3)} -> 0.71987717 | M10: {=GROWTH($P20:$Z20, $P$13:$Z$13, M$3)} -> 0.74869694 | ... O10: {=GROWTH($P20:$Z20, $P$13:$Z$13, O$3)} -> 0.809844
A11: 35 - 39 Years | B11: =AVERAGE($R60:$V60) -> 0.52 | C11: =1-(B11/1000) -> 0.99948
A12: 40 - 44 Years | B12: =AVERAGE($R61:$V61) -> 0.8 | C12: =1-(B12/1000) -> 0.9992 | E12: Fertility Rates from 2005 to 2025
A13: 45 - 49 Years | B13: =AVERAGE($R62:$V62) -> 1.34 | C13: =1-(B13/1000) -> 0.99866 | E13: Data Series | F13: 2005 | G13: 2006 | H13: 2007 | I13: 2008 | J13: 2009 | K13: 2010 | L13: 2011 | M13: 2012 | N13: 2013 | O13: 2014 | P13: 2015 | Q13: 2016 | R13: 2017 | S13: 2018 | T13: 2019 | U13: 2020 | V13: 2021 | W13: 2022 | X13: 2023 | Y13: 2024 | Z13: 2025
A14: 50 - 54 Years | B14: =AVERAGE($R63:$V63) -> 2.22 | C14: =1-(B14/1000) -> 0.99778 | E14: 15 - 19 Years | F14: 7.2 | G14: 6.6 | H14: 6.1 | I14: 6.1 | J14: 5 | K14: 4.8 | L14: 4.7 | M14: 4.3 | N14: 3.8 | O14: 3.3 | P14: 2.7 | Q14: 2.7 | R14: 2.6 | S14: 2.5 | T14: 2.5 | U14: 2.3 | V14: 2.2 | W14: 2.1 | X14: 2.2 | Y14: 2.3 | Z14: 1.3
A15: 55 - 59 Years | B15: =AVERAGE($R64:$V64) -> 3.58 | C15: =1-(B15/1000) -> 0.99642 | E15: 20 - 24 Years | F15: 32.5 | G15: 30.6 | H15: 31.2 | I15: 29.1 | J15: 25.4 | K15: 23.3 | L15: 22.4 | M15: 22.2 | N15: 19.7 | O15: 19.5 | P15: 18.7 | Q15: 17 | R15: 15.1 | S15: 14.4 | T15: 12.7 | U15: 12.7 | V15: 11.7 | W15: 11.2 | X15: 10.6 | Y15: 9.8 | Z15: 8.7
A16: 60 - 64 Years | B16: =AVERAGE($R65:$V65) -> 5.96 | C16: =1-(B16/1000) -> 0.99404 | E16: 25 - 29 Years | F16: 80.7 | G16: 79.6 | H16: 78.7 | I16: 78.9 | J16: 74.2 | K16: 68.1 | L16: 73.4 | M16: 76.7 | N16: 70.5 | O16: 71.1 | P16: 68.7 | Q16: 65.8 | R16: 62.2 | S16: 60.6 | T16: 59.4 | U16: 54.6 | V16: 53.4 | W16: 48.8 | X16: 43.7 | Y16: 42.6 | Z16: 38.3
A17: 65 - 69 Years | B17: =AVERAGE($R66:$V66) -> 9.62 | C17: =1-(B17/1000) -> 0.99038 | E17: 30 - 34 Years | F17: 89.2 | G17: 93.1 | H17: 94.4 | I17: 94.6 | J17: 90.1 | K17: 86 | L17: 89.5 | M17: 99.5 | N17: 90.2 | O17: 99.3 | P17: 98.5 | Q17: 96.2 | R17: 93.3 | S17: 92.9 | T17: 92.4 | U17: 90.8 | V17: 92.9 | W17: 86.7 | X17: 78.7 | Y17: 79.3 | Z17: 70
A18: 70 - 74 Years | B18: =AVERAGE($R67:$V67) -> 15.34 | C18: =1-(B18/1000) -> 0.98466 | E18: 35 - 39 Years | F18: 36.8 | G18: 38.7 | H18: 41.5 | I18: 41.5 | J18: 42.6 | K18: 42.2 | L18: 42.4 | M18: 46.3 | N18: 44.7 | O18: 48.3 | P18: 49.9 | Q18: 49.7 | R18: 48.6 | S18: 48.4 | T18: 50.1 | U18: 49 | V18: 53.6 | W18: 49.4 | X18: 47.9 | Y18: 50 | Z18: 46.2
A19: 75 - 79 Years | B19: =AVERAGE($R68:$V68) -> 26.66 | C19: =1-(B19/1000) -> 0.97334 | E19: 40 - 44 Years | F19: 6.2 | G19: 6.4 | H19: 6.4 | I19: 6.6 | J19: 7 | K19: 6.1 | L19: 7.2 | M19: 8 | N19: 8 | O19: 8.3 | P19: 8.9 | Q19: 8.8 | R19: 9 | S19: 8.8 | T19: 9.9 | U19: 9.5 | V19: 10.2 | W19: 9.8 | X19: 9.6 | Y19: 10.2 | Z19: 9.6
A20: 80 - 84 Years | B20: =AVERAGE($R69:$V69) -> 49.98 | C20: =1-(B20/1000) -> 0.95002 | E20: 45 - 49 Years | F20: 0.2 | G20: 0.2 | H20: 0.2 | I20: 0.2 | J20: 0.3 | K20: 0.3 | L20: 0.3 | M20: 0.3 | N20: 0.3 | O20: 0.3 | P20: 0.4 | Q20: 0.3 | R20: 0.5 | S20: 0.5 | T20: 0.4 | U20: 0.5 | V20: 0.3 | W20: 0.4 | X20: 0.6 | Y20: 0.7 | Z20: 0.5
A21: 85 - 89 Years | B21: =AVERAGE($R70:$V70) -> 91.9 | C21: =1-(B21/1000) -> 0.9081
A22: 90 Years & Over | B22: =AVERAGE($R71:$V71) -> 168.6 | C22: =1-(B22/1000) -> 0.8314
A50: Mortality Rates from 2005 to 2025
A51: Data Series | B51: 2005 | C51: 2006 | D51: 2007 | E51: 2008 | F51: 2009 | G51: 2010 | H51: 2011 | I51: 2012 | J51: 2013 | K51: 2014 | L51: 2015 | M51: 2016 | N51: 2017 | O51: 2018 | P51: 2019 | Q51: 2020 | R51: 2021 | S51: 2022 | T51: 2023 | U51: 2024 | V51: 2025
A52: Under 1 Year | B52: 2.1 | C52: 2.6 | D52: 2.1 | E52: 2.1 | F52: 2.2 | G52: 2 | H52: 2 | I52: 1.8 | J52: 2 | K52: 1.8 | L52: 1.7 | M52: 2.4 | N52: 2.2 | O52: 2.1 | P52: 1.7 | Q52: 1.8 | R52: 1.8 | S52: 1.8 | T52: 2.2 | U52: 2.3 | V52: 2
A53: 1 - 4 Years | B53: 0.2 | C53: 0.1 | D53: 0.1 | E53: 0.2 | F53: 0.2 | G53: 0.1 | H53: 0.2 | I53: 0.2 | J53: 0.2 | K53: 0.1 | L53: 0.1 | M53: 0.1 | N53: 0.1 | O53: 0.1 | P53: 0.1 | Q53: 0.1 | R53: 0.1 | S53: 0.1 | T53: 0.1 | U53: 0.1 | V53: 0.1
A54: 5 - 9 Years | B54: 0.1 | C54: 0.1 | D54: 0.1 | E54: 0.1 | F54: 0.1 | G54: 0.1 | H54: 0.1 | I54: 0.1 | J54: 0.1 | K54: - | L54: - | M54: 0.1 | N54: - | O54: 0.1 | P54: 0.1 | Q54: - | R54: - | S54: 0.1 | T54: 0.1 | U54: 0.1 | V54: 0.1
A55: 10 - 14 Years | B55: 0.1 | C55: 0.2 | D55: 0.1 | E55: 0.1 | F55: 0.1 | G55: 0.1 | H55: 0.1 | I55: 0.1 | J55: 0.1 | K55: - | L55: 0.1 | M55: 0.1 | N55: 0.1 | O55: 0.1 | P55: - | Q55: 0.1 | R55: 0.1 | S55: 0.2 | T55: 0.1 | U55: 0.1 | V55: 0.1
A56: 15 - 19 Years | B56: 0.2 | C56: 0.2 | D56: 0.2 | E56: 0.2 | F56: 0.2 | G56: 0.2 | H56: 0.2 | I56: 0.2 | J56: 0.2 | K56: 0.2 | L56: 0.2 | M56: 0.2 | N56: 0.2 | O56: 0.2 | P56: 0.2 | Q56: 0.2 | R56: 0.3 | S56: 0.2 | T56: 0.2 | U56: 0.2 | V56: 0.2
A57: 20 - 24 Years | B57: 0.4 | C57: 0.4 | D57: 0.4 | E57: 0.4 | F57: 0.4 | G57: 0.3 | H57: 0.3 | I57: 0.3 | J57: 0.3 | K57: 0.3 | L57: 0.2 | M57: 0.2 | N57: 0.2 | O57: 0.3 | P57: 0.3 | Q57: 0.2 | R57: 0.2 | S57: 0.3 | T57: 0.2 | U57: 0.3 | V57: 0.2
A58: 25 - 29 Years | B58: 0.4 | C58: 0.4 | D58: 0.4 | E58: 0.4 | F58: 0.3 | G58: 0.3 | H58: 0.3 | I58: 0.3 | J58: 0.3 | K58: 0.2 | L58: 0.3 | M58: 0.3 | N58: 0.3 | O58: 0.3 | P58: 0.2 | Q58: 0.3 | R58: 0.3 | S58: 0.3 | T58: 0.3 | U58: 0.3 | V58: 0.3
A59: 30 - 34 Years | B59: 0.5 | C59: 0.5 | D59: 0.4 | E59: 0.4 | F59: 0.4 | G59: 0.3 | H59: 0.4 | I59: 0.4 | J59: 0.4 | K59: 0.4 | L59: 0.4 | M59: 0.3 | N59: 0.4 | O59: 0.4 | P59: 0.4 | Q59: 0.3 | R59: 0.3 | S59: 0.4 | T59: 0.3 | U59: 0.4 | V59: 0.4
A60: 35 - 39 Years | B60: 0.8 | C60: 0.7 | D60: 0.6 | E60: 0.7 | F60: 0.6 | G60: 0.6 | H60: 0.5 | I60: 0.6 | J60: 0.5 | K60: 0.5 | L60: 0.5 | M60: 0.5 | N60: 0.5 | O60: 0.5 | P60: 0.5 | Q60: 0.5 | R60: 0.5 | S60: 0.6 | T60: 0.5 | U60: 0.5 | V60: 0.5
A61: 40 - 44 Years | B61: 1.2 | C61: 1.3 | D61: 1.2 | E61: 1.2 | F61: 0.9 | G61: 1 | H61: 0.9 | I61: 0.9 | J61: 0.9 | K61: 0.9 | L61: 0.9 | M61: 0.9 | N61: 0.8 | O61: 0.7 | P61: 0.8 | Q61: 0.8 | R61: 0.8 | S61: 0.8 | T61: 0.8 | U61: 0.8 | V61: 0.8
A62: 45 - 49 Years | B62: 1.9 | C62: 1.9 | D62: 1.9 | E62: 1.8 | F62: 1.6 | G62: 1.7 | H62: 1.7 | I62: 1.6 | J62: 1.5 | K62: 1.5 | L62: 1.5 | M62: 1.4 | N62: 1.4 | O62: 1.4 | P62: 1.3 | Q62: 1.3 | R62: 1.5 | S62: 1.4 | T62: 1.3 | U62: 1.3 | V62: 1.2
A63: 50 - 54 Years | B63: 3.5 | C63: 3.2 | D63: 3.1 | E63: 3.2 | F63: 3 | G63: 3 | H63: 2.8 | I63: 2.5 | J63: 2.7 | K63: 2.5 | L63: 2.5 | M63: 2.4 | N63: 2.6 | O63: 2.3 | P63: 2.1 | Q63: 2.2 | R63: 2.3 | S63: 2.3 | T63: 2.2 | U63: 2.2 | V63: 2.1
A64: 55 - 59 Years | B64: 5.7 | C64: 5.3 | D64: 5.1 | E64: 5.1 | F64: 4.7 | G64: 4.5 | H64: 4.4 | I64: 4.6 | J64: 4.3 | K64: 4.5 | L64: 4.2 | M64: 4.1 | N64: 3.9 | O64: 3.9 | P64: 3.7 | Q64: 3.7 | R64: 3.8 | S64: 3.6 | T64: 3.7 | U64: 3.5 | V64: 3.3
A65: 60 - 64 Years | B65: 9.3 | C65: 9 | D65: 8.5 | E65: 8.1 | F65: 7.4 | G65: 7.3 | H65: 7 | I65: 7.3 | J65: 7 | K65: 6.4 | L65: 6.5 | M65: 6.2 | N65: 6.3 | O65: 6.3 | P65: 5.9 | Q65: 5.9 | R65: 6.4 | S65: 6.3 | T65: 6 | U65: 5.7 | V65: 5.4
A66: 65 - 69 Years | B66: 16 | C66: 14.1 | D66: 14.1 | E66: 13.9 | F66: 12.8 | G66: 12.5 | H66: 12.6 | I66: 11.9 | J66: 11 | K66: 10.6 | L66: 10.4 | M66: 10.1 | N66: 9.9 | O66: 9.5 | P66: 9 | Q66: 9.2 | R66: 9.7 | S66: 10 | T66: 9.8 | U66: 9.5 | V66: 9.1
A67: 70 - 74 Years | B67: 24.8 | C67: 23.6 | D67: 25.9 | E67: 24.1 | F67: 21.7 | G67: 20.7 | H67: 19.9 | I67: 20 | J67: 19.6 | K67: 18.5 | L67: 18.2 | M67: 16.7 | N67: 16.9 | O67: 16.5 | P67: 15.3 | Q67: 15.1 | R67: 15.8 | S67: 16.2 | T67: 15.4 | U67: 14.9 | V67: 14.4
... A71: 90 Years & Over | B71: 163.3 | C71: 162.7 | D71: 159.2 | E71: 157.6 | F71: 159.2 | G71: 163.6 | H71: 158.2 | I71: 157.2 | J71: 164.7 | K71: 163.4 | L71: 160.4 | M71: 148.5 | N71: 151.8 | O71: 155.1 | P71: 149.5 | Q71: 143.8 | R71: 165.3 | S71: 185 | T71: 177.3 | U71: 160.8 | V71: 154.6
A73: Number of Residents from 2005 to 2025
A74: Data Series | B74: 2005 | C74: 2006 | D74: 2007 | E74: 2008 | F74: 2009 | G74: 2010 | H74: 2011 | I74: 2012 | J74: 2013 | K74: 2014 | L74: 2015 | M74: 2016 | N74: 2017 | O74: 2018 | P74: 2019 | Q74: 2020 | R74: 2021 | S74: 2022 | T74: 2023 | U74: 2024 | V74: 2025
A75: Under 1 Year | B75: 35003 | C75: 35563 | D75: 35770 | E75: 37444 | F75: 35145 | G75: 32788 | H75: 31172 | I75: 33237 | J75: 33912 | K75: 32782 | L75: 34559 | M75: 34640 | N75: 33374 | O75: 32664 | P75: 32967 | Q75: 33434 | R75: 31611 | S75: 32073 | T75: 30052 | U75: 29246 | V75: 29422
A76: 1 - 4 Years | B76: 164526 | C76: 158916 | D76: 157856 | E76: 156445 | F76: 162643 | G76: 161644 | H76: 157077 | I76: 153436 | J76: 149383 | K76: 148587 | L76: 149016 | M76: 152520 | N76: 154279 | O76: 152864 | P76: 152388 | Q76: 149642 | R76: 146824 | S76: 146012 | T76: 145216 | U76: 141250 | V76: 136128
A77: 5 - 9 Years | B77: 237237 | C77: 235204 | D77: 229541 | E77: 223622 | F77: 221435 | G77: 215675 | H77: 208119 | I77: 206324 | J77: 205704 | K77: 205790 | L77: 204452 | M77: 201509 | N77: 200575 | O77: 199066 | P77: 197775 | Q77: 198737 | R77: 198760 | S77: 201360 | T77: 201974 | U77: 202082 | V77: 199813
A78: 10 - 14 Years | B78: 258553 | C78: 256482 | D78: 255292 | E78: 253796 | F78: 248628 | G78: 244302 | H78: 240536 | I78: 233320 | J78: 226244 | K78: 220796 | L78: 214388 | M78: 207495 | N78: 206253 | O78: 206530 | P78: 207926 | Q78: 206393 | R78: 199993 | S78: 202379 | T78: 204459 | U78: 204391 | V78: 206577
A79: 15 - 19 Years | B79: 234921 | C79: 246547 | D79: 257298 | E79: 262856 | F79: 262775 | G79: 263750 | H79: 260738 | I79: 258861 | J79: 255066 | K79: 247337 | L79: 242902 | M79: 239771 | N79: 232973 | O79: 226520 | P79: 222222 | Q79: 215234 | R79: 204913 | S79: 206749 | T79: 209579 | U79: 211067 | V79: 211394
A80: 20 - 24 Years | B80: 218951 | C80: 219631 | D80: 218485 | E80: 225385 | F80: 241753 | G80: 247190 | H80: 255069 | I80: 264506 | J80: 266889 | K80: 263918 | L80: 264127 | M80: 260854 | N80: 259072 | O80: 255516 | P80: 249079 | Q80: 244537 | R80: 237720 | S80: 233303 | T80: 229066 | U80: 224644 | V80: 218686
A81: 25 - 29 Years | B81: 247799 | C81: 251659 | D81: 254523 | E81: 263114 | F81: 274308 | G81: 272639 | H81: 262606 | I81: 254582 | J81: 255615 | K81: 265659 | L81: 271030 | M81: 279988 | N81: 290198 | O81: 291631 | P81: 288194 | Q81: 286997 | R81: 278037 | S81: 280082 | T81: 277889 | U81: 269536 | V81: 263735
A82: 30 - 34 Years | B82: 293414 | C82: 293251 | D82: 294453 | E82: 289817 | F82: 297240 | G82: 298687 | H82: 297555 | I82: 295396 | J82: 296870 | K82: 292287 | L82: 290619 | M82: 285544 | N82: 279340 | O82: 281397 | P82: 293446 | Q82: 297798 | R82: 301060 | S82: 317153 | T82: 323627 | U82: 320486 | V82: 319836
A83: 35 - 39 Years | B83: 299153 | C83: 298203 | D83: 301973 | E83: 307243 | F83: 317311 | G83: 320024 | H83: 316161 | I83: 313970 | J83: 305503 | K83: 302029 | L83: 301067 | M83: 301998 | N83: 300956 | O83: 303720 | P83: 300818 | Q83: 299515 | R83: 289221 | S83: 290981 | T83: 300037 | U83: 314575 | V83: 320125
A84: 40 - 44 Years | B84: 321472 | C84: 323017 | D84: 321049 | E84: 317363 | F84: 312983 | G84: 309441 | H84: 306614 | I84: 308823 | J84: 312581 | K84: 316023 | L84: 316755 | M84: 313445 | N84: 311484 | O84: 303640 | P84: 300763 | Q84: 299291 | R84: 292770 | S84: 299871 | T84: 310173 | U84: 310259 | V84: 311772
A85: 45 - 49 Years | B85: 307546 | C85: 312858 | D85: 315552 | E85: 318078 | F85: 322497 | G85: 323459 | H85: 323991 | I85: 320925 | J85: 316336 | K85: 308533 | L85: 303413 | M85: 301183 | N85: 303457 | O85: 307838 | P85: 311682 | Q85: 311740 | R85: 300125 | S85: 304317 | T85: 302515 | U85: 301224 | V85: 302015
... A94: 90 Years & Over | B94: 8066 | C94: 8510 | D94: 9024 | E94: 9681 | F94: 10244 | G94: 10760 | H94: 11366 | I94: 12050 | J94: 12821 | K94: 13390 | L94: 14169 | M94: 15157 | N94: 16454 | O94: 17786 | P94: 19429 | Q94: 20875 | R94: 22090 | S94: 22942 | T94: 23728 | U94: 25155 | V94: 27360
A95: Total | B95: =SUM(B75:B94) -> 3467814 | C95: =SUM(C75:C94) -> 3525894 | D95: =SUM(D75:D94) -> 3583082 | E95: =SUM(E75:E94) -> 3642659 | F95: =SUM(F75:F94) -> 3733876 | G95: =SUM(G75:G94) -> 3771721 | H95: =SUM(H75:H94) -> 3789251 | I95: =SUM(I75:I94) -> 3818205 | ... V95: =SUM(V75:V94) -> 4204515

Sheet M1 Demand Driver
A1: Demographic Projection from 2025 - 2035
A3: Age group | B3: 2025 | C3: 2026 | D3: 2027 | E3: 2028 | F3: 2029 | G3: 2030 | H3: 2031 | I3: 2032 | J3: 2033 | K3: 2034 | L3: 2035 | O3: Age Group | P3: 2025 Pop | Q3: Neg 2025 | R3: 2035 Pop
A4: Under 1 Year | B4: ='M1 Population'!V75 -> 29422 | C4: =(SUMPRODUCT($B$8:$B$14,'M1 Population'!F$4:F$10) * 0.5 / 1000) * 'M1 Population'!$C3 -> 27351.397 | D4: =(SUMPRODUCT($B$8:$B$14,'M1 Population'!G$4:G$10) * 0.5 / 1000) * 'M1 Population'!$C3 -> 26676.8 | E4: =(SUMPRODUCT($B$8:$B$14,'M1 Population'!H$4:H$10) * 0.5 / 1000) * 'M1 Population'!$C3 -> 26031.763 | F4: =(SUMPRODUCT($B$8:$B$14,'M1 Population'!I$4:I$10) * 0.5 / 1000) * 'M1 Population'!$C3 -> 25414.892 | G4: =(SUMPRODUCT($B$8:$B$14,'M1 Population'!J$4:J$10) * 0.5 / 1000) * 'M1 Population'!$C3 -> 24824.867 | H4: =(SUMPRODUCT($B$8:$B$14,'M1 Population'!K$4:K$10) * 0.5 / 1000) * 'M1 Population'!$C3 -> 24260.438 | I4: =(SUMPRODUCT($B$8:$B$14,'M1 Population'!L$4:L$10) * 0.5 / 1000) * 'M1 Population'!$C3 -> 23720.419 | J4: =(SUMPRODUCT($B$8:$B$14,'M1 Population'!M$4:M$10) * 0.5 / 1000) * 'M1 Population'!$C3 -> 23203.691 | ... L4: =(SUMPRODUCT($B$8:$B$14,'M1 Population'!O$4:O$10) * 0.5 / 1000) * 'M1 Population'!$C3 -> 22235.906 | O4: Under 1 Year | P4: =B4 -> 29422 | Q4: =-1*P4 -> -29422 | R4: =L4 -> 22235.906
A5: 1 - 4 Years | B5: ='M1 Population'!V76 -> 136128 | C5: =(B4*'M1 Population'!$C$3) + (B5 * 0.8 * 'M1 Population'!$C$4) -> 138254.08 | D5: =(C4*'M1 Population'!$C$3) + (C5 * 0.8 * 'M1 Population'!$C$4) -> 137888.35 | E5: =(D4*'M1 Population'!$C$3) + (D5 * 0.8 * 'M1 Population'!$C$4) -> 136922.56 | F5: =(E4*'M1 Population'!$C$3) + (E5 * 0.8 * 'M1 Population'!$C$4) -> 135506.27 | G5: =(F4*'M1 Population'!$C$3) + (F5 * 0.8 * 'M1 Population'!$C$4) -> 133757.73 | H5: =(G4*'M1 Population'!$C$3) + (G5 * 0.8 * 'M1 Population'!$C$4) -> 131770.21 | I5: =(H4*'M1 Population'!$C$3) + (H5 * 0.8 * 'M1 Population'!$C$4) -> 129617.05 | J5: =(I4*'M1 Population'!$C$3) + (I5 * 0.8 * 'M1 Population'!$C$4) -> 127355.78 | ... L5: =(K4*'M1 Population'!$C$3) + (K5 * 0.8 * 'M1 Population'!$C$4) -> 122678.32 | O5: 1 - 4 Years | P5: =B5 -> 136128 | Q5: =-1*P5 -> -136128 | R5: =L5 -> 122678.32
A6: 5 - 9 Years | B6: ='M1 Population'!V77 -> 199813 | C6: =(B5 * 0.2 * 'M1 Population'!$C$4) +(B6 * 0.8 * 'M1 Population'!$C$5) -> 187057.29 | D6: =(C5 * 0.2 * 'M1 Population'!$C$4) +(C6 * 0.8 * 'M1 Population'!$C$5) -> 177278.92 | E6: =(D5 * 0.2 * 'M1 Population'!$C$4) +(D6 * 0.8 * 'M1 Population'!$C$5) -> 169383.87 | F6: =(E5 * 0.2 * 'M1 Population'!$C$4) +(E6 * 0.8 * 'M1 Population'!$C$5) -> 162875.32 | G6: =(F5 * 0.2 * 'M1 Population'!$C$4) +(F6 * 0.8 * 'M1 Population'!$C$5) -> 157385.77 | H6: =(G5 * 0.2 * 'M1 Population'!$C$4) +(G6 * 0.8 * 'M1 Population'!$C$5) -> 152644.89 | I6: =(H5 * 0.2 * 'M1 Population'!$C$4) +(H6 * 0.8 * 'M1 Population'!$C$5) -> 148455.11 | J6: =(I5 * 0.2 * 'M1 Population'!$C$4) +(I6 * 0.8 * 'M1 Population'!$C$5) -> 144673.03 | ... L6: =(K5 * 0.2 * 'M1 Population'!$C$4) +(K6 * 0.8 * 'M1 Population'!$C$5) -> 137948.82 | O6: 5 - 9 Years | P6: =B6 -> 199813 | Q6: =-1*P6 -> -199813 | R6: =L6 -> 137948.82
A7: 10 - 14 Years | B7: ='M1 Population'!V78 -> 206577 | C7: =(B6 * 0.2 * 'M1 Population'!$C5) + (B7 * 0.8 * 'M1 Population'!$C6) -> 205200.37 | D7: =(C6 * 0.2 * 'M1 Population'!$C5) + (C7 * 0.8 * 'M1 Population'!$C6) -> 201548.32 | E7: =(D6 * 0.2 * 'M1 Population'!$C5) + (D7 * 0.8 * 'M1 Population'!$C6) -> 196671.54 | F7: =(E6 * 0.2 * 'M1 Population'!$C5) + (E7 * 0.8 * 'M1 Population'!$C6) -> 191191.74 | G7: =(F6 * 0.2 * 'M1 Population'!$C5) + (F7 * 0.8 * 'M1 Population'!$C6) -> 185506.84 | H7: =(G6 * 0.2 * 'M1 Population'!$C5) + (G7 * 0.8 * 'M1 Population'!$C6) -> 179861.67 | I7: =(H6 * 0.2 * 'M1 Population'!$C5) + (H7 * 0.8 * 'M1 Population'!$C6) -> 174398 | J7: =(I6 * 0.2 * 'M1 Population'!$C5) + (I7 * 0.8 * 'M1 Population'!$C6) -> 169189.71 | ... L7: =(K6 * 0.2 * 'M1 Population'!$C5) + (K7 * 0.8 * 'M1 Population'!$C6) -> 159634.29 | O7: 10 - 14 Years | P7: =B7 -> 206577 | Q7: =-1*P7 -> -206577 | R7: =L7 -> 159634.29
A8: 15 - 19 Years | B8: ='M1 Population'!V79 -> 211394 | C8: =(B7 * 0.2 * 'M1 Population'!$C6) + (B8 * 0.8 * 'M1 Population'!$C7) -> 210388.44 | D8: =(C7 * 0.2 * 'M1 Population'!$C6) + (C8 * 0.8 * 'M1 Population'!$C7) -> 209308.87 | E8: =(D7 * 0.2 * 'M1 Population'!$C6) + (D8 * 0.8 * 'M1 Population'!$C7) -> 207715.08 | F8: =(E7 * 0.2 * 'M1 Population'!$C6) + (E8 * 0.8 * 'M1 Population'!$C7) -> 205465.1 | G8: =(F7 * 0.2 * 'M1 Population'!$C6) + (F8 * 0.8 * 'M1 Population'!$C7) -> 202569.68 | H8: =(G7 * 0.2 * 'M1 Population'!$C6) + (G8 * 0.8 * 'M1 Population'!$C7) -> 199117 | I8: =(H7 * 0.2 * 'M1 Population'!$C6) + (H8 * 0.8 * 'M1 Population'!$C7) -> 195226.58 | J8: =(I7 * 0.2 * 'M1 Population'!$C6) + (I8 * 0.8 * 'M1 Population'!$C7) -> 191022.31 | ... L8: =(K7 * 0.2 * 'M1 Population'!$C6) + (K8 * 0.8 * 'M1 Population'!$C7) -> 182111.15 | O8: 15 - 19 Years | P8: =B8 -> 211394 | Q8: =-1*P8 -> -211394 | R8: =L8 -> 182111.15
A9: 20 - 24 Years | B9: ='M1 Population'!V80 -> 218686 | C9: =(B8 * 0.2 * 'M1 Population'!$C7) + (B9 * 0.8 * 'M1 Population'!$C8) -> 217176.31 | D9: =(C8 * 0.2 * 'M1 Population'!$C7) + (C9 * 0.8 * 'M1 Population'!$C8) -> 215767.78 | E9: =(D8 * 0.2 * 'M1 Population'!$C7) + (D9 * 0.8 * 'M1 Population'!$C8) -> 214425.36 | F9: =(E8 * 0.2 * 'M1 Population'!$C7) + (E9 * 0.8 * 'M1 Population'!$C8) -> 213033 | G9: =(F8 * 0.2 * 'M1 Population'!$C7) + (F9 * 0.8 * 'M1 Population'!$C8) -> 211469.47 | H9: =(G8 * 0.2 * 'M1 Population'!$C7) + (G9 * 0.8 * 'M1 Population'!$C8) -> 209640 | I9: =(H8 * 0.2 * 'M1 Population'!$C7) + (H9 * 0.8 * 'M1 Population'!$C8) -> 207486.39 | J9: =(I8 * 0.2 * 'M1 Population'!$C7) + (I9 * 0.8 * 'M1 Population'!$C8) -> 204986 | ... L9: =(K8 * 0.2 * 'M1 Population'!$C7) + (K9 * 0.8 * 'M1 Population'!$C8) -> 198993 | O9: 20 - 24 Years | P9: =B9 -> 218686 | Q9: =-1*P9 -> -218686 | R9: =L9 -> 198993
A10: 25 - 29 Years | B10: ='M1 Population'!V81 -> 263735 | C10: =(B9 * 0.2 * 'M1 Population'!$C8) + (B10 * 0.8 * 'M1 Population'!$C9) -> 254651.41 | D10: =(C9 * 0.2 * 'M1 Population'!$C8) + (C10 * 0.8 * 'M1 Population'!$C9) -> 247084.85 | E10: =(D9 * 0.2 * 'M1 Population'!$C8) + (D10 * 0.8 * 'M1 Population'!$C9) -> 240751.78 | F10: =(E9 * 0.2 * 'M1 Population'!$C8) + (E10 * 0.8 * 'M1 Population'!$C9) -> 235418.42 | G10: =(F9 * 0.2 * 'M1 Population'!$C8) + (F10 * 0.8 * 'M1 Population'!$C9) -> 230874.61 | H10: =(G9 * 0.2 * 'M1 Population'!$C8) + (G10 * 0.8 * 'M1 Population'!$C9) -> 226928.02 | I10: =(H9 * 0.2 * 'M1 Population'!$C8) + (H10 * 0.8 * 'M1 Population'!$C9) -> 223405.89 | J10: =(I9 * 0.2 * 'M1 Population'!$C8) + (I10 * 0.8 * 'M1 Population'!$C9) -> 220158.41 | ... L10: =(K9 * 0.2 * 'M1 Population'!$C8) + (K10 * 0.8 * 'M1 Population'!$C9) -> 214016.31 | O10: 25 - 29 Years | P10: =B10 -> 263735 | Q10: =-1*P10 -> -263735 | R10: =L10 -> 214016.31
A11: 30 - 34 Years | B11: ='M1 Population'!V82 -> 319836 | C11: =(B10 * 0.2 * 'M1 Population'!$C9) + (B11 * 0.8 * 'M1 Population'!$C10) -> 308507.86 | D11: =(C10 * 0.2 * 'M1 Population'!$C9) + (C11 * 0.8 * 'M1 Population'!$C10) -> 297632.44 | E11: =(D10 * 0.2 * 'M1 Population'!$C9) + (D11 * 0.8 * 'M1 Population'!$C10) -> 287422.38 | F11: =(E10 * 0.2 * 'M1 Population'!$C9) + (E11 * 0.8 * 'M1 Population'!$C10) -> 277991.04 | G11: =(F10 * 0.2 * 'M1 Population'!$C9) + (F11 * 0.8 * 'M1 Population'!$C10) -> 269382.33 | H11: =(G10 * 0.2 * 'M1 Population'!$C9) + (G11 * 0.8 * 'M1 Population'!$C10) -> 261589.35 | I11: =(H10 * 0.2 * 'M1 Population'!$C9) + (H11 * 0.8 * 'M1 Population'!$C10) -> 254568.13 | J11: =(I10 * 0.2 * 'M1 Population'!$C9) + (I11 * 0.8 * 'M1 Population'!$C10) -> 248248.96 | ... L11: =(K10 * 0.2 * 'M1 Population'!$C9) + (K11 * 0.8 * 'M1 Population'!$C10) -> 237366.29 | O11: 30 - 34 Years | P11: =B11 -> 319836 | Q11: =-1*P11 -> -319836 | R11: =L11 -> 237366.29
A12: 35 - 39 Years | B12: ='M1 Population'!V83 -> 320125 | C12: =(B11 * 0.2 * 'M1 Population'!$C10) + (B12 * 0.8 * 'M1 Population'!$C11) -> 319911 | D12: =(C11 * 0.2 * 'M1 Population'!$C10) + (C12 * 0.8 * 'M1 Population'!$C11) -> 317475.08 | E12: =(D11 * 0.2 * 'M1 Population'!$C10) + (D12 * 0.8 * 'M1 Population'!$C11) -> 313353.05 | F12: =(E11 * 0.2 * 'M1 Population'!$C10) + (E12 * 0.8 * 'M1 Population'!$C11) -> 308015.87 | G12: =(F11 * 0.2 * 'M1 Population'!$C10) + (F12 * 0.8 * 'M1 Population'!$C11) -> 301862.75 | H12: =(G11 * 0.2 * 'M1 Population'!$C10) + (G12 * 0.8 * 'M1 Population'!$C11) -> 295221.7 | I12: =(H11 * 0.2 * 'M1 Population'!$C10) + (H12 * 0.8 * 'M1 Population'!$C11) -> 288353.58 | J12: =(I11 * 0.2 * 'M1 Population'!$C10) + (I12 * 0.8 * 'M1 Population'!$C11) -> 281458.21 | ... L12: =(K11 * 0.2 * 'M1 Population'!$C10) + (K12 * 0.8 * 'M1 Population'!$C11) -> 268122.62 | O12: 35 - 39 Years | P12: =B12 -> 320125 | Q12: =-1*P12 -> -320125 | R12: =L12 -> 268122.62
A13: 40 - 44 Years | B13: ='M1 Population'!V84 -> 311772 | C13: =(B12 * 0.2 * 'M1 Population'!$C11) + (B13 * 0.8 * 'M1 Population'!$C12) -> 313209.77 | D13: =(C12 * 0.2 * 'M1 Population'!$C11) + (C13 * 0.8 * 'M1 Population'!$C12) -> 314316.29 | E13: =(D12 * 0.2 * 'M1 Population'!$C11) + (D13 * 0.8 * 'M1 Population'!$C12) -> 314713.87 | F13: =(E12 * 0.2 * 'M1 Population'!$C11) + (E13 * 0.8 * 'M1 Population'!$C12) -> 314207.7 | G13: =(F12 * 0.2 * 'M1 Population'!$C11) + (F13 * 0.8 * 'M1 Population'!$C12) -> 312736.21 | H13: =(G12 * 0.2 * 'M1 Population'!$C11) + (G13 * 0.8 * 'M1 Population'!$C12) -> 310329.97 | I13: =(H12 * 0.2 * 'M1 Population'!$C11) + (H13 * 0.8 * 'M1 Population'!$C12) -> 307079 | J13: =(I12 * 0.2 * 'M1 Population'!$C11) + (I13 * 0.8 * 'M1 Population'!$C12) -> 303107.4 | ... L13: =(K12 * 0.2 * 'M1 Population'!$C11) + (K13 * 0.8 * 'M1 Population'!$C12) -> 293560.08 | O13: 40 - 44 Years | P13: =B13 -> 311772 | Q13: =-1*P13 -> -311772 | R13: =L13 -> 293560.08
A14: 45 - 49 Years | B14: ='M1 Population'!V85 -> 302015 | C14: =(B13 * 0.2 * 'M1 Population'!$C12) + (B14 * 0.8 * 'M1 Population'!$C13) -> 303592.76 | D14: =(C13 * 0.2 * 'M1 Population'!$C12) + (C14 * 0.8 * 'M1 Population'!$C13) -> 305140.59 | E14: =(D13 * 0.2 * 'M1 Population'!$C12) + (D14 * 0.8 * 'M1 Population'!$C13) -> 306598.33 | F14: =(E13 * 0.2 * 'M1 Population'!$C12) + (E14 * 0.8 * 'M1 Population'!$C13) -> 307842.41 | G14: =(F13 * 0.2 * 'M1 Population'!$C12) + (F14 * 0.8 * 'M1 Population'!$C13) -> 308735.19 | H14: =(G13 * 0.2 * 'M1 Population'!$C12) + (G14 * 0.8 * 'M1 Population'!$C13) -> 309154.39 | I14: =(H13 * 0.2 * 'M1 Population'!$C12) + (H14 * 0.8 * 'M1 Population'!$C13) -> 309008.44 | J14: =(I13 * 0.2 * 'M1 Population'!$C12) + (I14 * 0.8 * 'M1 Population'!$C13) -> 308242.16 | ... L14: =(K13 * 0.2 * 'M1 Population'!$C12) + (K14 * 0.8 * 'M1 Population'!$C13) -> 304803.19 | O14: 45 - 49 Years | P14: =B14 -> 302015 | Q14: =-1*P14 -> -302015 | R14: =L14 -> 304803.19
A15: 50 - 54 Years | B15: ='M1 Population'!V86 -> 308978 | C15: =(B14 * 0.2 * 'M1 Population'!$C13) + (B15 * 0.8 * 'M1 Population'!$C14) -> 306955.72 | D15: =(C14 * 0.2 * 'M1 Population'!$C13) + (C15 * 0.8 * 'M1 Population'!$C14) -> 305656.61 | E15: =(D14 * 0.2 * 'M1 Population'!$C13) + (D15 * 0.8 * 'M1 Population'!$C14) -> 304928.78 | F15: =(E14 * 0.2 * 'M1 Population'!$C13) + (E15 * 0.8 * 'M1 Population'!$C14) -> 304638.97 | G15: =(F14 * 0.2 * 'M1 Population'!$C13) + (F15 * 0.8 * 'M1 Population'!$C14) -> 304656.12 | H15: =(G14 * 0.2 * 'M1 Population'!$C13) + (G15 * 0.8 * 'M1 Population'!$C14) -> 304848.12 | I15: =(H14 * 0.2 * 'M1 Population'!$C13) + (H15 * 0.8 * 'M1 Population'!$C14) -> 305085.11 | J15: =(I14 * 0.2 * 'M1 Population'!$C13) + (I15 * 0.8 * 'M1 Population'!$C14) -> 305245.13 | ... L15: =(K14 * 0.2 * 'M1 Population'!$C13) + (K15 * 0.8 * 'M1 Population'!$C14) -> 304918.8 | O15: 50 - 54 Years | P15: =B15 -> 308978 | Q15: =-1*P15 -> -308978 | R15: =L15 -> 304918.8
A16: 55 - 59 Years | B16: ='M1 Population'!V87 -> 289783 | C16: =(B15 * 0.2 * 'M1 Population'!$C14) + (B16 * 0.8 * 'M1 Population'!$C15) -> 292654.88 | D16: =(C15 * 0.2 * 'M1 Population'!$C14) + (C16 * 0.8 * 'M1 Population'!$C15) -> 294540.59 | E16: =(D15 * 0.2 * 'M1 Population'!$C14) + (D16 * 0.8 * 'M1 Population'!$C15) -> 295784.52 | F16: =(E15 * 0.2 * 'M1 Population'!$C14) + (E16 * 0.8 * 'M1 Population'!$C15) -> 296630.86 | G16: =(F15 * 0.2 * 'M1 Population'!$C14) + (F16 * 0.8 * 'M1 Population'!$C15) -> 297247.67 | H16: =(G15 * 0.2 * 'M1 Population'!$C14) + (G16 * 0.8 * 'M1 Population'!$C15) -> 297742.77 | I16: =(H15 * 0.2 * 'M1 Population'!$C14) + (H16 * 0.8 * 'M1 Population'!$C15) -> 298175.76 | J16: =(I15 * 0.2 * 'M1 Population'!$C14) + (I16 * 0.8 * 'M1 Population'!$C15) -> 298568.19 | ... L16: =(K15 * 0.2 * 'M1 Population'!$C14) + (K16 * 0.8 * 'M1 Population'!$C15) -> 299182.72 | O16: 55 - 59 Years | P16: =B16 -> 289783 | Q16: =-1*P16 -> -289783 | R16: =L16 -> 299182.72
A17: 60 - 64 Years | B17: ='M1 Population'!V88 -> 296675 | C17: =(B16 * 0.2 * 'M1 Population'!$C15) + (B17 * 0.8 * 'M1 Population'!$C16) -> 293674.57 | D17: =(C16 * 0.2 * 'M1 Population'!$C15) + (C17 * 0.8 * 'M1 Population'!$C16) -> 291860.85 | E17: =(D16 * 0.2 * 'M1 Population'!$C15) + (D17 * 0.8 * 'M1 Population'!$C16) -> 290794.31 | F17: =(E16 * 0.2 * 'M1 Population'!$C15) + (E17 * 0.8 * 'M1 Population'!$C16) -> 290194.07 | G17: =(F16 * 0.2 * 'M1 Population'!$C15) + (F17 * 0.8 * 'M1 Population'!$C16) -> 289885.39 | H17: =(G16 * 0.2 * 'M1 Population'!$C15) + (G17 * 0.8 * 'M1 Population'!$C16) -> 289762.84 | I17: =(H16 * 0.2 * 'M1 Population'!$C15) + (H17 * 0.8 * 'M1 Population'!$C16) -> 289764.06 | J17: =(I16 * 0.2 * 'M1 Population'!$C15) + (I17 * 0.8 * 'M1 Population'!$C16) -> 289851.31 | ... L17: =(K16 * 0.2 * 'M1 Population'!$C15) + (K17 * 0.8 * 'M1 Population'!$C16) -> 290184.97 | O17: 60 - 64 Years | P17: =B17 -> 296675 | Q17: =-1*P17 -> -296675 | R17: =L17 -> 290184.97
A18: 65 - 69 Years | B18: ='M1 Population'!V89 -> 272419 | C18: =(B17 * 0.2 * 'M1 Population'!$C16) + (B18 * 0.8 * 'M1 Population'!$C17) -> 274820.03 | D18: =(C17 * 0.2 * 'M1 Population'!$C16) + (C18 * 0.8 * 'M1 Population'!$C17) -> 276125.86 | E18: =(D17 * 0.2 * 'M1 Population'!$C16) + (D18 * 0.8 * 'M1 Population'!$C17) -> 276799.9 | F18: =(E17 * 0.2 * 'M1 Population'!$C16) + (E18 * 0.8 * 'M1 Population'!$C17) -> 277121.9 | G18: =(F17 * 0.2 * 'M1 Population'!$C16) + (F18 * 0.8 * 'M1 Population'!$C17) -> 277257.69 | H18: =(G17 * 0.2 * 'M1 Population'!$C16) + (G18 * 0.8 * 'M1 Population'!$C17) -> 277303.91 | I18: =(H17 * 0.2 * 'M1 Population'!$C16) + (H18 * 0.8 * 'M1 Population'!$C17) -> 277316.17 | J18: =(I17 * 0.2 * 'M1 Population'!$C16) + (I18 * 0.8 * 'M1 Population'!$C17) -> 277326.12 | ... L18: =(K17 * 0.2 * 'M1 Population'!$C16) + (K18 * 0.8 * 'M1 Population'!$C17) -> 277400.69 | O18: 65 - 69 Years | P18: =B18 -> 272419 | Q18: =-1*P18 -> -272419 | R18: =L18 -> 277400.69
... A22: 85 - 89 Years | B22: ='M1 Population'!V93 -> 47550 | C22: =(B21 * 0.2 * 'M1 Population'!$C20) + (B22 * 0.8 * 'M1 Population'!$C21) -> 48758.323 | D22: =(C21 * 0.2 * 'M1 Population'!$C20) + (C22 * 0.8 * 'M1 Population'!$C21) -> 51877.426 | E22: =(D21 * 0.2 * 'M1 Population'!$C20) + (D22 * 0.8 * 'M1 Population'!$C21) -> 56159.035 | F22: =(E21 * 0.2 * 'M1 Population'!$C20) + (E22 * 0.8 * 'M1 Population'!$C21) -> 61105.794 | G22: =(F21 * 0.2 * 'M1 Population'!$C20) + (F22 * 0.8 * 'M1 Population'!$C21) -> 66383.752 | H22: =(G21 * 0.2 * 'M1 Population'!$C20) + (G22 * 0.8 * 'M1 Population'!$C21) -> 71765.485 | I22: =(H21 * 0.2 * 'M1 Population'!$C20) + (H22 * 0.8 * 'M1 Population'!$C21) -> 77093.963 | J22: =(I21 * 0.2 * 'M1 Population'!$C20) + (I22 * 0.8 * 'M1 Population'!$C21) -> 82259.921 | ... L22: =(K21 * 0.2 * 'M1 Population'!$C20) + (K22 * 0.8 * 'M1 Population'!$C21) -> 91826.448 | O22: 85 - 89 Years | P22: =B22 -> 47550 | Q22: =-1*P22 -> -47550 | R22: =L22 -> 91826.448
A23: 90 Years & Over | B23: ='M1 Population'!V94 -> 27360 | C23: =(B22*0.2*'M1 Population'!$C$21) + (B23*'M1 Population'!$C$22) -> 31383.135 | D23: =(C22*0.2*'M1 Population'!$C$21) + (C23*'M1 Population'!$C$22) -> 34947.425 | E23: =(D22*0.2*'M1 Population'!$C$21) + (D23*'M1 Population'!$C$22) -> 38477.267 | F23: =(E22*0.2*'M1 Population'!$C$21) + (E23*'M1 Population'!$C$22) -> 42189.604 | G23: =(F22*0.2*'M1 Population'!$C$21) + (F23*'M1 Population'!$C$22) -> 46174.471 | H23: =(G22*0.2*'M1 Population'!$C$21) + (G23*'M1 Population'!$C$22) -> 50446.072 | I23: =(H22*0.2*'M1 Population'!$C$21) + (H23*'M1 Population'!$C$22) -> 54974.912 | J23: =(I22*0.2*'M1 Population'!$C$21) + (I23*'M1 Population'!$C$22) -> 59707.947 | ... L23: =(K22*0.2*'M1 Population'!$C$21) + (K23*'M1 Population'!$C$22) -> 69527.874 | O23: 90 Years & Over | P23: =B23 -> 27360 | Q23: =-1*P23 -> -27360 | R23: =L23 -> 69527.874
A24: TOTAL | B24: =SUM(B4:B23) -> 4204515 | C24: =SUM(C4:C23) -> 4204434.4 | D24: =SUM(D4:D23) -> 4201945 | E24: =SUM(E4:E23) -> 4197066.8 | F24: =SUM(F4:F23) -> 4189808.3 | G24: =SUM(G4:G23) -> 4180178.9 | H24: =SUM(H4:H23) -> 4168197.6 | I24: =SUM(I4:I23) -> 4153896.3 | ... L24: =SUM(L4:L23) -> 4097610.2
A27: Group | B27: 2005 | C27: 2006 | D27: 2007 | E27: 2008 | F27: 2009 | G27: 2010 | H27: 2011 | I27: 2012 | J27: 2013 | K27: 2014 | L27: 2015 | M27: 2016 | N27: 2017 | O27: 2018 | P27: 2019 | Q27: 2020 | R27: 2021 | S27: 2022 | T27: 2023 | U27: 2024 | V27: 2025 | W27: 2026 | X27: 2027 | Y27: 2028 | Z27: 2029 | AA27: 2030 | AB27: 2031 | AC27: 2032 | AD27: 2033 | AE27: 2034 | AF27: 2035
A28: Working age (15-64) | B28: =SUM('M1 Population'!B79:B88) -> 2492802 | C28: =SUM('M1 Population'!C79:C88) -> 2545003 | D28: =SUM('M1 Population'!D79:D88) -> 2599037 | E28: =SUM('M1 Population'!E79:E88) -> 2655562 | F28: =SUM('M1 Population'!F79:F88) -> 2735893 | G28: =SUM('M1 Population'!G79:G88) -> 2778925 | H28: =SUM('M1 Population'!H79:H88) -> 2799702 | I28: =SUM('M1 Population'!I79:I88) -> 2813252 | ... U28: =SUM('M1 Population'!U79:U88) -> 2849994 | V28: =SUM(B8:B17) -> 2842999 | W28: =SUM(C8:C17) -> 2820722.7 | X28: =SUM(D8:D17) -> 2798784 | Y28: =SUM(E8:E17) -> 2776487.5 | Z28: =SUM(F8:F17) -> 2753437.4 | AA28: =SUM(G8:G17) -> 2729419.4 | AB28: =SUM(H8:H17) -> 2704334.2 | AC28: =SUM(I8:I17) -> 2678152.9 | ... AF28: =SUM(L8:L17) -> 2593259.1
A29: Seniors (65+) | B29: =SUM('M1 Population'!B89:B94) -> 279693 | C29: =SUM('M1 Population'!C89:C94) -> 294726 | D29: =SUM('M1 Population'!D89:D94) -> 305586 | E29: =SUM('M1 Population'!E89:E94) -> 315790 | F29: =SUM('M1 Population'!F89:F94) -> 330132 | G29: =SUM('M1 Population'!G89:G94) -> 338387 | H29: =SUM('M1 Population'!H89:H94) -> 352645 | I29: =SUM('M1 Population'!I89:I94) -> 378636 | ... U29: =SUM('M1 Population'!U89:U94) -> 753905 | V29: =SUM(B18:B23) -> 789576 | W29: =SUM(C18:C23) -> 825848.54 | X29: =SUM(D18:D23) -> 859768.62 | Y29: =SUM(E18:E23) -> 891569.58 | Z29: =SUM(F18:F23) -> 921382.63 | AA29: =SUM(G18:G23) -> 949284.3 | AB29: =SUM(H18:H23) -> 975326.17 | AC29: =SUM(I18:I23) -> 999552.82 | ... AF29: =SUM(L18:L23) -> 1061853.8
A30: Dependency ratio | B30: =(B29/B28)*100 -> 11.220025 | C30: =(C29/C28)*100 -> 11.580576 | D30: =(D29/D28)*100 -> 11.757663 | E30: =(E29/E28)*100 -> 11.891645 | F30: =(F29/F28)*100 -> 12.0667 | G30: =(G29/G28)*100 -> 12.176903 | H30: =(H29/H28)*100 -> 12.595805 | I30: =(I29/I28)*100 -> 13.459015 | ... AF30: =(AF29/AF28)*100 -> 40.94669
B32: Actual | C32: Projected
A33: 2005 | B33: ='M1 Population'!B95 -> 3467814
A34: 2006 | B34: ='M1 Population'!C95 -> 3525894
A35: 2007 | B35: ='M1 Population'!D95 -> 3583082
A36: 2008 | B36: ='M1 Population'!E95 -> 3642659
A37: 2009 | B37: ='M1 Population'!F95 -> 3733876
A38: 2010 | B38: ='M1 Population'!G95 -> 3771721
A39: 2011 | B39: ='M1 Population'!H95 -> 3789251
A40: 2012 | B40: ='M1 Population'!I95 -> 3818205
A41: 2013 | B41: ='M1 Population'!J95 -> 3844751
A42: 2014 | B42: ='M1 Population'!K95 -> 3870739
A43: 2015 | B43: ='M1 Population'!L95 -> 3902690
A44: 2016 | B44: ='M1 Population'!M95 -> 3933559
A45: 2017 | B45: ='M1 Population'!N95 -> 3965796
A46: 2018 | B46: ='M1 Population'!O95 -> 3994283
A47: 2019 | B47: ='M1 Population'!P95 -> 4026209
A48: 2020 | B48: ='M1 Population'!Q95 -> 4044210
A49: 2021 | B49: ='M1 Population'!R95 -> 3986842
A50: 2022 | B50: ='M1 Population'!S95 -> 4073239
A51: 2023 | B51: ='M1 Population'!T95 -> 4149253
A52: 2024 | B52: ='M1 Population'!U95 -> 4180868
A53: 2025 | B53: ='M1 Population'!V95 -> 4204515 | C53: =B24 -> 4204515
A54: 2026 | C54: =C24 -> 4204434.4
A55: 2027 | C55: =D24 -> 4201945
A56: 2028 | C56: =E24 -> 4197066.8
A57: 2029 | C57: =F24 -> 4189808.3
A58: 2030 | C58: =G24 -> 4180178.9
A59: 2031 | C59: =H24 -> 4168197.6
A60: 2032 | C60: =I24 -> 4153896.3
A61: 2033 | C61: =J24 -> 4137322
A62: 2034 | C62: =K24 -> 4118535.3
A63: 2035 | C63: =L24 -> 4097610.2

Sheet M2 HAR
A1: Hospital Admission Rate | B1: 2024 | C1: 2023 | D1: 2022 | E1: 2021 | F1: 2020 | G1: 2019 | H1: 2018 | I1: 2017 | J1: 2016 | K1: 2015 | L1: 2014 | M1: 2013 | N1: 2012 | O1: 2011 | P1: 2010 | Q1: 2009 | R1: 2008 | S1: 2007 | T1: 2006
A2: Acute Hospitals - Male | B2: 138.6 | C2: 137.5 | D2: 133.9 | E2: 128.2 | F2: 121.8 | G2: 136.8 | H2: 130 | I2: 127.4 | J2: 123.7 | K2: 110.5 | L2: 108.2 | M2: 104.5 | N2: 100.7 | O2: 96.9 | P2: 93.2 | Q2: 90.2 | R2: 90.6 | S2: 91 | T2: 90.2
A3: 0 - 14 Years Old | B3: 135.4 | C3: 139.5 | D3: 140.4 | E3: 119.7 | F3: 110.9 | G3: 148.4 | H3: 145.4 | I3: 142.7 | J3: 142.1 | K3: 128.5 | L3: 126.6 | M3: 120.2 | N3: 118.5 | O3: 111.6 | P3: 104.3 | Q3: 100.1 | R3: 99.2 | S3: 95 | T3: 92.5
A4: 15 - 64 Years Old | B4: 82.4 | C4: 81.1 | D4: 78.7 | E4: 82.7 | F4: 80.3 | G4: 88.8 | H4: 84.3 | I4: 83.8 | J4: 81.5 | K4: 71.5 | L4: 71 | M4: 70 | N4: 66.7 | O4: 65.4 | P4: 63.8 | Q4: 62.7 | R4: 62.6 | S4: 63.9 | T4: 64
A5: 65 Years Old & Above | B5: 366 | C5: 373.4 | D5: 371.8 | E5: 348.4 | F5: 338.4 | G5: 376.5 | H5: 368.2 | I5: 369.1 | J5: 366.7 | K5: 347.6 | L5: 347.7 | M5: 343.7 | N5: 347.6 | O5: 345.2 | P5: 339.6 | Q5: 323 | R5: 333.2 | S5: 340.4 | T5: 337.9
A6: Acute Hospitals - Female | B6: 132.1 | C6: 131.5 | D6: 129.4 | E6: 126.2 | F6: 117.4 | G6: 135.6 | H6: 129.6 | I6: 127.4 | J6: 123.4 | K6: 111.9 | L6: 111 | M6: 107.7 | N6: 105.5 | O6: 102.7 | P6: 98.3 | Q6: 96.4 | R6: 98.1 | S6: 99.4 | T6: 98.3
A7: 0 - 14 Years Old | B7: 119.5 | C7: 121.8 | D7: 123.4 | E7: 109.4 | F7: 98 | G7: 131.8 | H7: 127 | I7: 124.3 | J7: 121.5 | K7: 112 | L7: 109.4 | M7: 102 | N7: 101.2 | O7: 95.6 | P7: 88 | Q7: 84.9 | R7: 86.6 | S7: 83.2 | T7: 81.4
A8: 15 - 64 Years Old | B8: 86.4 | C8: 86.5 | D8: 86.1 | E8: 90.3 | F8: 85.2 | G8: 96.5 | H8: 92.3 | I8: 90.6 | J8: 88.6 | K8: 80.1 | L8: 80 | M8: 78.3 | N8: 77.2 | O8: 75.7 | P8: 74.2 | Q8: 73.5 | R8: 75 | S8: 77.3 | T8: 77.4
A9: 65 Years Old & Above | B9: 305.3 | C9: 307.7 | D9: 303.7 | E9: 286 | F9: 274.6 | G9: 318.9 | H9: 313.8 | I9: 319.8 | J9: 314.1 | K9: 292.9 | L9: 299.9 | M9: 302.6 | N9: 304 | O9: 308 | P9: 295.3 | Q9: 287.7 | R9: 294.8 | S9: 299.8 | T9: 295.7
A10: Psychiatric Hospitals - Male | B10: 2.6 | C10: 2.7 | D10: 2.5 | E10: 2.2 | F10: 2.4 | G10: 2.6 | H10: 2.7 | I10: 2.7 | J10: 2.7 | K10: 2.6 | L10: 2.4 | M10: 2.2 | N10: 2.3 | O10: 2.8 | P10: 2.8 | Q10: 2.7 | R10: 2.6 | S10: 2.5 | T10: 2.5
A11: 0 - 14 Years Old | B11: 0.1 | C11: 0.2 | D11: 0.1 | E11: 0.2 | F11: 0.1 | G11: 0.1 | H11: 0.1 | I11: 0.2 | J11: 0.2 | K11: 0.1 | L11: 0.2 | M11: 0.2 | N11: 0.1 | O11: 0.1 | P11: 0.2 | Q11: 0.1 | R11: 0.1 | S11: 0.1 | T11: 0.1
A12: 15 - 64 Years Old | B12: 3 | C12: 3.2 | D12: 3 | E12: 2.7 | F12: 2.9 | G12: 3.2 | H12: 3.3 | I12: 3.3 | J12: 3.3 | K12: 3.2 | L12: 3 | M12: 2.7 | N12: 2.8 | O12: 3.5 | P12: 3.5 | Q12: 3.3 | R12: 3.3 | S12: 3.1 | T12: 3.2
... A18: Community Hospitals - Male | B18: 5.6 | C18: 4.6 | D18: 5.2 | E18: 5 | F18: 4.4 | G18: 4.5 | H18: 4.1 | I18: 3.7 | J18: 3.1 | K18: 2.2 | L18: 1.9 | M18: 1.8 | N18: 1.6 | O18: 1.7 | P18: 1.7 | Q18: 1.5 | R18: 1.4 | S18: 1.3 | T18: 1.2
A19: 0 - 14 Years Old | B19: 0 | C19: 0.1 | D19: 0 | E19: 0 | F19: 0 | G19: 0 | H19: 0.1 | I19: 0.1 | J19: 0.1 | K19: 0 | L19: 0 | M19: 0 | N19: 0 | O19: - | P19: - | Q19: - | R19: 0.1 | S19: - | T19: 0
A20: 15 - 64 Years Old | B20: 1.4 | C20: 1.3 | D20: 1.4 | E20: 1.8 | F20: 1.5 | G20: 1.5 | H20: 1.3 | I20: 1.2 | J20: 1.1 | K20: 0.7 | L20: 0.6 | M20: 0.6 | N20: 0.6 | O20: 0.6 | P20: 0.7 | Q20: 0.6 | R20: 0.5 | S20: 0.5 | T20: 0.5
A21: 65 Years Old & Above | B21: 27 | C21: 22.5 | D21: 26.7 | E21: 25 | F21: 23.4 | G21: 25.6 | H21: 24.1 | I21: 23.4 | J21: 20.3 | K21: 15.6 | L21: 14.4 | M21: 13.9 | N21: 13 | O21: 14.9 | P21: 14.9 | Q21: 13.6 | R21: 13.5 | S21: 12.8 | T21: 12.2
A22: Community Hospitals - Female | B22: 6.6 | C22: 5.2 | D22: 5.2 | E22: 5.1 | F22: 4.4 | G22: 5.1 | H22: 4.6 | I22: 4.3 | J22: 3.7 | K22: 2.7 | L22: 2.4 | M22: 2.3 | N22: 2.1 | O22: 2.1 | P22: 2 | Q22: 1.9 | R22: 1.9 | S22: 1.6 | T22: 1.6
A23: 0 - 14 Years Old | B23: 0 | C23: 0.1 | D23: 0.1 | E23: 0 | F23: 0 | G23: 0 | H23: 0 | I23: 0 | J23: 0 | K23: 0 | L23: 0 | M23: 0 | N23: 0 | O23: - | P23: - | Q23: - | R23: - | S23: - | T23: 0
A24: 15 - 64 Years Old | B24: 1.2 | C24: 1 | D24: 1 | E24: 1.3 | F24: 1.1 | G24: 1.1 | H24: 1 | I24: 0.9 | J24: 0.8 | K24: 0.6 | L24: 0.5 | M24: 0.5 | N24: 0.5 | O24: 0.5 | P24: 0.4 | Q24: 0.4 | R24: 0.4 | S24: 0.4 | T24: 0.4
A25: 65 Years Old & Above | B25: 30.4 | C25: 24.8 | D25: 25.5 | E25: 24.8 | F25: 23 | G25: 27.9 | H25: 26.7 | I25: 26.2 | J25: 23.3 | K25: 18 | L25: 16.7 | M25: 16.8 | N25: 16 | O25: 17.5 | P25: 16.9 | Q25: 16.4 | R25: 16.4 | S25: 14.4 | T25: 14.1
D27: =_xlfn.FORMULATEXT(B33) -> =MAX(0,FORECAST.LINEAR(B31, $B$3:$T$3, $B$1:$T$1))
A28: Projected Admissions | D28: =_xlfn.FORMULATEXT(B35) -> =MAX(0,FORECAST.LINEAR(B31, $B$5:$T$5, $B$1:$T$1)*(1+$B$29)^(B31-$B$1))
A29: Government Policy Factor(r) | B29: ='M2 BOR & Tradeoff analysis'!B12 -> -0.006 | D29: Adjusted Rate_year ​ =Linear Forecast Rate×(1−r)^(Year−2024)
B30: -0.6 to 0
A31: Hospital Admission Rate | B31: 2035 | C31: =B31-1 -> 2034 | D31: =C31-1 -> 2033 | E31: =D31-1 -> 2032 | F31: =E31-1 -> 2031 | G31: =F31-1 -> 2030 | H31: =G31-1 -> 2029 | I31: =H31-1 -> 2028 | J31: =I31-1 -> 2027 | ... L31: =K31-1 -> 2025 | M31: 2024 | N31: 2023 | O31: 2022 | P31: 2021 | Q31: 2020 | R31: 2019 | S31: 2018 | T31: 2017 | U31: 2016 | V31: 2015 | W31: 2014 | X31: 2013 | Y31: 2012 | Z31: 2011 | AA31: 2010 | AB31: 2009 | AC31: 2008 | AD31: 2007 | AE31: 2006
A32: Acute Hospitals - Male - Projected
A33: 0 - 14 Years Old | B33: =MAX(0,_xlfn.FORECAST.LINEAR(B31, $B$3:$T$3, $B$1:$T$1)) -> 173.7193 | C33: =MAX(0,_xlfn.FORECAST.LINEAR(C31, $B$3:$T$3, $B$1:$T$1)) -> 171.14123 | D33: =MAX(0,_xlfn.FORECAST.LINEAR(D31, $B$3:$T$3, $B$1:$T$1)) -> 168.56316 | E33: =MAX(0,_xlfn.FORECAST.LINEAR(E31, $B$3:$T$3, $B$1:$T$1)) -> 165.98509 | F33: =MAX(0,_xlfn.FORECAST.LINEAR(F31, $B$3:$T$3, $B$1:$T$1)) -> 163.40702 | G33: =MAX(0,_xlfn.FORECAST.LINEAR(G31, $B$3:$T$3, $B$1:$T$1)) -> 160.82895 | H33: =MAX(0,_xlfn.FORECAST.LINEAR(H31, $B$3:$T$3, $B$1:$T$1)) -> 158.25088 | I33: =MAX(0,_xlfn.FORECAST.LINEAR(I31, $B$3:$T$3, $B$1:$T$1)) -> 155.67281 | ... L33: =MAX(0,_xlfn.FORECAST.LINEAR(L31, $B$3:$T$3, $B$1:$T$1)) -> 147.9386
A34: 15 - 64 Years Old | B34: =(SUM('M1 Demand Driver'!L8:L16)/SUM('M1 Demand Driver'!L8:L17)*MAX(0,_xlfn.FORECAST.LINEAR(B31,$B$4:$T$4,$B$1:$T$1)))+('M1 Demand Driver'!L17/SUM('M1 Demand Driver'!L8:L17)*MAX(0,_xlfn.FORECAST.LINEAR(B31,$B$4:$T$4,$B$1:$T$1)*(1+$B$29)^(B31-$B$1))) -> 101.39778 | C34: =(SUM('M1 Demand Driver'!K8:K16)/SUM('M1 Demand Driver'!K8:K17)*MAX(0,_xlfn.FORECAST.LINEAR(C31,$B$4:$T$4,$B$1:$T$1)))+('M1 Demand Driver'!K17/SUM('M1 Demand Driver'!K8:K17)*MAX(0,_xlfn.FORECAST.LINEAR(C31,$B$4:$T$4,$B$1:$T$1)*(1+$B$29)^(C31-$B$1))) -> 100.07073 | D34: =(SUM('M1 Demand Driver'!J8:J16)/SUM('M1 Demand Driver'!J8:J17)*MAX(0,_xlfn.FORECAST.LINEAR(D31,$B$4:$T$4,$B$1:$T$1)))+('M1 Demand Driver'!J17/SUM('M1 Demand Driver'!J8:J17)*MAX(0,_xlfn.FORECAST.LINEAR(D31,$B$4:$T$4,$B$1:$T$1)*(1+$B$29)^(D31-$B$1))) -> 98.740126 | E34: =(SUM('M1 Demand Driver'!I8:I16)/SUM('M1 Demand Driver'!I8:I17)*MAX(0,_xlfn.FORECAST.LINEAR(E31,$B$4:$T$4,$B$1:$T$1)))+('M1 Demand Driver'!I17/SUM('M1 Demand Driver'!I8:I17)*MAX(0,_xlfn.FORECAST.LINEAR(E31,$B$4:$T$4,$B$1:$T$1)*(1+$B$29)^(E31-$B$1))) -> 97.406132 | F34: =(SUM('M1 Demand Driver'!H8:H16)/SUM('M1 Demand Driver'!H8:H17)*MAX(0,_xlfn.FORECAST.LINEAR(F31,$B$4:$T$4,$B$1:$T$1)))+('M1 Demand Driver'!H17/SUM('M1 Demand Driver'!H8:H17)*MAX(0,_xlfn.FORECAST.LINEAR(F31,$B$4:$T$4,$B$1:$T$1)*(1+$B$29)^(F31-$B$1))) -> 96.068929 | G34: =(SUM('M1 Demand Driver'!G8:G16)/SUM('M1 Demand Driver'!G8:G17)*MAX(0,_xlfn.FORECAST.LINEAR(G31,$B$4:$T$4,$B$1:$T$1)))+('M1 Demand Driver'!G17/SUM('M1 Demand Driver'!G8:G17)*MAX(0,_xlfn.FORECAST.LINEAR(G31,$B$4:$T$4,$B$1:$T$1)*(1+$B$29)^(G31-$B$1))) -> 94.72869 | H34: =(SUM('M1 Demand Driver'!F8:F16)/SUM('M1 Demand Driver'!F8:F17)*MAX(0,_xlfn.FORECAST.LINEAR(H31,$B$4:$T$4,$B$1:$T$1)))+('M1 Demand Driver'!F17/SUM('M1 Demand Driver'!F8:F17)*MAX(0,_xlfn.FORECAST.LINEAR(H31,$B$4:$T$4,$B$1:$T$1)*(1+$B$29)^(H31-$B$1))) -> 93.385587 | I34: =(SUM('M1 Demand Driver'!E8:E16)/SUM('M1 Demand Driver'!E8:E17)*MAX(0,_xlfn.FORECAST.LINEAR(I31,$B$4:$T$4,$B$1:$T$1)))+('M1 Demand Driver'!E17/SUM('M1 Demand Driver'!E8:E17)*MAX(0,_xlfn.FORECAST.LINEAR(I31,$B$4:$T$4,$B$1:$T$1)*(1+$B$29)^(I31-$B$1))) -> 92.039796 | J34: =(SUM('M1 Demand Driver'!D8:D16)/SUM('M1 Demand Driver'!D8:D17)*MAX(0,_xlfn.FORECAST.LINEAR(J31,$B$4:$T$4,$B$1:$T$1)))+('M1 Demand Driver'!D17/SUM('M1 Demand Driver'!D8:D17)*MAX(0,_xlfn.FORECAST.LINEAR(J31,$B$4:$T$4,$B$1:$T$1)*(1+$B$29)^(J31-$B$1))) -> 90.691522 | K34: =(SUM('M1 Demand Driver'!C8:C16)/SUM('M1 Demand Driver'!C8:C17)*MAX(0,_xlfn.FORECAST.LINEAR(K31, $B$4:$T$4, $B$1:$T$1)))+('M1 Demand Driver'!C17/SUM('M1 Demand Driver'!C8:C17)*MAX(0,_xlfn.FORECAST.LINEAR(K31, $B$4:$T$4, $B$1:$T$1)*(1+$B$29)^(K31-$B$1))) -> 89.341033 | L34: =(SUM('M1 Demand Driver'!B8:B16)/SUM('M1 Demand Driver'!B8:B17)*MAX(0,_xlfn.FORECAST.LINEAR(L31,$B$4:$T$4,$B$1:$T$1)))+('M1 Demand Driver'!B17/SUM('M1 Demand Driver'!B8:B17)*MAX(0,_xlfn.FORECAST.LINEAR(L31,$B$4:$T$4,$B$1:$T$1)*(1+$B$29)^(L31-$B$1))) -> 87.988734
A35: 65 Years Old & Above | B35: =MAX(0,_xlfn.FORECAST.LINEAR(B31, $B$5:$T$5, $B$1:$T$1)*(1+$B$29)^(B31-$B$1)) -> 368.36488 | C35: =MAX(0,_xlfn.FORECAST.LINEAR(C31, $B$5:$T$5, $B$1:$T$1)*(1+$B$29)^(C31-$B$1)) -> 368.62213 | D35: =MAX(0,_xlfn.FORECAST.LINEAR(D31, $B$5:$T$5, $B$1:$T$1)*(1+$B$29)^(D31-$B$1)) -> 368.86906 | E35: =MAX(0,_xlfn.FORECAST.LINEAR(E31, $B$5:$T$5, $B$1:$T$1)*(1+$B$29)^(E31-$B$1)) -> 369.10555 | F35: =MAX(0,_xlfn.FORECAST.LINEAR(F31, $B$5:$T$5, $B$1:$T$1)*(1+$B$29)^(F31-$B$1)) -> 369.33145 | G35: =MAX(0,_xlfn.FORECAST.LINEAR(G31, $B$5:$T$5, $B$1:$T$1)*(1+$B$29)^(G31-$B$1)) -> 369.54662 | H35: =MAX(0,_xlfn.FORECAST.LINEAR(H31, $B$5:$T$5, $B$1:$T$1)*(1+$B$29)^(H31-$B$1)) -> 369.75094 | I35: =MAX(0,_xlfn.FORECAST.LINEAR(I31, $B$5:$T$5, $B$1:$T$1)*(1+$B$29)^(I31-$B$1)) -> 369.94426 | ... L35: =MAX(0,_xlfn.FORECAST.LINEAR(L31, $B$5:$T$5, $B$1:$T$1)*(1+$B$29)^(L31-$B$1)) -> 370.45682
A36: Acute Hospitals - Female - Projected
A37: 0 - 14 Years Old | B37: =MAX(0,_xlfn.FORECAST.LINEAR(B31, $B$7:$T$7, $B$1:$T$1)) -> 154.97193 | C37: =MAX(0,_xlfn.FORECAST.LINEAR(C31, $B$7:$T$7, $B$1:$T$1)) -> 152.54175 | D37: =MAX(0,_xlfn.FORECAST.LINEAR(D31, $B$7:$T$7, $B$1:$T$1)) -> 150.11158 | E37: =MAX(0,_xlfn.FORECAST.LINEAR(E31, $B$7:$T$7, $B$1:$T$1)) -> 147.6814 | F37: =MAX(0,_xlfn.FORECAST.LINEAR(F31, $B$7:$T$7, $B$1:$T$1)) -> 145.25123 | G37: =MAX(0,_xlfn.FORECAST.LINEAR(G31, $B$7:$T$7, $B$1:$T$1)) -> 142.82105 | H37: =MAX(0,_xlfn.FORECAST.LINEAR(H31, $B$7:$T$7, $B$1:$T$1)) -> 140.39088 | I37: =MAX(0,_xlfn.FORECAST.LINEAR(I31, $B$7:$T$7, $B$1:$T$1)) -> 137.9607 | ... L37: =MAX(0,_xlfn.FORECAST.LINEAR(L31, $B$7:$T$7, $B$1:$T$1)) -> 130.67018
A38: 15 - 64 Years Old | B38: =(SUM('M1 Demand Driver'!L8:L16)/SUM('M1 Demand Driver'!L8:L17)*MAX(0,_xlfn.FORECAST.LINEAR(B31,$B$8:$T$8,$B$1:$T$1)))+('M1 Demand Driver'!L17/SUM('M1 Demand Driver'!L8:L17)*MAX(0,_xlfn.FORECAST.LINEAR(B31,$B$8:$T$8,$B$1:$T$1)*(1+$B$29)^(B31-$B$1))) -> 101.25495 | C38: =(SUM('M1 Demand Driver'!K8:K16)/SUM('M1 Demand Driver'!K8:K17)*MAX(0,_xlfn.FORECAST.LINEAR(C31,$B$8:$T$8,$B$1:$T$1)))+('M1 Demand Driver'!K17/SUM('M1 Demand Driver'!K8:K17)*MAX(0,_xlfn.FORECAST.LINEAR(C31,$B$8:$T$8,$B$1:$T$1)*(1+$B$29)^(C31-$B$1))) -> 100.36897 | D38: =(SUM('M1 Demand Driver'!J8:J16)/SUM('M1 Demand Driver'!J8:J17)*MAX(0,_xlfn.FORECAST.LINEAR(D31,$B$8:$T$8,$B$1:$T$1)))+('M1 Demand Driver'!J17/SUM('M1 Demand Driver'!J8:J17)*MAX(0,_xlfn.FORECAST.LINEAR(D31,$B$8:$T$8,$B$1:$T$1)*(1+$B$29)^(D31-$B$1))) -> 99.480046 | E38: =(SUM('M1 Demand Driver'!I8:I16)/SUM('M1 Demand Driver'!I8:I17)*MAX(0,_xlfn.FORECAST.LINEAR(E31,$B$8:$T$8,$B$1:$T$1)))+('M1 Demand Driver'!I17/SUM('M1 Demand Driver'!I8:I17)*MAX(0,_xlfn.FORECAST.LINEAR(E31,$B$8:$T$8,$B$1:$T$1)*(1+$B$29)^(E31-$B$1))) -> 98.588335 | F38: =(SUM('M1 Demand Driver'!H8:H16)/SUM('M1 Demand Driver'!H8:H17)*MAX(0,_xlfn.FORECAST.LINEAR(F31,$B$8:$T$8,$B$1:$T$1)))+('M1 Demand Driver'!H17/SUM('M1 Demand Driver'!H8:H17)*MAX(0,_xlfn.FORECAST.LINEAR(F31,$B$8:$T$8,$B$1:$T$1)*(1+$B$29)^(F31-$B$1))) -> 97.693995 | G38: =(SUM('M1 Demand Driver'!G8:G16)/SUM('M1 Demand Driver'!G8:G17)*MAX(0,_xlfn.FORECAST.LINEAR(G31,$B$8:$T$8,$B$1:$T$1)))+('M1 Demand Driver'!G17/SUM('M1 Demand Driver'!G8:G17)*MAX(0,_xlfn.FORECAST.LINEAR(G31,$B$8:$T$8,$B$1:$T$1)*(1+$B$29)^(G31-$B$1))) -> 96.797185 | H38: =(SUM('M1 Demand Driver'!F8:F16)/SUM('M1 Demand Driver'!F8:F17)*MAX(0,_xlfn.FORECAST.LINEAR(H31,$B$8:$T$8,$B$1:$T$1)))+('M1 Demand Driver'!F17/SUM('M1 Demand Driver'!F8:F17)*MAX(0,_xlfn.FORECAST.LINEAR(H31,$B$8:$T$8,$B$1:$T$1)*(1+$B$29)^(H31-$B$1))) -> 95.898064 | I38: =(SUM('M1 Demand Driver'!E8:E16)/SUM('M1 Demand Driver'!E8:E17)*MAX(0,_xlfn.FORECAST.LINEAR(I31,$B$8:$T$8,$B$1:$T$1)))+('M1 Demand Driver'!E17/SUM('M1 Demand Driver'!E8:E17)*MAX(0,_xlfn.FORECAST.LINEAR(I31,$B$8:$T$8,$B$1:$T$1)*(1+$B$29)^(I31-$B$1))) -> 94.996798 | J38: =(SUM('M1 Demand Driver'!D8:D16)/SUM('M1 Demand Driver'!D8:D17)*MAX(0,_xlfn.FORECAST.LINEAR(J31,$B$8:$T$8,$B$1:$T$1)))+('M1 Demand Driver'!D17/SUM('M1 Demand Driver'!D8:D17)*MAX(0,_xlfn.FORECAST.LINEAR(J31,$B$8:$T$8,$B$1:$T$1)*(1+$B$29)^(J31-$B$1))) -> 94.093583 | K38: =(SUM('M1 Demand Driver'!C8:C16)/SUM('M1 Demand Driver'!C8:C17)*MAX(0,_xlfn.FORECAST.LINEAR(K31,$B$8:$T$8,$B$1:$T$1)))+('M1 Demand Driver'!C17/SUM('M1 Demand Driver'!C8:C17)*MAX(0,_xlfn.FORECAST.LINEAR(K31,$B$8:$T$8,$B$1:$T$1)*(1+$B$29)^(K31-$B$1))) -> 93.188691 | L38: =(SUM('M1 Demand Driver'!B8:B16)/SUM('M1 Demand Driver'!B8:B17)*MAX(0,_xlfn.FORECAST.LINEAR(L31,$B$8:$T$8,$B$1:$T$1)))+('M1 Demand Driver'!B17/SUM('M1 Demand Driver'!B8:B17)*MAX(0,_xlfn.FORECAST.LINEAR(L31,$B$8:$T$8,$B$1:$T$1)*(1+$B$29)^(L31-$B$1))) -> 92.282535
A39: 65 Years Old & Above | B39: =MAX(0,_xlfn.FORECAST.LINEAR(B31, $B$9:$T$9, $B$1:$T$1)*(1+$B$29)^(B31-$B$1)) -> 289.21351 | C39: =MAX(0,_xlfn.FORECAST.LINEAR(C31, $B$9:$T$9, $B$1:$T$1)*(1+$B$29)^(C31-$B$1)) -> 290.59617 | D39: =MAX(0,_xlfn.FORECAST.LINEAR(D31, $B$9:$T$9, $B$1:$T$1)*(1+$B$29)^(D31-$B$1)) -> 291.98499 | E39: =MAX(0,_xlfn.FORECAST.LINEAR(E31, $B$9:$T$9, $B$1:$T$1)*(1+$B$29)^(E31-$B$1)) -> 293.37998 | F39: =MAX(0,_xlfn.FORECAST.LINEAR(F31, $B$9:$T$9, $B$1:$T$1)*(1+$B$29)^(F31-$B$1)) -> 294.78118 | G39: =MAX(0,_xlfn.FORECAST.LINEAR(G31, $B$9:$T$9, $B$1:$T$1)*(1+$B$29)^(G31-$B$1)) -> 296.18861 | H39: =MAX(0,_xlfn.FORECAST.LINEAR(H31, $B$9:$T$9, $B$1:$T$1)*(1+$B$29)^(H31-$B$1)) -> 297.60228 | I39: =MAX(0,_xlfn.FORECAST.LINEAR(I31, $B$9:$T$9, $B$1:$T$1)*(1+$B$29)^(I31-$B$1)) -> 299.02223 | ... L39: =MAX(0,_xlfn.FORECAST.LINEAR(L31, $B$9:$T$9, $B$1:$T$1)*(1+$B$29)^(L31-$B$1)) -> 303.31997
A40: Total Acute Hospitals - Projected
A41: 0 - 14 Years Old (Projected) | B41: =B33+B37 -> 328.69123 | C41: =C33+C37 -> 323.68298 | D41: =D33+D37 -> 318.67474 | E41: =E33+E37 -> 313.66649 | F41: =F33+F37 -> 308.65825 | G41: =G33+G37 -> 303.65 | H41: =H33+H37 -> 298.64175 | I41: =I33+I37 -> 293.63351 | ... L41: =L33+L37 -> 278.60877 | M41: =B3+B7 -> 254.9
A42: 15 - 64 Years Old (Projected) | B42: =B34+B38 -> 202.65274 | C42: =C34+C38 -> 200.4397 | D42: =D34+D38 -> 198.22017 | E42: =E34+E38 -> 195.99447 | F42: =F34+F38 -> 193.76292 | G42: =G34+G38 -> 191.52587 | H42: =H34+H38 -> 189.28365 | I42: =I34+I38 -> 187.03659 | ... L42: =L34+L38 -> 180.27127 | M42: =B4+B8 -> 168.8
A43: 65 Years Old & Above (Projected) | B43: =B35+B39 -> 657.57839 | C43: =C35+C39 -> 659.2183 | D43: =D35+D39 -> 660.85405 | E43: =E35+E39 -> 662.48553 | F43: =F35+F39 -> 664.11263 | G43: =G35+G39 -> 665.73523 | H43: =H35+H39 -> 667.35322 | I43: =I35+I39 -> 668.96649 | ... L43: =L35+L39 -> 673.7768 | M43: =B5+B9 -> 671.3
A44: Admission Rate - Total
A45: 0 - 14 Years Old | B45: =AVERAGE(B33,B37)/1000 -> 0.16434561 | C45: =AVERAGE(C33,C37)/1000 -> 0.16184149 | D45: =AVERAGE(D33,D37)/1000 -> 0.15933737 | E45: =AVERAGE(E33,E37)/1000 -> 0.15683325 | F45: =AVERAGE(F33,F37)/1000 -> 0.15432912 | G45: =AVERAGE(G33,G37)/1000 -> 0.151825 | H45: =AVERAGE(H33,H37)/1000 -> 0.14932088 | I45: =AVERAGE(I33,I37)/1000 -> 0.14681675 | ... L45: =AVERAGE(L33,L37)/1000 -> 0.13930439
A46: 15 - 64 Years Old | B46: =AVERAGE(B34,B38)/1000 -> 0.10132637 | C46: =AVERAGE(C34,C38)/1000 -> 0.10021985 | D46: =AVERAGE(D34,D38)/1000 -> 0.099110086 | E46: =AVERAGE(E34,E38)/1000 -> 0.097997234 | F46: =AVERAGE(F34,F38)/1000 -> 0.096881462 | G46: =AVERAGE(G34,G38)/1000 -> 0.095762937 | H46: =AVERAGE(H34,H38)/1000 -> 0.094641825 | I46: =AVERAGE(I34,I38)/1000 -> 0.093518297 | ... L46: =AVERAGE(L34,L38)/1000 -> 0.090135634
A47: 65 Years Old & Above | B47: =AVERAGE(B35,B39)/1000 -> 0.32878919 | C47: =AVERAGE(C35,C39)/1000 -> 0.32960915 | D47: =AVERAGE(D35,D39)/1000 -> 0.33042703 | E47: =AVERAGE(E35,E39)/1000 -> 0.33124277 | F47: =AVERAGE(F35,F39)/1000 -> 0.33205631 | G47: =AVERAGE(G35,G39)/1000 -> 0.33286762 | H47: =AVERAGE(H35,H39)/1000 -> 0.33367661 | I47: =AVERAGE(I35,I39)/1000 -> 0.33448325 | ... L47: =AVERAGE(L35,L39)/1000 -> 0.3368884
A48: Total Acute Hospitals - History
A49: 0 - 14 Years Old (Actual) | M49: =B3+B7 -> 254.9 | N49: =C3+C7 -> 261.3 | O49: =D3+D7 -> 263.8 | P49: =E3+E7 -> 229.1 | Q49: =F3+F7 -> 208.9 | R49: =G3+G7 -> 280.2 | S49: =H3+H7 -> 272.4 | T49: =I3+I7 -> 267 | ... AE49: =T3+T7 -> 173.9
A50: 15 - 64 Years Old (Actual) | M50: =B4+B8 -> 168.8 | N50: =C4+C8 -> 167.6 | O50: =D4+D8 -> 164.8 | P50: =E4+E8 -> 173 | Q50: =F4+F8 -> 165.5 | R50: =G4+G8 -> 185.3 | S50: =H4+H8 -> 176.6 | T50: =I4+I8 -> 174.4 | ... AE50: =T4+T8 -> 141.4
A51: 65 Years Old & Above (Actual) | M51: =B5+B9 -> 671.3 | N51: =C5+C9 -> 681.1 | O51: =D5+D9 -> 675.5 | P51: =E5+E9 -> 634.4 | Q51: =F5+F9 -> 613 | R51: =G5+G9 -> 695.4 | S51: =H5+H9 -> 682 | T51: =I5+I9 -> 688.9 | ... AE51: =T5+T9 -> 633.6
A54: Government Policy Factor(r) is a bidirectional variable that simulates the impact of the government policies.
A55: Negative Value (r<0): Represents Proactive Policy outcomes, such as reduced acute demand through preventative care (e.g., Healthier SG).
A56: Positive Value (r>0): Represents policy-induced risks, resulting in increased acute demand.

Sheet M2 Beds
A1: Beds In Inpatient Facilities | B1: 2023 | C1: 2022 | D1: 2021 | E1: 2020 | F1: 2019 | G1: 2018 | H1: 2017 | I1: 2016 | J1: 2015 | K1: 2014 | L1: 2013 | M1: 2012 | N1: 2011 | O1: 2010 | P1: 2009 | Q1: 2008 | R1: 2007 | S1: 2006
A2: Acute Hospitals | B2: 12025 | C2: 11830 | D2: 11704 | E2: 11545 | F2: 11321 | G2: 10826 | H2: 10340 | I2: 10318 | J2: 9844 | K2: 9262 | L2: 8939 | M2: 8725 | N2: 8304 | O2: 8249 | P2: 8289 | Q2: 8190 | R2: 8235 | S2: 8187
A3: Public | B3: 9956 | C3: 9820 | D3: 9762 | E3: 9610 | F3: 9404 | G3: 9071 | H3: 8623 | I3: 8561 | J3: 8128 | K3: 7652 | L3: 7377 | M3: 7170 | N3: 6925 | O3: 6871 | P3: 6416 | Q3: 6255 | R3: 6304 | S3: 6256
A4: Not-For-Profit | B4: 347 | C4: 273 | D4: 270 | E4: 285 | F4: 288 | G4: 273 | H4: 271 | I4: 316 | J4: 316 | K4: 283 | L4: 283 | M4: 283 | N4: 283 | O4: 283 | P4: 303 | Q4: 303 | R4: 303 | S4: 303
A5: Private | B5: 1722 | C5: 1737 | D5: 1672 | E5: 1650 | F5: 1629 | G5: 1482 | H5: 1446 | I5: 1441 | J5: 1400 | K5: 1327 | L5: 1279 | M5: 1272 | N5: 1096 | O5: 1095 | P5: 1570 | Q5: 1632 | R5: 1628 | S5: 1628
A6: Psychiatric Hospitals | B6: 1950 | C6: 1950 | D6: 1950 | E6: 1950 | F6: 1950 | G6: 1950 | H6: 1950 | I6: 1950 | J6: 1950 | K6: 1950 | L6: 2010 | M6: 2010 | N6: 2010 | O6: 2010 | P6: 2040 | Q6: 2064 | R6: 2064 | S6: 2113
A7: Public | B7: 1950 | C7: 1950 | D7: 1950 | E7: 1950 | F7: 1950 | G7: 1950 | H7: 1950 | I7: 1950 | J7: 1950 | K7: 1950 | L7: 2010 | M7: 2010 | N7: 2010 | O7: 2010 | P7: 2040 | Q7: 2064 | R7: 2064 | S7: 2064
A8: Not-For-Profit | B8: 0 | C8: 0 | D8: 0 | E8: 0 | F8: 0 | G8: 0 | H8: 0 | I8: 0 | J8: 0 | K8: 0 | L8: 0 | M8: 0 | N8: 0 | O8: 0 | P8: 0 | Q8: 0 | R8: 0 | S8: 0
A9: Private | B9: 0 | C9: 0 | D9: 0 | E9: 0 | F9: 0 | G9: 0 | H9: 0 | I9: 0 | J9: 0 | K9: 0 | L9: 0 | M9: 0 | N9: 0 | O9: 0 | P9: 0 | Q9: 0 | R9: 0 | S9: 49
A10: Community Hospitals | B10: 2303 | C10: 2194 | D10: 2011 | E10: 2069 | F10: 1986 | G10: 1778 | H10: 1663 | I10: 1663 | J10: 1464 | K10: 1065 | L10: 852 | M10: 842 | N10: 800 | O10: 842 | P10: 877 | Q10: 872 | R10: 749 | S10: 771
A11: Public | B11: 1331 | C11: 1226 | D11: 1112 | E11: 1130 | F11: 974 | G11: 799 | H11: 690 | I11: 690 | J11: 503 | K11: 142 | L11: 110 | M11: 100 | N11: 100 | O11: 0 | P11: 0 | Q11: 0 | R11: 0 | S11: 0
A12: Not-For-Profit | B12: 972 | C12: 968 | D12: 899 | E12: 939 | F12: 1012 | G12: 979 | H12: 969 | I12: 961 | J12: 961 | K12: 905 | L12: 722 | M12: 722 | N12: 680 | O12: 818 | P12: 819 | Q12: 814 | R12: 691 | S12: 713
... A17: Private | B17: 4474 | C17: 3932 | D17: 3905 | E17: 3867 | F17: 3858 | G17: 3671 | H17: 3765 | I17: 3854 | J17: 3895 | K17: 3575 | L17: 3684 | M17: 3400 | N17: 3303 | O17: 3258 | P17: 3180 | Q17: 3657 | R17: 3504 | S17: 3282
A18: Inpatient Hospice Palliative Care Service (IHPCS) | B18: 284 | C18: 264 | D18: 264 | E18: 253 | F18: na | G18: na | H18: na | I18: na | J18: na | K18: na | L18: na | M18: na | N18: na | O18: na | P18: na | Q18: na | R18: na | S18: na
A19: Public | B19: 64 | C19: 64 | D19: 64 | E19: 60 | F19: na | G19: na | H19: na | I19: na | J19: na | K19: na | L19: na | M19: na | N19: na | O19: na | P19: na | Q19: na | R19: na | S19: na
A20: Not-For-Profit | B20: 220 | C20: 200 | D20: 200 | E20: 193 | F20: na | G20: na | H20: na | I20: na | J20: na | K20: na | L20: na | M20: na | N20: na | O20: na | P20: na | Q20: na | R20: na | S20: na
A21: Private | B21: 0 | C21: 0 | D21: 0 | E21: 0 | F21: na | G21: na | H21: na | I21: na | J21: na | K21: na | L21: na | M21: na | N21: na | O21: na | P21: na | Q21: na | R21: na | S21: na
A23: Projected Beds
A24: Annual Bed Expansion Rate (r) | B24: ='M2 BOR & Tradeoff analysis'!B9 -> 0.0353
B25: Projected | M25: Historical
A26: Beds In Inpatient Facilities | B26: 2035 | C26: =B26-1 -> 2034 | D26: =C26-1 -> 2033 | E26: =D26-1 -> 2032 | F26: =E26-1 -> 2031 | G26: =F26-1 -> 2030 | H26: =G26-1 -> 2029 | I26: =H26-1 -> 2028 | J26: =I26-1 -> 2027 | ... L26: =K26-1 -> 2025 | M26: 2024 | N26: 2023 | O26: 2022 | P26: 2021 | Q26: 2020 | R26: 2019 | S26: 2018 | T26: 2017 | U26: 2016 | V26: 2015 | W26: 2014 | X26: 2013 | Y26: 2012 | Z26: 2011 | AA26: 2010 | AB26: 2009 | AC26: 2008 | AD26: 2007 | AE26: 2006
A27: Public Acute Hospitals - by History | B27: =MAX(0, _xlfn.FORECAST.LINEAR(B26, $B$3:$S$3,$B$1:$S$1)*(1+$B$24)^(B26-2024)) -> 19336.378 | C27: =MAX(0, _xlfn.FORECAST.LINEAR(C26, $B$3:$S$3,$B$1:$S$1)*(1+$B$24)^(C26-2024)) -> 18318.693 | D27: =MAX(0, _xlfn.FORECAST.LINEAR(D26, $B$3:$S$3,$B$1:$S$1)*(1+$B$24)^(D26-2024)) -> 17347.927 | E27: =MAX(0, _xlfn.FORECAST.LINEAR(E26, $B$3:$S$3,$B$1:$S$1)*(1+$B$24)^(E26-2024)) -> 16422.063 | F27: =MAX(0, _xlfn.FORECAST.LINEAR(F26, $B$3:$S$3,$B$1:$S$1)*(1+$B$24)^(F26-2024)) -> 15539.168 | G27: =MAX(0, _xlfn.FORECAST.LINEAR(G26, $B$3:$S$3,$B$1:$S$1)*(1+$B$24)^(G26-2024)) -> 14697.389 | H27: =MAX(0, _xlfn.FORECAST.LINEAR(H26, $B$3:$S$3,$B$1:$S$1)*(1+$B$24)^(H26-2024)) -> 13894.948 | I27: =MAX(0, _xlfn.FORECAST.LINEAR(I26, $B$3:$S$3,$B$1:$S$1)*(1+$B$24)^(I26-2024)) -> 13130.141 | ... M27: =MAX(0, _xlfn.FORECAST.LINEAR(M26, $B$3:$S$3,$B$1:$S$1)*(1+$B$24)^(M26-2024)) -> 10415.582 | N27: =B3 -> 9956
A28: Public Acute Hospitals - by Exp. Rate | B28: =ROUNDUP(C28*(1+$B$24),0) -> 17583 | C28: =ROUNDUP(D28*(1+$B$24),0) -> 16983 | D28: =ROUNDUP(E28*(1+$B$24),0) -> 16403 | E28: =ROUNDUP(F28*(1+$B$24),0) -> 15843 | F28: =ROUNDUP(G28*(1+$B$24),0) -> 15302 | G28: =ROUNDUP(H28*(1+$B$24),0) -> 14780 | H28: =ROUNDUP(I28*(1+$B$24),0) -> 14276 | I28: =ROUNDUP(J28*(1+$B$24),0) -> 13789 | ... L28: =ROUNDUP(M28*(1+$B$24),0) -> 12424 | M28: ='M2 BOR & Tradeoff analysis'!B7 -> 12000 | N28: =B3 -> 9956
A29: Public Acute Hospitals | B29: =B28 -> 17583 | C29: =C28 -> 16983 | D29: =D28 -> 16403 | E29: =E28 -> 15843 | F29: =F28 -> 15302 | G29: =G28 -> 14780 | H29: =H28 -> 14276 | I29: =I28 -> 13789 | ... M29: =M28 -> 12000 | N29: 9956 | O29: 9820 | P29: 9762 | Q29: 9610 | R29: 9404 | S29: 9071 | T29: 8623 | U29: 8561 | V29: 8128 | W29: 7652 | X29: 7377 | Y29: 7170 | Z29: 6925 | AA29: 6871 | AB29: 6416 | AC29: 6255 | AD29: 6304 | AE29: 6256
A30: Public Acute Hospitals - History | N30: 9956 | O30: 9820 | P30: 9762 | Q30: 9610 | R30: 9404 | S30: 9071 | T30: 8623 | U30: 8561 | V30: 8128 | W30: 7652 | X30: 7377 | Y30: 7170 | Z30: 6925 | AA30: 6871 | AB30: 6416 | AC30: 6255 | AD30: 6304 | AE30: 6256
L33: Annual Bed Expansion Rate (r) - Data Source: MOH Bed Expansion Plan
L34: Base beds (2024): B_2024=12,000​ (public acute hospital beds)
L35: Additional beds (2025–2030): 2,800
L36: Target beds (2030): B_2030​=12,000+2,800=14,800
L37: Time period: 6 years (n=6)
L38: B_2030=B_2024*(1+r)^n, r=the annual expansion rate
L39: Solve for r=3.53%
L41: Two methods for predicting the bed number form 2024 to 2035:
L42: A27 'Public Acute Hospitals - by History' uses historical data (2006–2023) to make predictions from 2024 to 2035.
L43: A28 'Acute Hospitals - by Exp. Rate' is calculated using the expansion rate r and the bed number of 2024 (defined in BOR!A7), which is not affected by historical data.
L45: A29 'Public Acute Hospitals' is a complete sequence of bed numbers from 2006 to 2035, combining historical data (2006-2023) and predicted data (2024-2035).
L47: by history | N47: =_xlfn.FORMULATEXT(B27) -> =MAX(0, FORECAST.LINEAR(B26, $B$3:$S$3,$B$1:$S$1)*(1+$B$24)^(B26-2024))
L48: by rate | N48: =_xlfn.FORMULATEXT(B28) -> =ROUNDUP(C28*(1+$B$24),0)

Sheet M2 BOR & Tradeoff analysis
A1: Bed Occupancy Rate (BOR) | N1: Option Define
A2: Core Assumptions & Official Parameters | N2: Bed Expansion Rate
A3: Parameter | B3: Baseline Value | C3: Data Source/Description | E3: Year | F3: Annual Acute Beds | N3: 0.02
A4: Bed Availability Factor | B4: 0.95 | E4: 2025 | F4: =INDEX('M2 Beds'!$B$29:$N$29, MATCH(E4, 'M2 Beds'!$B$26:$N$26, 0)) -> 12424 | N4: 0.023
A5: BOR Warning Threshold | B5: 0.8 | C5: Hospital bed occupancy rate | E5: =E4+1 -> 2026 | F5: =INDEX('M2 Beds'!$B$29:$N$29, MATCH(E5, 'M2 Beds'!$B$26:$N$26, 0)) -> 12863 | N5: 0.03
A6: BOR Critical Red Line | B6: 0.85 | C6: Hospital bed occupancy rate | E6: =E5+1 -> 2027 | F6: =INDEX('M2 Beds'!$B$29:$N$29, MATCH(E6, 'M2 Beds'!$B$26:$N$26, 0)) -> 13318 | N6: 0.0353
A7: 2024 Acute Hospital Beds | B7: 12000 | C7: MOH Bed Expansion Plan | D7: Baseline | E7: =E6+1 -> 2028 | F7: =INDEX('M2 Beds'!$B$29:$N$29, MATCH(E7, 'M2 Beds'!$B$26:$N$26, 0)) -> 13789 | N7: Average ALOS
A8: Average ALOS | B8: 6 | C8: Waiting Times for Admissions | E8: =E7+1 -> 2029 | F8: =INDEX('M2 Beds'!$B$29:$N$29, MATCH(E8, 'M2 Beds'!$B$26:$N$26, 0)) -> 14276 | N8: 5.5
A9: Annual Bed Expansion Rate | B9: 0.0353 | C9: MOH Bed Expansion Plan | D9: Adjustable | E9: =E8+1 -> 2030 | F9: =INDEX('M2 Beds'!$B$29:$N$29, MATCH(E9, 'M2 Beds'!$B$26:$N$26, 0)) -> 14780 | N9: 6
A10: ALOS Adjustment Factor | B10: 0 | C10: Adjusts all age groups' ALOS | E10: =E9+1 -> 2031 | F10: =INDEX('M2 Beds'!$B$29:$N$29, MATCH(E10, 'M2 Beds'!$B$26:$N$26, 0)) -> 15302 | N10: 6.5
A11: 65+ Pop. Growth Adjust | B11: 0 | C11: Adjusts 65+ population | E11: =E10+1 -> 2032 | F11: =INDEX('M2 Beds'!$B$29:$N$29, MATCH(E11, 'M2 Beds'!$B$26:$N$26, 0)) -> 15843 | N11: 7
A12: Government Policy Factor | B12: -0.006 | C12: e.g., Healthier SG | E12: =E11+1 -> 2033 | F12: =INDEX('M2 Beds'!$B$29:$N$29, MATCH(E12, 'M2 Beds'!$B$26:$N$26, 0)) -> 16403 | N12: 8
E13: =E12+1 -> 2034 | F13: =INDEX('M2 Beds'!$B$29:$N$29, MATCH(E13, 'M2 Beds'!$B$26:$N$26, 0)) -> 16983 | N13: 65+ Population Growth Adjust
E14: =E13+1 -> 2035 | F14: =INDEX('M2 Beds'!$B$29:$N$29, MATCH(E14, 'M2 Beds'!$B$26:$N$26, 0)) -> 17583 | N14: -0.01
N15: 0
A16: Age Group | B16: Average ALOS (Days) | C16: Reasonable Range (Days) | D16: Age Factor | N16: 0.005
A17: 0 - 14 Years Old | B17: =$B$8*D17 -> 4.2 | C17: 4~5 | D17: 0.7 | N17: 0.01
A18: 15 - 64 Years Old | B18: =$B$8*D18 -> 5.4 | C18: 5~7 | D18: 0.9 | N18: 0.015
A19: 65 Years Old & Above | B19: =$B$8*D19 -> 7.8 | C19: 10~14 | D19: 1.3 | N19: ALOS Adjustment Factor
N20: -0.08
A21: Statistics | N21: 0
A22: BOR-2025 | B22: BOR-2030 | C22: BOR-2035 | D22: Average BOR | E22: First Warning Year | F22: First Redline Year | N22: 0.08
A23: =G27 -> 0.8957827 | B23: =G32 -> 0.83291931 | C23: =G37 -> 0.74213922 | D23: =AVERAGE(G27:G37) -> 0.82740489 | E23: =_xlfn.MINIFS(A27:A37, G27:G37, ">="&$B$5) -> 2025 | F23: =_xlfn.MINIFS(A27:A37, G27:G37, ">="&$B$6) -> 2025 | N23: 0.16
I24: Annual Bed Expansion Rate (%) | M24: Primary BOR Influence Factors | N24: 0.25
A25: Supply-Side: Beds | I25: 0.02 | J25: 0.023 | K25: 0.03 | L25: 0.0353 | M25: Annual Bed Expansion Rate | N25: Govt Policy Factor
A26: Year | B26: Opening Acute Beds | C26: Closing Acute Beds | D26: Avg Acute Beds | E26: Total Bed Days Demand | F26: Available Bed Days | G26: Bed Occ. Rate (BOR) | I26: Bed Occupancy Rate (BOR) | M26: Government Policy Factor | N26: -0.006
A27: 2025 | B27: =IF(A27=2025,$B$7,OFFSET(C27,-1,0)) -> 12000 | C27: =VLOOKUP(A27,$E$4:$F$14,2) -> 12424 | D27: =AVERAGE(B27,C27) -> 12212 | E27: =VLOOKUP(A27,$A$42:$L$52,12) -> 3793201.7 | F27: =D27*365*$B$4 -> 4234511 | G27: =E27/F27 -> 0.8957827 | I27: 0.90258237 | J27: 0.90124389 | K27: 0.89813615 | L27: 0.8957827 | N27: 0
A28: =A27+1 -> 2026 | B28: =IF(A28=2025,$B$7,OFFSET(C28,-1,0)) -> 12424 | C28: =VLOOKUP(A28,$E$4:$F$14,2) -> 12863 | D28: =AVERAGE(B28,C28) -> 12643.5 | E28: =VLOOKUP(A28,$A$42:$L$52,12) -> 3887356.8 | F28: =D28*365*$B$4 -> 4384133.6 | G28: =E28/F28 -> 0.88668758 | I28: 0.90684202 | J28: 0.9028254 | K28: 0.893614 | L28: 0.88668758 | N28: ·
A29: =A28+1 -> 2027 | B29: =IF(A29=2025,$B$7,OFFSET(C29,-1,0)) -> 12863 | C29: =VLOOKUP(A29,$E$4:$F$14,2) -> 13318 | D29: =AVERAGE(B29,C29) -> 13090.5 | E29: =VLOOKUP(A29,$A$42:$L$52,12) -> 3974229.1 | F29: =D29*365*$B$4 -> 4539130.9 | G29: =E29/F29 -> 0.87554847 | I29: 0.90891096 | J29: 0.90222122 | K29: 0.88696543 | L29: 0.87554847
A30: =A29+1 -> 2028 | B30: =IF(A30=2025,$B$7,OFFSET(C30,-1,0)) -> 13318 | C30: =VLOOKUP(A30,$E$4:$F$14,2) -> 13789 | D30: =AVERAGE(B30,C30) -> 13553.5 | E30: =VLOOKUP(A30,$A$42:$L$52,12) -> 4054404 | F30: =D30*365*$B$4 -> 4699676.1 | G30: =E30/F30 -> 0.8626986 | I30: 0.90904454 | J30: 0.89970648 | K30: 0.87848125 | L30: 0.8626986
A31: =A30+1 -> 2029 | B31: =IF(A31=2025,$B$7,OFFSET(C31,-1,0)) -> 13789 | C31: =VLOOKUP(A31,$E$4:$F$14,2) -> 14276 | D31: =AVERAGE(B31,C31) -> 14032.5 | E31: =VLOOKUP(A31,$A$42:$L$52,12) -> 4128223.4 | F31: =D31*365*$B$4 -> 4865769.4 | G31: =E31/F31 -> 0.84842151 | I31: 0.90742949 | J31: 0.89545146 | K31: 0.86837891 | L31: 0.84842151
A32: =A31+1 -> 2030 | B32: =IF(A32=2025,$B$7,OFFSET(C32,-1,0)) -> 14276 | C32: =VLOOKUP(A32,$E$4:$F$14,2) -> 14780 | D32: =AVERAGE(B32,C32) -> 14528 | E32: =VLOOKUP(A32,$A$42:$L$52,12) -> 4195901 | F32: =D32*365*$B$4 -> 5037584 | G32: =E32/F32 -> 0.83291931 | I32: 0.90421459 | J32: 0.88962297 | K32: 0.8568653 | L32: 0.83291931
A33: =A32+1 -> 2031 | B33: =IF(A33=2025,$B$7,OFFSET(C33,-1,0)) -> 14780 | C33: =VLOOKUP(A33,$E$4:$F$14,2) -> 15302 | D33: =AVERAGE(B33,C33) -> 15041 | E33: =VLOOKUP(A33,$A$42:$L$52,12) -> 4257593.4 | F33: =D33*365*$B$4 -> 5215466.8 | G33: =E33/F33 -> 0.81633987 | I33: 0.89949584 | J33: 0.88236628 | K33: 0.84411989 | L33: 0.81633987
A34: =A33+1 -> 2032 | B34: =IF(A34=2025,$B$7,OFFSET(C34,-1,0)) -> 15302 | C34: =VLOOKUP(A34,$E$4:$F$14,2) -> 15843 | D34: =AVERAGE(B34,C34) -> 15572.5 | E34: =VLOOKUP(A34,$A$42:$L$52,12) -> 4313443.3 | F34: =D34*365*$B$4 -> 5399764.4 | G34: =E34/F34 -> 0.79882065 | I34: 0.89339518 | J34: 0.87381529 | K34: 0.83027763 | L34: 0.79882065
A35: =A34+1 -> 2033 | B35: =IF(A35=2025,$B$7,OFFSET(C35,-1,0)) -> 15843 | C35: =VLOOKUP(A35,$E$4:$F$14,2) -> 16403 | D35: =AVERAGE(B35,C35) -> 16123 | E35: =VLOOKUP(A35,$A$42:$L$52,12) -> 4363602 | F35: =D35*365*$B$4 -> 5590650.2 | G35: =E35/F35 -> 0.78051779 | I35: 0.8860303 | J35: 0.86406813 | K35: 0.81544068 | L35: 0.78051779
A36: =A35+1 -> 2034 | B36: =IF(A36=2025,$B$7,OFFSET(C36,-1,0)) -> 16403 | C36: =VLOOKUP(A36,$E$4:$F$14,2) -> 16983 | D36: =AVERAGE(B36,C36) -> 16693 | E36: =VLOOKUP(A36,$A$42:$L$52,12) -> 4408240.5 | F36: =D36*365*$B$4 -> 5788297.8 | G36: =E36/F36 -> 0.76157804 | I36: 0.87751663 | J36: 0.8532516 | K36: 0.79976235 | L36: 0.76157804
A37: =A36+1 -> 2035 | B37: =IF(A37=2025,$B$7,OFFSET(C37,-1,0)) -> 16983 | C37: =VLOOKUP(A37,$E$4:$F$14,2) -> 17583 | D37: =AVERAGE(B37,C37) -> 17283 | E37: =VLOOKUP(A37,$A$42:$L$52,12) -> 4447551.5 | F37: =D37*365*$B$4 -> 5992880.2 | G37: =E37/F37 -> 0.74213922 | I37: 0.86796767 | J37: 0.84148875 | K37: 0.78338681 | L37: 0.74213922
A39: Demand-Sid: Admissions & Bed Days
A40: Year | B40: 0-14 Years Old | E40: 15 - 64 Years Old | H40: 65 Years Old & Above | K40: Total Admits | L40: Total Bed-Day Demand
B41: Population | C41: Admits(HAR) | D41: Bed Days | E41: Population | F41: Admits(HAR) | G41: Bed Days | H41: Population | I41: Admits(HAR) | J41: Bed Days | N41: 2024 total cost per admission per day
A42: 2025 | B42: =SUM(INDEX('M1 Demand Driver'!$B$4:$L$7, , MATCH($A42, 'M1 Demand Driver'!$B$3:$L$3, 0))) -> 571940 | C42: =B42*INDEX('M2 HAR'!$B$45:$AE$45, MATCH($A42, 'M2 HAR'!$B$31:$AE$31, 0)) -> 79673.751 | D42: =C42*$B$17*(1+$B$10) -> 334629.75 | E42: =SUM(INDEX('M1 Demand Driver'!$B$8:$L$17, , MATCH($A42, 'M1 Demand Driver'!$B$3:$L$3, 0))) -> 2842999 | F42: =E42*INDEX('M2 HAR'!$B$46:$AE$46, MATCH($A42, 'M2 HAR'!$B$31:$AE$31, 0)) -> 256255.52 | G42: =F42*$B$18*(1+$B$10) -> 1383779.8 | H42: =SUM(INDEX('M1 Demand Driver'!$B$18:$L$23, , MATCH($A42, 'M1 Demand Driver'!$B$3:$L$3, 0)))*(1+$B$11) -> 789576 | I42: =H42*INDEX('M2 HAR'!$B$47:$AE$47, MATCH($A42, 'M2 HAR'!$B$31:$AE$31, 0)) -> 265998.99 | J42: =I42*$B$19*(1+$B$10) -> 2074792.2 | K42: =SUM(C42,F42,I42) -> 601928.26 | L42: =SUM(D42,G42,J42) -> 3793201.7 | N42: apply medical inflation
A43: =A42+1 -> 2026 | B43: =SUM(INDEX('M1 Demand Driver'!$B$4:$L$7, , MATCH($A43, 'M1 Demand Driver'!$B$3:$L$3, 0))) -> 557863.14 | C43: =B43*INDEX('M2 HAR'!$B$45:$AE$45, MATCH($A43, 'M2 HAR'!$B$31:$AE$31, 0)) -> 79109.74 | D43: =C43*$B$17*(1+$B$10) -> 332260.91 | E43: =SUM(INDEX('M1 Demand Driver'!$B$8:$L$17, , MATCH($A43, 'M1 Demand Driver'!$B$3:$L$3, 0))) -> 2820722.7 | F43: =E43*INDEX('M2 HAR'!$B$46:$AE$46, MATCH($A43, 'M2 HAR'!$B$31:$AE$31, 0)) -> 257432.87 | G43: =F43*$B$18*(1+$B$10) -> 1390137.5 | H43: =SUM(INDEX('M1 Demand Driver'!$B$18:$L$23, , MATCH($A43, 'M1 Demand Driver'!$B$3:$L$3, 0)))*(1+$B$11) -> 825848.54 | I43: =H43*INDEX('M2 HAR'!$B$47:$AE$47, MATCH($A43, 'M2 HAR'!$B$31:$AE$31, 0)) -> 277558.77 | J43: =I43*$B$19*(1+$B$10) -> 2164958.4 | K43: =SUM(C43,F43,I43) -> 614101.38 | L43: =SUM(D43,G43,J43) -> 3887356.8 | N43: 2025 - cost per admmission (with infaltion factor in)
A44: =A43+1 -> 2027 | B44: =SUM(INDEX('M1 Demand Driver'!$B$4:$L$7, , MATCH($A44, 'M1 Demand Driver'!$B$3:$L$3, 0))) -> 543392.38 | C44: =B44*INDEX('M2 HAR'!$B$45:$AE$45, MATCH($A44, 'M2 HAR'!$B$31:$AE$31, 0)) -> 78418.385 | D44: =C44*$B$17*(1+$B$10) -> 329357.22 | E44: =SUM(INDEX('M1 Demand Driver'!$B$8:$L$17, , MATCH($A44, 'M1 Demand Driver'!$B$3:$L$3, 0))) -> 2798784 | F44: =E44*INDEX('M2 HAR'!$B$46:$AE$46, MATCH($A44, 'M2 HAR'!$B$31:$AE$31, 0)) -> 258586.79 | G44: =F44*$B$18*(1+$B$10) -> 1396368.7 | H44: =SUM(INDEX('M1 Demand Driver'!$B$18:$L$23, , MATCH($A44, 'M1 Demand Driver'!$B$3:$L$3, 0)))*(1+$B$11) -> 859768.62 | I44: =H44*INDEX('M2 HAR'!$B$47:$AE$47, MATCH($A44, 'M2 HAR'!$B$31:$AE$31, 0)) -> 288269.64 | J44: =I44*$B$19*(1+$B$10) -> 2248503.2 | K44: =SUM(C44,F44,I44) -> 625274.82 | L44: =SUM(D44,G44,J44) -> 3974229.1 | N44: do it for every year until 2035
A45: =A44+1 -> 2028 | B45: =SUM(INDEX('M1 Demand Driver'!$B$4:$L$7, , MATCH($A45, 'M1 Demand Driver'!$B$3:$L$3, 0))) -> 529009.73 | C45: =B45*INDEX('M2 HAR'!$B$45:$AE$45, MATCH($A45, 'M2 HAR'!$B$31:$AE$31, 0)) -> 77667.492 | D45: =C45*$B$17*(1+$B$10) -> 326203.47 | E45: =SUM(INDEX('M1 Demand Driver'!$B$8:$L$17, , MATCH($A45, 'M1 Demand Driver'!$B$3:$L$3, 0))) -> 2776487.5 | F45: =E45*INDEX('M2 HAR'!$B$46:$AE$46, MATCH($A45, 'M2 HAR'!$B$31:$AE$31, 0)) -> 259652.38 | G45: =F45*$B$18*(1+$B$10) -> 1402122.9 | H45: =SUM(INDEX('M1 Demand Driver'!$B$18:$L$23, , MATCH($A45, 'M1 Demand Driver'!$B$3:$L$3, 0)))*(1+$B$11) -> 891569.58 | I45: =H45*INDEX('M2 HAR'!$B$47:$AE$47, MATCH($A45, 'M2 HAR'!$B$31:$AE$31, 0)) -> 298215.09 | J45: =I45*$B$19*(1+$B$10) -> 2326077.7 | K45: =SUM(C45,F45,I45) -> 635534.96 | L45: =SUM(D45,G45,J45) -> 4054404
A46: =A45+1 -> 2029 | B46: =SUM(INDEX('M1 Demand Driver'!$B$4:$L$7, , MATCH($A46, 'M1 Demand Driver'!$B$3:$L$3, 0))) -> 514988.22 | C46: =B46*INDEX('M2 HAR'!$B$45:$AE$45, MATCH($A46, 'M2 HAR'!$B$31:$AE$31, 0)) -> 76898.493 | D46: =C46*$B$17*(1+$B$10) -> 322973.67 | E46: =SUM(INDEX('M1 Demand Driver'!$B$8:$L$17, , MATCH($A46, 'M1 Demand Driver'!$B$3:$L$3, 0))) -> 2753437.4 | F46: =E46*INDEX('M2 HAR'!$B$46:$AE$46, MATCH($A46, 'M2 HAR'!$B$31:$AE$31, 0)) -> 260590.34 | G46: =F46*$B$18*(1+$B$10) -> 1407187.9 | H46: =SUM(INDEX('M1 Demand Driver'!$B$18:$L$23, , MATCH($A46, 'M1 Demand Driver'!$B$3:$L$3, 0)))*(1+$B$11) -> 921382.63 | I46: =H46*INDEX('M2 HAR'!$B$47:$AE$47, MATCH($A46, 'M2 HAR'!$B$31:$AE$31, 0)) -> 307443.83 | J46: =I46*$B$19*(1+$B$10) -> 2398061.9 | K46: =SUM(C46,F46,I46) -> 644932.67 | L46: =SUM(D46,G46,J46) -> 4128223.4 | N46: Metric | O46: 2025 | P46: 2026 | Q46: 2027 | R46: 2028 | S46: 2029 | T46: 2030 | U46: 2031 | V46: 2032 | W46: 2033 | X46: 2034 | Y46: 2035
A47: =A46+1 -> 2030 | B47: =SUM(INDEX('M1 Demand Driver'!$B$4:$L$7, , MATCH($A47, 'M1 Demand Driver'!$B$3:$L$3, 0))) -> 501475.21 | C47: =B47*INDEX('M2 HAR'!$B$45:$AE$45, MATCH($A47, 'M2 HAR'!$B$31:$AE$31, 0)) -> 76136.474 | D47: =C47*$B$17*(1+$B$10) -> 319773.19 | E47: =SUM(INDEX('M1 Demand Driver'!$B$8:$L$17, , MATCH($A47, 'M1 Demand Driver'!$B$3:$L$3, 0))) -> 2729419.4 | F47: =E47*INDEX('M2 HAR'!$B$46:$AE$46, MATCH($A47, 'M2 HAR'!$B$31:$AE$31, 0)) -> 261377.22 | G47: =F47*$B$18*(1+$B$10) -> 1411437 | H47: =SUM(INDEX('M1 Demand Driver'!$B$18:$L$23, , MATCH($A47, 'M1 Demand Driver'!$B$3:$L$3, 0)))*(1+$B$11) -> 949284.3 | I47: =H47*INDEX('M2 HAR'!$B$47:$AE$47, MATCH($A47, 'M2 HAR'!$B$31:$AE$31, 0)) -> 315986 | J47: =I47*$B$19*(1+$B$10) -> 2464690.8 | K47: =SUM(C47,F47,I47) -> 653499.69 | L47: =SUM(D47,G47,J47) -> 4195901 | N47: cost per admission every year * total number of admission = total admission cost
A48: =A47+1 -> 2031 | B48: =SUM(INDEX('M1 Demand Driver'!$B$4:$L$7, , MATCH($A48, 'M1 Demand Driver'!$B$3:$L$3, 0))) -> 488537.21 | C48: =B48*INDEX('M2 HAR'!$B$45:$AE$45, MATCH($A48, 'M2 HAR'!$B$31:$AE$31, 0)) -> 75395.519 | D48: =C48*$B$17*(1+$B$10) -> 316661.18 | E48: =SUM(INDEX('M1 Demand Driver'!$B$8:$L$17, , MATCH($A48, 'M1 Demand Driver'!$B$3:$L$3, 0))) -> 2704334.2 | F48: =E48*INDEX('M2 HAR'!$B$46:$AE$46, MATCH($A48, 'M2 HAR'!$B$31:$AE$31, 0)) -> 261999.85 | G48: =F48*$B$18*(1+$B$10) -> 1414799.2 | H48: =SUM(INDEX('M1 Demand Driver'!$B$18:$L$23, , MATCH($A48, 'M1 Demand Driver'!$B$3:$L$3, 0)))*(1+$B$11) -> 975326.17 | I48: =H48*INDEX('M2 HAR'!$B$47:$AE$47, MATCH($A48, 'M2 HAR'!$B$31:$AE$31, 0)) -> 323863.21 | J48: =I48*$B$19*(1+$B$10) -> 2526133.1 | K48: =SUM(C48,F48,I48) -> 661258.58 | L48: =SUM(D48,G48,J48) -> 4257593.4
A49: =A48+1 -> 2032 | B49: =SUM(INDEX('M1 Demand Driver'!$B$4:$L$7, , MATCH($A49, 'M1 Demand Driver'!$B$3:$L$3, 0))) -> 476190.58 | C49: =B49*INDEX('M2 HAR'!$B$45:$AE$45, MATCH($A49, 'M2 HAR'!$B$31:$AE$31, 0)) -> 74682.514 | D49: =C49*$B$17*(1+$B$10) -> 313666.56 | E49: =SUM(INDEX('M1 Demand Driver'!$B$8:$L$17, , MATCH($A49, 'M1 Demand Driver'!$B$3:$L$3, 0))) -> 2678152.9 | F49: =E49*INDEX('M2 HAR'!$B$46:$AE$46, MATCH($A49, 'M2 HAR'!$B$31:$AE$31, 0)) -> 262451.58 | G49: =F49*$B$18*(1+$B$10) -> 1417238.5 | H49: =SUM(INDEX('M1 Demand Driver'!$B$18:$L$23, , MATCH($A49, 'M1 Demand Driver'!$B$3:$L$3, 0)))*(1+$B$11) -> 999552.82 | I49: =H49*INDEX('M2 HAR'!$B$47:$AE$47, MATCH($A49, 'M2 HAR'!$B$31:$AE$31, 0)) -> 331094.64 | J49: =I49*$B$19*(1+$B$10) -> 2582538.2 | K49: =SUM(C49,F49,I49) -> 668228.73 | L49: =SUM(D49,G49,J49) -> 4313443.3
A50: =A49+1 -> 2033 | B50: =SUM(INDEX('M1 Demand Driver'!$B$4:$L$7, , MATCH($A50, 'M1 Demand Driver'!$B$3:$L$3, 0))) -> 464422.21 | C50: =B50*INDEX('M2 HAR'!$B$45:$AE$45, MATCH($A50, 'M2 HAR'!$B$31:$AE$31, 0)) -> 73999.812 | D50: =C50*$B$17*(1+$B$10) -> 310799.21 | E50: =SUM(INDEX('M1 Demand Driver'!$B$8:$L$17, , MATCH($A50, 'M1 Demand Driver'!$B$3:$L$3, 0))) -> 2650888.1 | F50: =E50*INDEX('M2 HAR'!$B$46:$AE$46, MATCH($A50, 'M2 HAR'!$B$31:$AE$31, 0)) -> 262729.75 | G50: =F50*$B$18*(1+$B$10) -> 1418740.6 | H50: =SUM(INDEX('M1 Demand Driver'!$B$18:$L$23, , MATCH($A50, 'M1 Demand Driver'!$B$3:$L$3, 0)))*(1+$B$11) -> 1022011.7 | I50: =H50*INDEX('M2 HAR'!$B$47:$AE$47, MATCH($A50, 'M2 HAR'!$B$31:$AE$31, 0)) -> 337700.27 | J50: =I50*$B$19*(1+$B$10) -> 2634062.1 | K50: =SUM(C50,F50,I50) -> 674429.83 | L50: =SUM(D50,G50,J50) -> 4363602
A51: =A50+1 -> 2034 | B51: =SUM(INDEX('M1 Demand Driver'!$B$4:$L$7, , MATCH($A51, 'M1 Demand Driver'!$B$3:$L$3, 0))) -> 453203.14 | C51: =B51*INDEX('M2 HAR'!$B$45:$AE$45, MATCH($A51, 'M2 HAR'!$B$31:$AE$31, 0)) -> 73347.072 | D51: =C51*$B$17*(1+$B$10) -> 308057.7 | E51: =SUM(INDEX('M1 Demand Driver'!$B$8:$L$17, , MATCH($A51, 'M1 Demand Driver'!$B$3:$L$3, 0))) -> 2622574.7 | F51: =E51*INDEX('M2 HAR'!$B$46:$AE$46, MATCH($A51, 'M2 HAR'!$B$31:$AE$31, 0)) -> 262834.04 | G51: =F51*$B$18*(1+$B$10) -> 1419303.8 | H51: =SUM(INDEX('M1 Demand Driver'!$B$18:$L$23, , MATCH($A51, 'M1 Demand Driver'!$B$3:$L$3, 0)))*(1+$B$11) -> 1042757.5 | I51: =H51*INDEX('M2 HAR'!$B$47:$AE$47, MATCH($A51, 'M2 HAR'!$B$31:$AE$31, 0)) -> 343702.43 | J51: =I51*$B$19*(1+$B$10) -> 2680878.9 | K51: =SUM(C51,F51,I51) -> 679883.54 | L51: =SUM(D51,G51,J51) -> 4408240.5
A52: =A51+1 -> 2035 | B52: =SUM(INDEX('M1 Demand Driver'!$B$4:$L$7, , MATCH($A52, 'M1 Demand Driver'!$B$3:$L$3, 0))) -> 442497.33 | C52: =B52*INDEX('M2 HAR'!$B$45:$AE$45, MATCH($A52, 'M2 HAR'!$B$31:$AE$31, 0)) -> 72722.496 | D52: =C52*$B$17*(1+$B$10) -> 305434.48 | E52: =SUM(INDEX('M1 Demand Driver'!$B$8:$L$17, , MATCH($A52, 'M1 Demand Driver'!$B$3:$L$3, 0))) -> 2593259.1 | F52: =E52*INDEX('M2 HAR'!$B$46:$AE$46, MATCH($A52, 'M2 HAR'!$B$31:$AE$31, 0)) -> 262765.53 | G52: =F52*$B$18*(1+$B$10) -> 1418933.9 | H52: =SUM(INDEX('M1 Demand Driver'!$B$18:$L$23, , MATCH($A52, 'M1 Demand Driver'!$B$3:$L$3, 0)))*(1+$B$11) -> 1061853.8 | I52: =H52*INDEX('M2 HAR'!$B$47:$AE$47, MATCH($A52, 'M2 HAR'!$B$31:$AE$31, 0)) -> 349126.05 | J52: =I52*$B$19*(1+$B$10) -> 2723183.2 | K52: =SUM(C52,F52,I52) -> 684614.07 | L52: =SUM(D52,G52,J52) -> 4447551.5
A54: ALOS Sensitivity Matrix | G54: Admissions Sensitivity Matrix
A55: ALOS Adjustment Factor | B55: Annual Bed Expansion Rate (%) | G55: 65+ Pop. Growth Adjust (%) | H55: Annual Bed Expansion Rate (%)
A56: =G37 -> 0.74213922 | B56: 0.02 | C56: 0.025 | D56: 0.03 | E56: 0.0353 | G56: =G37 -> 0.74213922 | H56: 0.02 | I56: 0.025 | J56: 0.03 | K56: 0.0353
A57: -0.1 | B57: 0.7811709 | C57: 0.74195796 | D57: 0.70504813 | E57: 0.6679253 | G57: -0.01 | H57: 0.8626532 | I57: 0.81935005 | J57: 0.77859022 | K57: 0.73759519
A58: -0.05 | B58: 0.82456928 | C58: 0.78317785 | D58: 0.74421747 | E58: 0.70503226 | G58: 0 | H58: 0.86796767 | I58: 0.82439774 | J58: 0.78338681 | K58: 0.74213922
A59: 0 | B59: 0.86796767 | C59: 0.82439774 | D59: 0.78338681 | E59: 0.74213922 | G59: 0.005 | H59: 0.8706249 | I59: 0.82692158 | J59: 0.7857851 | K59: 0.74441124
A60: 0.05 | B60: 0.91136605 | C60: 0.86561762 | D60: 0.82255615 | E60: 0.77924618 | G60: 0.01 | H60: 0.87328213 | I60: 0.82944543 | J60: 0.78818339 | K60: 0.74668325
A61: 0.1 | B61: 0.95476443 | C61: 0.90683751 | D61: 0.86172549 | E61: 0.81635315 | G61: 0.015 | H61: 0.87593936 | I61: 0.83196927 | J61: 0.79058168 | K61: 0.74895527
A63: Govt Policy Factor Sensitivity Matrix
A64: Healthier SG Efficiency Rate | B64: Annual Bed Expansion Rate (%)
A65: =G37 -> 0.74213922 | B65: 0.02 | C65: 0.025 | D65: 0.03 | E65: 0.0353
A66: -0.01 | B66: 0.84364321 | C66: 0.80129431 | D66: 0.76143269 | E66: 0.72134106
A67: =-0.6% -> -0.006 | B67: 0.86796767 | C67: 0.82439774 | D67: 0.78338681 | E67: 0.74213922
A68: 0 | B68: 0.90633856 | C68: 0.8608425 | D68: 0.81801857 | E68: 0.77494752
A69: 0.005 | B69: 0.94012126 | C69: 0.89292939 | D69: 0.84850925 | E69: 0.80383278
A70: 0.01 | B70: 0.97562717 | C70: 0.92665299 | D70: 0.88055522 | E70: 0.83419143

Sheet M2 Sensitivity Analysis
A1: BOR Influence Factors Summary
A2: The Annual Bed Expansion Rate has the largest absolute impact: cutting it from 3.53% to 2.00% increases BOR by 12.71 pp (from 74.21% to 86.80%). The BOR also jumped to over about 87%, breaching the safety threshold and risking patient care.
A3: Government Policy Factor has a strong positive impact: 1 pp efficiency gain raises BOR by ~5.5 pp. (-0.6% → 0%, BOR increases by ~3.3 pp)
A4: 65+ Pop. Growth Facor has a non-linear impact: reducing growth from 1.5% to 0% raises BOR by 0.68 pp
A5: ALOS Factor has a linear, moderate effect: a 10% ALOS reduction cuts BOR by ~5.5 pp.
A7: Summary
A8: Factor | B8: Scenario | C8: ΔBOR (pp)
A9: Annual Bed Expansion Rate | B9: 3.53% → 2.50% | C9: =D35-D33 -> -0.082258514
A10: ALOS Adjustment Factor | B10: 100% → 90% | C10: =E42-E40 -> 0.074213922
A11: 65+ Pop. Growth Adjust | B11: 1.5% → 0% | C11: =E53-E50 -> 0.006816046
A12: Government Policy Factor | B12: -0.6% → 0.0% | C12: =E59-E60 -> -0.032808298
A14: Single-Variable Sensitivity Analysis: Impact of ALOS
A15: ALOS Adjustment Factor | B15: 2035 BOR (Rate=3.53%)
A16: -8% (Average ALOS≈5.5) | B16: 0.68276809
A17: 0% (Average ALOS=6) | B17: 0.74213922
A18: 8% (Average ALOS≈6.5) | B18: 0.80151036
A19: 16% (Average ALOS≈7) | B19: 0.8608815
A20: 25% (Average ALOS≈7.5) | B20: 0.92767403
A22: Single-Variable Sensitivity Analysis: Impact of 65+ Pop. Growth Adjust
A23: 65+ Pop. Growth Adjust | B23: 2035 BOR (Rate=3.53%)
A24: -0.01 | B24: 0.73759519
A25: 0 | B25: 0.74213922
A26: 0.005 | B26: 0.74441124
A27: 0.01 | B27: 0.74668325
A28: 0.015 | B28: 0.74895527
A30: Single-Variable Sensitivity Analysis: Impact of Annual Bed Expansion Rate on Key BOR Metrics
A31: Annual Bed Expansion Rate | B31: 2025 BOR | C31: 2030 BOR | D31: 2035 BOR | E31: Average BOR | F31: First Warning Year | G31: First Redline Year
A32: 0.02 | B32: 0.90258237 | C32: 0.90421459 | D32: 0.86796767 | E32: 0.89667542 | F32: 2025 | G32: 2025
A33: 0.025 | B33: 0.90035377 | C33: 0.8800474 | D33: 0.82439774 | E33: 0.87304676 | F33: 2025 | G33: 2025
A34: 0.03 | B34: 0.89813615 | C34: 0.8568653 | D34: 0.78338681 | E34: 0.85049349 | F34: 2025 | G34: 2025
A35: 0.0353 | B35: 0.8957827 | C35: 0.83291931 | D35: 0.74213922 | E35: 0.82740489 | F35: 2025 | G35: 2025
A37: Two-Variable Sensitivity Analysis: Annual Bed Expansion Rate vs. ALOS Adjustment Factor (Link to BOR_Sensitivity Matrix)
A38: ALOS Adjustment Factor | B38: Annual Bed Expansion Rate (%)
A39: {='M2 BOR & Tradeoff analysis'!A56:E61} -> 0.74213922 | B39: 0.02 | C39: 0.025 | D39: 0.03 | E39: 0.0353
A40: -0.1 | B40: 0.7811709 | C40: 0.74195796 | D40: 0.70504813 | E40: 0.6679253
A41: -0.05 | B41: 0.82456928 | C41: 0.78317785 | D41: 0.74421747 | E41: 0.70503226
A42: 0 | B42: 0.86796767 | C42: 0.82439774 | D42: 0.78338681 | E42: 0.74213922
A43: 0.05 | B43: 0.91136605 | C43: 0.86561762 | D43: 0.82255615 | E43: 0.77924618
A44: 0.1 | B44: 0.95476443 | C44: 0.90683751 | D44: 0.86172549 | E44: 0.81635315
A46: Two-Variable Sensitivity Analysis: Annual Bed Expansion Rate vs. 65+ Pop. Growth Adjust (Link to BOR_Admissions Sensitivity Matrix)
A47: 65+ Pop. Growth Adjust (%) | B47: Annual Bed Expansion Rate (%)
A48: {='M2 BOR & Tradeoff analysis'!G56:K61} -> 0.74213922 | B48: 0.02 | C48: 0.025 | D48: 0.03 | E48: 0.0353
A49: -0.01 | B49: 0.8626532 | C49: 0.81935005 | D49: 0.77859022 | E49: 0.73759519
A50: 0 | B50: 0.86796767 | C50: 0.82439774 | D50: 0.78338681 | E50: 0.74213922
A51: 0.005 | B51: 0.8706249 | C51: 0.82692158 | D51: 0.7857851 | E51: 0.74441124
A52: 0.01 | B52: 0.87328213 | C52: 0.82944543 | D52: 0.78818339 | E52: 0.74668325
A53: 0.015 | B53: 0.87593936 | C53: 0.83196927 | D53: 0.79058168 | E53: 0.74895527
A55: Two-Variable Sensitivity Analysis: Annual Bed Expansion Rate vs. Government Policy Factor (Link to BOR_Govt Policy Factor Sensitivity Matrix)
A56: Government Policy Factor | B56: Annual Bed Expansion Rate (%)
A57: {='M2 BOR & Tradeoff analysis'!A65:E70} -> 0.74213922 | B57: 0.02 | C57: 0.025 | D57: 0.03 | E57: 0.0353
A58: -0.01 | B58: 0.84364321 | C58: 0.80129431 | D58: 0.76143269 | E58: 0.72134106
A59: -0.006 | B59: 0.86796767 | C59: 0.82439774 | D59: 0.78338681 | E59: 0.74213922
A60: 0 | B60: 0.90633856 | C60: 0.8608425 | D60: 0.81801857 | E60: 0.77494752
A61: 0.005 | B61: 0.94012126 | C61: 0.89292939 | D61: 0.84850925 | E61: 0.80383278
A62: 0.01 | B62: 0.97562717 | C62: 0.92665299 | D62: 0.88055522 | E62: 0.83419143

Sheet M3 Healthcare Budget
A1: Assumptions*
A2: % of Operating Expenditure on Health Spent on Public Hospitals | B2: 0.4
B3: Projected | L3: Historical
A4: Year | B4: 2035 | C4: 2034 | D4: 2033 | E4: 2032 | F4: 2031 | G4: 2030 | H4: 2029 | I4: 2028 | J4: 2027 | K4: 2026 | L4: 2025 | M4: 2024 | N4: 2023 | O4: 2022 | P4: 2021 | Q4: 2020 | R4: 2019 | S4: 2018 | T4: 2017 | U4: 2016 | V4: 2015 | W4: 2014 | X4: 2013 | Y4: 2012 | Z4: 2011 | AA4: 2010 | AB4: 2009 | AC4: 2008 | AD4: 2007 | AE4: 2006 | AF4: 2005
A5: Operating Expenditure On Health | B5: =FORECAST(B4,$L$5:$N$5,$L$4:$N$4) -> 32883.35 | C5: =FORECAST(C4,$L$5:$N$5,$L$4:$N$4) -> 31453.4 | D5: =FORECAST(D4,$L$5:$N$5,$L$4:$N$4) -> 30023.45 | E5: =FORECAST(E4,$L$5:$N$5,$L$4:$N$4) -> 28593.5 | F5: =FORECAST(F4,$L$5:$N$5,$L$4:$N$4) -> 27163.55 | G5: =FORECAST(G4,$L$5:$N$5,$L$4:$N$4) -> 25733.6 | H5: =FORECAST(H4,$L$5:$N$5,$L$4:$N$4) -> 24303.65 | I5: =FORECAST(I4,$L$5:$N$5,$L$4:$N$4) -> 22873.7 | ... K5: =FORECAST(K4,$L$5:$N$5,$L$4:$N$4) -> 20013.8 | L5: 18795.3 | M5: 16731 | N5: 15935.4 | O5: 15908.6 | P5: 16273.7 | Q5: 14310.6 | R5: 9914.8 | S5: 8937.4 | T5: 8734.4 | U5: 8199.4 | V5: 7519.8 | W5: 5872.4 | X5: 5043.9 | Y5: 4066.1 | Z5: 3488.8 | AA5: 3258 | AB5: 2920.2 | AC5: 2378.5 | AD5: 2019.5 | AE5: 1839.5 | AF5: 1680.4
A6: Operating Expenditure (Hospital) | B6: =$B$2*B5 -> 13153.34 | C6: =$B$2*C5 -> 12581.36 | D6: =$B$2*D5 -> 12009.38 | E6: =$B$2*E5 -> 11437.4 | F6: =$B$2*F5 -> 10865.42 | G6: =$B$2*G5 -> 10293.44 | H6: =$B$2*H5 -> 9721.46 | I6: =$B$2*I5 -> 9149.48 | ... AF6: =$B$2*AF5 -> 672.16
I13: `

Sheet M3 Healthcare Costs
A1: Medical Inflation
A3: Year (Historical, base year 2024) | B3: 2014 | C3: 2015 | D3: 2016 | E3: 2017 | F3: 2018 | G3: 2019 | H3: 2020 | I3: 2021 | J3: 2022 | K3: 2023 | L3: 2024 | M3: 2025
A4: Healthcare CPI | B4: 84.7 | C4: 84.6 | D4: 85.5 | E4: 87.6 | F4: 89.436 | G4: 90.5 | H4: 89.1 | I4: 90.1 | J4: 92.1 | K4: 96.2 | L4: 100 | M4: 102.7
A5: Inflation % | C5: =(C4-B4)/B4 -> -0.0011806375 | D5: =(D4-C4)/C4 -> 0.010638298 | E5: =(E4-D4)/D4 -> 0.024561404 | F5: =(F4-E4)/E4 -> 0.020958904 | G5: =(G4-F4)/F4 -> 0.011896775 | H5: =(H4-G4)/G4 -> -0.015469613 | I5: =(I4-H4)/H4 -> 0.011223345 | J5: =(J4-I4)/I4 -> 0.022197558 | ... M5: =(M4-L4)/L4 -> 0.027
A7: Year (Forecast) | B7: 2026 | C7: 2027 | D7: 2028 | E7: 2029 | F7: 2030 | G7: 2031 | H7: 2032 | I7: 2033 | J7: 2034 | K7: 2035
A8: Inflation % | B8: =FORECAST(B7,$C$5:$M$5,$C$3:$M$3) -> 0.035150772 | C8: =FORECAST(C7,$C$5:$M$5,$C$3:$M$3) -> 0.038041902 | D8: =FORECAST(D7,$C$5:$M$5,$C$3:$M$3) -> 0.040933032 | E8: =FORECAST(E7,$C$5:$M$5,$C$3:$M$3) -> 0.043824162 | F8: =FORECAST(F7,$C$5:$M$5,$C$3:$M$3) -> 0.046715292 | G8: =FORECAST(G7,$C$5:$M$5,$C$3:$M$3) -> 0.049606422 | H8: =FORECAST(H7,$C$5:$M$5,$C$3:$M$3) -> 0.052497552 | I8: =FORECAST(I7,$C$5:$M$5,$C$3:$M$3) -> 0.055388682 | ... K8: =FORECAST(K7,$C$5:$M$5,$C$3:$M$3) -> 0.061170942
A10: Government Cost Per Admission (Base = 2025), millions S$
A11: Bed Demand Days (M2) | B11: ='M2 BOR & Tradeoff analysis'!E27 -> 3793201.7
A12: Government operating expenditure on hospital | B12: ='M3 Healthcare Budget'!L6 -> 7518.12
A13: Government cost per admission day | B13: =B12/B11 -> 0.0019819985
A15: Projected Government Healthcare Costs (millions)
A16: Year | B16: 2026 | C16: 2027 | D16: 2028 | E16: 2029 | F16: 2030 | G16: 2031 | H16: 2032 | I16: 2033 | J16: 2034 | K16: 2035
A17: Bed Demand Days (M2) | B17: ='M2 BOR & Tradeoff analysis'!E28 -> 3887356.8 | C17: ='M2 BOR & Tradeoff analysis'!E29 -> 3974229.1 | D17: ='M2 BOR & Tradeoff analysis'!E30 -> 4054404 | E17: ='M2 BOR & Tradeoff analysis'!E31 -> 4128223.4 | F17: ='M2 BOR & Tradeoff analysis'!E32 -> 4195901 | G17: ='M2 BOR & Tradeoff analysis'!E33 -> 4257593.4 | H17: ='M2 BOR & Tradeoff analysis'!E34 -> 4313443.3 | I17: ='M2 BOR & Tradeoff analysis'!E35 -> 4363602 | J17: ='M2 BOR & Tradeoff analysis'!E36 -> 4408240.5 | K17: ='M2 BOR & Tradeoff analysis'!E37 -> 4447551.5
A18: Inflation | B18: =B8 -> 0.035150772 | C18: =C8 -> 0.038041902 | D18: =D8 -> 0.040933032 | E18: =E8 -> 0.043824162 | F18: =F8 -> 0.046715292 | G18: =G8 -> 0.049606422 | H18: =H8 -> 0.052497552 | I18: =I8 -> 0.055388682 | ... K18: =K8 -> 0.061170942
A19: Total | B19: =(B13*B17)*(1+B18) -> 7975.5627 | C19: =(B19/B17)*(1+C18)*C17 -> 8463.9816 | D19: =(C19/C17)*(1+D18)*D17 -> 8988.1771 | E19: =(D19/D17)*(1+E18)*E17 -> 9552.898 | F19: =(E19/E17)*(1+F18)*F17 -> 10163.089 | G19: =(F19/F17)*(1+G18)*G17 -> 10824.085 | H19: =(G19/G17)*(1+H18)*H17 -> 11541.764 | I19: =(H19/H17)*(1+I18)*I17 -> 12322.694 | J19: =(I19/I17)*(1+J18)*J17 -> 13174.262 | K19: =(J19/J17)*(1+K18)*K17 -> 14104.814

Sheet M3 Sensitivity Analysis
B1: One-Variable Sensitivity Analysis: Inflation Rate vs Healthcare Costs
B2: Admissions held constant per year. | G2: `
B3: Base Year | C3: 2025
B4: Demand (M2) | C4: ='M2 BOR & Tradeoff analysis'!E27 -> 3793201.7
B5: Cost per Admission | C5: ='M3 Healthcare Costs'!B13 -> 0.0019819985
B7: Inflation Rate | C7: 2025 | D7: 2026 | E7: 2027 | F7: 2028 | G7: 2029 | H7: 2030 | I7: 2031 | J7: 2032 | K7: 2033 | L7: 2034 | M7: 2035
B8: 0.01 | C8: =$C$10 -> 7518.12 | D8: =$C$4*$C$5*(1+$B8)^1 -> 7593.3012 | E8: =$C$4*$C$5*(1+$B8)^2 -> 7669.2342 | F8: =$C$4*$C$5*(1+$B8)^3 -> 7745.9266 | G8: =$C$4*$C$5*(1+$B8)^4 -> 7823.3858 | H8: =$C$4*$C$5*(1+$B8)^5 -> 7901.6197 | I8: =$C$4*$C$5*(1+$B8)^6 -> 7980.6359 | J8: =$C$4*$C$5*(1+$B8)^7 -> 8060.4422 | K8: =$C$4*$C$5*(1+$B8)^8 -> 8141.0467 | L8: =$C$4*$C$5*(1+$B8)^9 -> 8222.4571 | M8: =$C$4*$C$5*(1+$B8)^10 -> 8304.6817
B9: 0.02 | C9: =$C$10 -> 7518.12 | D9: =$C$4*$C$5*(1+$B9)^1 -> 7668.4824 | E9: =$C$4*$C$5*(1+$B9)^2 -> 7821.852 | F9: =$C$4*$C$5*(1+$B9)^3 -> 7978.2891 | G9: =$C$4*$C$5*(1+$B9)^4 -> 8137.8549 | H9: =$C$4*$C$5*(1+$B9)^5 -> 8300.612 | I9: =$C$4*$C$5*(1+$B9)^6 -> 8466.6242 | J9: =$C$4*$C$5*(1+$B9)^7 -> 8635.9567 | K9: =$C$4*$C$5*(1+$B9)^8 -> 8808.6758 | L9: =$C$4*$C$5*(1+$B9)^9 -> 8984.8493 | M9: =$C$4*$C$5*(1+$B9)^10 -> 9164.5463
B10: 0.027 | C10: ='M3 Healthcare Budget'!L6 -> 7518.12 | D10: =$C$4*$C$5*(1+$B10)^1 -> 7721.1092 | E10: =$C$4*$C$5*(1+$B10)^2 -> 7929.5792 | F10: =$C$4*$C$5*(1+$B10)^3 -> 8143.6778 | G10: =$C$4*$C$5*(1+$B10)^4 -> 8363.5571 | H10: =$C$4*$C$5*(1+$B10)^5 -> 8589.3732 | I10: =$C$4*$C$5*(1+$B10)^6 -> 8821.2862 | J10: =$C$4*$C$5*(1+$B10)^7 -> 9059.461 | K10: =$C$4*$C$5*(1+$B10)^8 -> 9304.0664 | L10: =$C$4*$C$5*(1+$B10)^9 -> 9555.2762 | M10: =$C$4*$C$5*(1+$B10)^10 -> 9813.2687
B11: 0.03 | C11: =$C$10 -> 7518.12 | D11: =$C$4*$C$5*(1+$B11)^1 -> 7743.6636 | E11: =$C$4*$C$5*(1+$B11)^2 -> 7975.9735 | F11: =$C$4*$C$5*(1+$B11)^3 -> 8215.2527 | G11: =$C$4*$C$5*(1+$B11)^4 -> 8461.7103 | H11: =$C$4*$C$5*(1+$B11)^5 -> 8715.5616 | I11: =$C$4*$C$5*(1+$B11)^6 -> 8977.0285 | J11: =$C$4*$C$5*(1+$B11)^7 -> 9246.3393 | K11: =$C$4*$C$5*(1+$B11)^8 -> 9523.7295 | L11: =$C$4*$C$5*(1+$B11)^9 -> 9809.4414 | M11: =$C$4*$C$5*(1+$B11)^10 -> 10103.725
B12: 0.04 | C12: =$C$10 -> 7518.12 | D12: =$C$4*$C$5*(1+$B12)^1 -> 7818.8448 | E12: =$C$4*$C$5*(1+$B12)^2 -> 8131.5986 | F12: =$C$4*$C$5*(1+$B12)^3 -> 8456.8625 | G12: =$C$4*$C$5*(1+$B12)^4 -> 8795.137 | H12: =$C$4*$C$5*(1+$B12)^5 -> 9146.9425 | I12: =$C$4*$C$5*(1+$B12)^6 -> 9512.8202 | J12: =$C$4*$C$5*(1+$B12)^7 -> 9893.333 | K12: =$C$4*$C$5*(1+$B12)^8 -> 10289.066 | L12: =$C$4*$C$5*(1+$B12)^9 -> 10700.629 | M12: =$C$4*$C$5*(1+$B12)^10 -> 11128.654
B13: 0.05 | C13: =$C$10 -> 7518.12 | D13: =$C$4*$C$5*(1+$B13)^1 -> 7894.026 | E13: =$C$4*$C$5*(1+$B13)^2 -> 8288.7273 | F13: =$C$4*$C$5*(1+$B13)^3 -> 8703.1637 | G13: =$C$4*$C$5*(1+$B13)^4 -> 9138.3218 | H13: =$C$4*$C$5*(1+$B13)^5 -> 9595.2379 | I13: =$C$4*$C$5*(1+$B13)^6 -> 10075 | J13: =$C$4*$C$5*(1+$B13)^7 -> 10578.75 | K13: =$C$4*$C$5*(1+$B13)^8 -> 11107.687 | L13: =$C$4*$C$5*(1+$B13)^9 -> 11663.072 | M13: =$C$4*$C$5*(1+$B13)^10 -> 12246.225
B14: 0.06 | C14: =$C$10 -> 7518.12 | D14: =$C$4*$C$5*(1+$B14)^1 -> 7969.2072 | E14: =$C$4*$C$5*(1+$B14)^2 -> 8447.3596 | F14: =$C$4*$C$5*(1+$B14)^3 -> 8954.2012 | G14: =$C$4*$C$5*(1+$B14)^4 -> 9491.4533 | H14: =$C$4*$C$5*(1+$B14)^5 -> 10060.94 | I14: =$C$4*$C$5*(1+$B14)^6 -> 10664.597 | J14: =$C$4*$C$5*(1+$B14)^7 -> 11304.473 | K14: =$C$4*$C$5*(1+$B14)^8 -> 11982.741 | L14: =$C$4*$C$5*(1+$B14)^9 -> 12701.706 | M14: =$C$4*$C$5*(1+$B14)^10 -> 13463.808
B15: 0.07 | C15: =$C$10 -> 7518.12 | D15: =$C$4*$C$5*(1+$B15)^1 -> 8044.3884 | E15: =$C$4*$C$5*(1+$B15)^2 -> 8607.4956 | F15: =$C$4*$C$5*(1+$B15)^3 -> 9210.0203 | G15: =$C$4*$C$5*(1+$B15)^4 -> 9854.7217 | H15: =$C$4*$C$5*(1+$B15)^5 -> 10544.552 | I15: =$C$4*$C$5*(1+$B15)^6 -> 11282.671 | J15: =$C$4*$C$5*(1+$B15)^7 -> 12072.458 | K15: =$C$4*$C$5*(1+$B15)^8 -> 12917.53 | L15: =$C$4*$C$5*(1+$B15)^9 -> 13821.757 | M15: =$C$4*$C$5*(1+$B15)^10 -> 14789.28
B16: 0.08 | C16: =$C$10 -> 7518.12 | D16: =$C$4*$C$5*(1+$B16)^1 -> 8119.5696 | E16: =$C$4*$C$5*(1+$B16)^2 -> 8769.1352 | F16: =$C$4*$C$5*(1+$B16)^3 -> 9470.666 | G16: =$C$4*$C$5*(1+$B16)^4 -> 10228.319 | H16: =$C$4*$C$5*(1+$B16)^5 -> 11046.585 | I16: =$C$4*$C$5*(1+$B16)^6 -> 11930.312 | J16: =$C$4*$C$5*(1+$B16)^7 -> 12884.737 | K16: =$C$4*$C$5*(1+$B16)^8 -> 13915.515 | L16: =$C$4*$C$5*(1+$B16)^9 -> 15028.757 | M16: =$C$4*$C$5*(1+$B16)^10 -> 16231.057
B18: Two-Variable Sensitivity Analysis: Elderly Cost Multiplier & Inflation Rate vs Healthcare Costs
B19: Base Year | C19: 2025
B20: Cost per Admission | C20: =C5 -> 0.0019819985
B21: Inflation Rate | C21: ='M3 Healthcare Costs'!M5 -> 0.027
B23: Admissions Numbers (M1, M2) | C23: 2025 | D23: 2030 | E23: 2035 | F23: Cost Multiplier
B24: Age 0–14 | C24: =SUM('M1 Demand Driver'!B4:B7)*'M2 HAR'!L45 -> 79673.751 | D24: =SUM('M1 Demand Driver'!G4:G7)*'M2 HAR'!G45 -> 76136.474 | E24: =SUM('M1 Demand Driver'!L4:L7)*'M2 HAR'!B45 -> 72722.496 | F24: 1
B25: Age 15–64 | C25: =SUM('M1 Demand Driver'!B8:B17)*'M2 HAR'!L46 -> 256255.52 | D25: =SUM('M1 Demand Driver'!G8:G17)*'M2 HAR'!G46 -> 261377.22 | E25: =SUM('M1 Demand Driver'!L8:L17)*'M2 HAR'!B46 -> 262765.53 | F25: 1
B26: Age 65+ | C26: =SUM('M1 Demand Driver'!B18:B23)*'M2 HAR'!L47 -> 265998.99 | D26: =SUM('M1 Demand Driver'!G18:G23)*'M2 HAR'!G47 -> 315986 | E26: =SUM('M1 Demand Driver'!L18:L23)*'M2 HAR'!B47 -> 349126.05 | F26: 2.5 (max)
B28: Base Year 2025
B29: Elderly Cost Multiplier | C29: Total Cost
B30: 1 | C30: =(C$24*$C$20)*$F$24+(C$25*$C$20)*$F$25+(C$26*$C$20)*B30 -> 1193.0209
B31: 1.5 | C31: =(C$24*$C$20)*$F$24+(C$25*$C$20)*$F$25+(C$26*$C$20)*B31 -> 1456.6257
B32: 2 | C32: =(C$24*$C$20)*$F$24+(C$25*$C$20)*$F$25+(C$26*$C$20)*B32 -> 1720.2305
B33: 2.5 | C33: =(C$24*$C$20)*$F$24+(C$25*$C$20)*$F$25+(C$26*$C$20)*B33 -> 1983.8353
B35: 2030
B36: Elderly Cost Multiplier / Inflation Rate | C36: =C21 -> 0.027 | D36: 0.03 | E36: 0.04 | F36: 0.05 | G36: 0.06 | H36: 0.07 | I36: 0.08
B37: =B30 -> 1 | C37: =C30*(1+$C$21)^5 -> 1363.0139 | D37: =$C$30*(1+D$36)^5 -> 1383.0382 | E37: =$C$30*(1+E$36)^5 -> 1451.4923 | F37: =$C$30*(1+F$36)^5 -> 1522.6306 | G37: =$C$30*(1+G$36)^5 -> 1596.5311 | H37: =$C$30*(1+H$36)^5 -> 1673.2735 | I37: =$C$30*(1+I$36)^5 -> 1752.9391
B38: =B31 -> 1.5 | C38: =C31*(1+$C$21)^5 -> 1664.1796 | D38: =$C$31*(1+D$36)^5 -> 1688.6284 | E38: =$C$31*(1+E$36)^5 -> 1772.2079 | F38: =$C$31*(1+F$36)^5 -> 1859.0645 | G38: =$C$31*(1+G$36)^5 -> 1949.2938 | H38: =$C$31*(1+H$36)^5 -> 2042.9929 | I38: =$C$31*(1+I$36)^5 -> 2140.261
B39: =B32 -> 2 | C39: =C32*(1+$C$21)^5 -> 1965.3453 | D39: =$C$32*(1+D$36)^5 -> 1994.2186 | E39: =$C$32*(1+E$36)^5 -> 2092.9234 | F39: =$C$32*(1+F$36)^5 -> 2195.4985 | G39: =$C$32*(1+G$36)^5 -> 2302.0565 | H39: =$C$32*(1+H$36)^5 -> 2412.7123 | I39: =$C$32*(1+I$36)^5 -> 2527.583
B40: =B33 -> 2.5 | C40: =C33*(1+$C$21)^5 -> 2266.511 | D40: =$C$33*(1+D$36)^5 -> 2299.8088 | E40: =$C$33*(1+E$36)^5 -> 2413.639 | F40: =$C$33*(1+F$36)^5 -> 2531.9324 | G40: =$C$33*(1+G$36)^5 -> 2654.8191 | H40: =$C$33*(1+H$36)^5 -> 2782.4316 | I40: =$C$33*(1+I$36)^5 -> 2914.9049
B42: 2035
B43: Elderly Cost Multiplier / Inflation Rate | C43: =C21 -> 0.027 | D43: 0.03 | E43: 0.04 | F43: 0.05 | G43: 0.06 | H43: 0.07 | I43: 0.08
B44: =B30 -> 1 | C44: =C30*(1+$C$21)^10 -> 1557.229 | D44: =$C$30*(1+D$36)^10 -> 1603.3203 | E44: =$C$30*(1+E$36)^10 -> 1765.9624 | F44: =$C$30*(1+F$36)^10 -> 1943.3053 | G44: =$C$30*(1+G$36)^10 -> 2136.5187 | H44: =$C$30*(1+H$36)^10 -> 2346.8527 | I44: =$C$30*(1+I$36)^10 -> 2575.6426
B45: =B31 -> 1.5 | C45: =C31*(1+$C$21)^10 -> 1901.3077 | D45: =$C$31*(1+D$36)^10 -> 1957.5831 | E45: =$C$31*(1+E$36)^10 -> 2156.1619 | F45: =$C$31*(1+F$36)^10 -> 2372.6898 | G45: =$C$31*(1+G$36)^10 -> 2608.5948 | H45: =$C$31*(1+H$36)^10 -> 2865.4032 | I45: =$C$31*(1+I$36)^10 -> 3144.7456
B46: =B32 -> 2 | C46: =C32*(1+$C$21)^10 -> 2245.3864 | D46: =$C$32*(1+D$36)^10 -> 2311.8459 | E46: =$C$32*(1+E$36)^10 -> 2546.3614 | F46: =$C$32*(1+F$36)^10 -> 2802.0742 | G46: =$C$32*(1+G$36)^10 -> 3080.6708 | H46: =$C$32*(1+H$36)^10 -> 3383.9538 | I46: =$C$32*(1+I$36)^10 -> 3713.8486
B47: =B33 -> 2.5 | C47: =C33*(1+$C$21)^10 -> 2589.465 | D47: =$C$33*(1+D$36)^10 -> 2666.1088 | E47: =$C$33*(1+E$36)^10 -> 2936.5609 | F47: =$C$33*(1+F$36)^10 -> 3231.4587 | G47: =$C$33*(1+G$36)^10 -> 3552.7469 | H47: =$C$33*(1+H$36)^10 -> 3902.5043 | I47: =$C$33*(1+I$36)^10 -> 4282.9516

Sheet M4 Household data
A1: Household size in singapore 2000-2025
A2: DataSeries | B2: 2035 | C2: 2034 | D2: 2033 | E2: 2032 | F2: 2031 | G2: 2030 | H2: 2029 | I2: 2028 | J2: 2027 | K2: 2026 | L2: 2025 | M2: 2024 | N2: 2023 | O2: 2022 | P2: 2021 | Q2: 2020 | R2: 2019 | S2: 2018 | T2: 2017 | U2: 2016 | V2: 2015 | W2: 2014 | X2: 2013 | Y2: 2012 | Z2: 2011 | AA2: 2010 | AB2: 2009 | AC2: 2008 | AD2: 2007 | AE2: 2006 | AF2: 2005 | AG2: 2004 | AH2: 2003 | AI2: 2002 | AJ2: 2001 | AK2: 2000
A3: Projection Assumption: Resident Households grow at 1.6% p.a (recent trend 2020-2025) | Avg Household Size declines at -0.026 p.a (historic trend 2000-2025)
A4: Resident Households | B4: =C4*1.016 -> 1742919.2 | C4: =D4*1.016 -> 1715471.6 | D4: =E4*1.016 -> 1688456.3 | E4: =F4*1.016 -> 1661866.5 | F4: =G4*1.016 -> 1635695.4 | G4: =H4*1.016 -> 1609936.4 | H4: =I4*1.016 -> 1584583 | I4: =J4*1.016 -> 1559629 | ... K4: =L4*1.016 -> 1510893.6 | L4: 1487100 | M4: 1463400 | N4: 1425100 | O4: 1399600 | P4: 1390600 | Q4: 1372600 | R4: 1372400 | S4: 1325300 | T4: 1289900 | U4: 1263600 | V4: 1225300 | W4: 1200000 | X4: 1174500 | Y4: 1152000 | Z4: 1146200 | AA4: 1145900 | AB4: 1119600 | AC4: 1093100 | AD4: 1074800 | AE4: 1054100 | AF4: 1024500 | AG4: 1003800 | AH4: 989000 | AI4: 964600 | AJ4: 934400 | AK4: 915100
A5: 1-Person Households | B5: =C5*1.016 -> 290545.13 | C5: =D5*1.016 -> 285969.62 | D5: =E5*1.016 -> 281466.16 | E5: =F5*1.016 -> 277033.62 | F5: =G5*1.016 -> 272670.89 | G5: =H5*1.016 -> 268376.86 | H5: =I5*1.016 -> 264150.45 | I5: =J5*1.016 -> 259990.6 | ... K5: =L5*1.016 -> 251866.4 | L5: 247900 | M5: 236200 | N5: 222700 | O5: 217300 | P5: 217400 | Q5: 220300 | R5: 208000 | S5: 185400 | T5: 167900 | U5: 156200 | V5: 146000 | W5: 134800 | X5: 124400 | Y5: 109500 | Z5: 114000 | AA5: 139900 | AB5: 115700 | AC5: 109700 | AD5: 116400 | AE5: 112500 | AF5: 103300 | AG5: 96300 | AH5: 94800 | AI5: 82700 | AJ5: 73200 | AK5: 75400
A6: 2-Person Households | B6: =C6*1.016 -> 415131.45 | C6: =D6*1.016 -> 408593.95 | D6: =E6*1.016 -> 402159.4 | E6: =F6*1.016 -> 395826.18 | F6: =G6*1.016 -> 389592.69 | G6: =H6*1.016 -> 383457.38 | H6: =I6*1.016 -> 377418.68 | I6: =J6*1.016 -> 371475.08 | ... K6: =L6*1.016 -> 359867.2 | L6: 354200 | M6: 343700 | N6: 344200 | O6: 331300 | P6: 331200 | Q6: 309800 | R6: 334400 | S6: 306300 | T6: 289200 | U6: 276100 | V6: 259200 | W6: 252200 | X6: 234100 | Y6: 230900 | Z6: 227900 | AA6: 215000 | AB6: 219400 | AC6: 214300 | AD6: 204600 | AE6: 207600 | AF6: 191200 | AG6: 193000 | AH6: 190500 | AI6: 181400 | AJ6: 173700 | AK6: 157200
A7: 3-Person Households | B7: =C7*1.016 -> 393566.18 | C7: =D7*1.016 -> 387368.29 | D7: =E7*1.016 -> 381268 | E7: =F7*1.016 -> 375263.78 | F7: =G7*1.016 -> 369354.11 | G7: =H7*1.016 -> 363537.51 | H7: =I7*1.016 -> 357812.51 | I7: =J7*1.016 -> 352177.67 | ... K7: =L7*1.016 -> 341172.8 | L7: 335800 | M7: 335000 | N7: 315500 | O7: 329300 | P7: 297500 | Q7: 280500 | R7: 286400 | S7: 276900 | T7: 277000 | U7: 266200 | V7: 256200 | W7: 251500 | X7: 243700 | Y7: 238300 | Z7: 237100 | AA7: 231400 | AB7: 234300 | AC7: 227200 | AD7: 223300 | AE7: 217500 | AF7: 206000 | AG7: 206800 | AH7: 201300 | AI7: 205700 | AJ7: 188300 | AK7: 175100
A8: 4-Person Households | B8: =C8*1.016 -> 347622.78 | C8: =D8*1.016 -> 342148.4 | D8: =E8*1.016 -> 336760.24 | E8: =F8*1.016 -> 331456.93 | F8: =G8*1.016 -> 326237.13 | G8: =H8*1.016 -> 321099.54 | H8: =I8*1.016 -> 316042.86 | I8: =J8*1.016 -> 311065.8 | ... K8: =L8*1.016 -> 301345.6 | L8: 296600 | M8: 294900 | N8: 287100 | O8: 287100 | P8: 279100 | Q8: 275600 | R8: 283500 | S8: 284500 | T8: 278100 | U8: 286200 | V8: 282200 | W8: 280100 | X8: 290900 | Y8: 281100 | Z8: 279600 | AA8: 263900 | AB8: 271300 | AC8: 268200 | AD8: 262900 | AE8: 258000 | AF8: 247300 | AG8: 250300 | AH8: 249600 | AI8: 242200 | AJ8: 242200 | AK8: 233400
A9: 5-Person Households | B9: =C9*1.016 -> 189399.33 | C9: =D9*1.016 -> 186416.66 | D9: =E9*1.016 -> 183480.97 | E9: =F9*1.016 -> 180591.5 | F9: =G9*1.016 -> 177747.54 | G9: =H9*1.016 -> 174948.37 | H9: =I9*1.016 -> 172193.28 | I9: =J9*1.016 -> 169481.57 | ... K9: =L9*1.016 -> 164185.6 | L9: 161600 | M9: 161800 | N9: 156500 | O9: 147500 | P9: 160900 | Q9: 163500 | R9: 155100 | S9: 160700 | T9: 161400 | U9: 161200 | V9: 164000 | W9: 162900 | X9: 165500 | Y9: 170500 | Z9: 169700 | AA9: 168000 | AB9: 164500 | AC9: 163700 | AD9: 166100 | AE9: 160300 | AF9: 163100 | AG9: 160200 | AH9: 155500 | AI9: 162700 | AJ9: 163200 | AK9: 163700
A10: 6-Person Households Or Larger | B10: =C10*1.016 -> 106654.33 | C10: =D10*1.016 -> 104974.73 | D10: =E10*1.016 -> 103321.58 | E10: =F10*1.016 -> 101694.47 | F10: =G10*1.016 -> 100092.98 | G10: =H10*1.016 -> 98516.717 | H10: =I10*1.016 -> 96965.273 | I10: =J10*1.016 -> 95438.261 | ... K10: =L10*1.016 -> 92456 | L10: 91000 | M10: 91900 | N10: 99200 | O10: 87100 | P10: 104400 | Q10: 122900 | R10: 104900 | S10: 111600 | T10: 116300 | U10: 117600 | V10: 117600 | W10: 118400 | X10: 116000 | Y10: 121800 | Z10: 117900 | AA10: 127800 | AB10: 114400 | AC10: 110200 | AD10: 101400 | AE10: 98200 | AF10: 113600 | AG10: 97200 | AH10: 97100 | AI10: 89900 | AJ10: 93800 | AK10: 110200
A11: Average Household Size Among Resident Households | B11: =MAX(C11-0.026,2.5) -> 2.8 | C11: =MAX(D11-0.026,2.5) -> 2.826 | D11: =MAX(E11-0.026,2.5) -> 2.852 | E11: =MAX(F11-0.026,2.5) -> 2.878 | F11: =MAX(G11-0.026,2.5) -> 2.904 | G11: =MAX(H11-0.026,2.5) -> 2.93 | H11: =MAX(I11-0.026,2.5) -> 2.956 | I11: =MAX(J11-0.026,2.5) -> 2.982 | ... K11: =MAX(L11-0.026,2.5) -> 3.034 | L11: 3.06 | M11: 3.09 | N11: 3.11 | O11: 3.09 | P11: 3.15 | Q11: 3.22 | R11: 3.16 | S11: 3.24 | T11: 3.3 | U11: 3.35 | V11: 3.39 | W11: 3.43 | X11: 3.47 | Y11: 3.53 | Z11: 3.51 | AA11: 3.5 | AB11: 3.49 | AC11: 3.5 | AD11: 3.48 | AE11: 3.46 | AF11: 3.56 | AG11: 3.52 | AH11: 3.52 | AI11: 3.55 | AJ11: 3.61 | AK11: 3.7
A12: Total HDB Dwellings | B12: =MAX(C12-0.026,1.5) -> 2.72 | C12: =MAX(D12-0.026,1.5) -> 2.746 | D12: =MAX(E12-0.026,1.5) -> 2.772 | E12: =MAX(F12-0.026,1.5) -> 2.798 | F12: =MAX(G12-0.026,1.5) -> 2.824 | G12: =MAX(H12-0.026,1.5) -> 2.85 | H12: =MAX(I12-0.026,1.5) -> 2.876 | I12: =MAX(J12-0.026,1.5) -> 2.902 | ... K12: =MAX(L12-0.026,1.5) -> 2.954 | L12: 2.98 | M12: 3.01 | N12: 3.04 | O12: 3.02 | P12: 3.09 | Q12: 3.13 | R12: 3.07 | S12: 3.18 | T12: 3.25 | U12: 3.3 | V12: 3.34 | W12: 3.37 | X12: 3.42 | Y12: 3.48 | Z12: 3.46 | AA12: 3.45 | AB12: 3.45 | AC12: 3.45 | AD12: 3.44 | AE12: 3.43 | AF12: 3.51 | AG12: 3.46 | AH12: 3.47 | AI12: 3.51 | AJ12: 3.57 | AK12: 3.66
A13: HDB 1- And 2-Room Flats | B13: =MAX(C13-0.026,1.5) -> 1.66 | C13: =MAX(D13-0.026,1.5) -> 1.686 | D13: =MAX(E13-0.026,1.5) -> 1.712 | E13: =MAX(F13-0.026,1.5) -> 1.738 | F13: =MAX(G13-0.026,1.5) -> 1.764 | G13: =MAX(H13-0.026,1.5) -> 1.79 | H13: =MAX(I13-0.026,1.5) -> 1.816 | I13: =MAX(J13-0.026,1.5) -> 1.842 | ... K13: =MAX(L13-0.026,1.5) -> 1.894 | L13: 1.92 | M13: 1.92 | N13: 1.99 | O13: 2.05 | P13: 2.01 | Q13: 2.09 | R13: 2.02 | S13: 2.08 | T13: 2.19 | U13: 2.16 | V13: 2.24 | W13: 2.32 | X13: 2.38 | Y13: 2.36 | Z13: 2.24 | AA13: 2.11 | AB13: 2.12 | AC13: 2.09 | AD13: 2.01 | AE13: 2 | AF13: 2.04 | AG13: 2.04 | AH13: 1.96 | AI13: 2.07 | AJ13: 2.19 | AK13: 2.2
A14: HDB 3-Room Flats | B14: =MAX(C14-0.026,1.5) -> 2.17 | C14: =MAX(D14-0.026,1.5) -> 2.196 | D14: =MAX(E14-0.026,1.5) -> 2.222 | E14: =MAX(F14-0.026,1.5) -> 2.248 | F14: =MAX(G14-0.026,1.5) -> 2.274 | G14: =MAX(H14-0.026,1.5) -> 2.3 | H14: =MAX(I14-0.026,1.5) -> 2.326 | I14: =MAX(J14-0.026,1.5) -> 2.352 | ... K14: =MAX(L14-0.026,1.5) -> 2.404 | L14: 2.43 | M14: 2.45 | N14: 2.49 | O14: 2.46 | P14: 2.48 | Q14: 2.54 | R14: 2.5 | S14: 2.58 | T14: 2.63 | U14: 2.67 | V14: 2.69 | W14: 2.7 | X14: 2.74 | Y14: 2.79 | Z14: 2.77 | AA14: 2.78 | AB14: 2.77 | AC14: 2.77 | AD14: 2.76 | AE14: 2.77 | AF14: 2.8 | AG14: 2.81 | AH14: 2.85 | AI14: 2.93 | AJ14: 3.01 | AK14: 3.11
A15: HDB 4-Room Flats | B15: =MAX(C15-0.026,1.5) -> 2.9 | C15: =MAX(D15-0.026,1.5) -> 2.926 | D15: =MAX(E15-0.026,1.5) -> 2.952 | E15: =MAX(F15-0.026,1.5) -> 2.978 | F15: =MAX(G15-0.026,1.5) -> 3.004 | G15: =MAX(H15-0.026,1.5) -> 3.03 | H15: =MAX(I15-0.026,1.5) -> 3.056 | I15: =MAX(J15-0.026,1.5) -> 3.082 | ... K15: =MAX(L15-0.026,1.5) -> 3.134 | L15: 3.16 | M15: 3.18 | N15: 3.17 | O15: 3.15 | P15: 3.27 | Q15: 3.29 | R15: 3.22 | S15: 3.34 | T15: 3.42 | U15: 3.46 | V15: 3.49 | W15: 3.53 | X15: 3.58 | Y15: 3.63 | Z15: 3.65 | AA15: 3.66 | AB15: 3.66 | AC15: 3.66 | AD15: 3.65 | AE15: 3.69 | AF15: 3.76 | AG15: 3.73 | AH15: 3.75 | AI15: 3.75 | AJ15: 3.87 | AK15: 3.95
A16: HDB 5-Room And Executive Flats | B16: =MAX(C16-0.026,1.5) -> 3.22 | C16: =MAX(D16-0.026,1.5) -> 3.246 | D16: =MAX(E16-0.026,1.5) -> 3.272 | E16: =MAX(F16-0.026,1.5) -> 3.298 | F16: =MAX(G16-0.026,1.5) -> 3.324 | G16: =MAX(H16-0.026,1.5) -> 3.35 | H16: =MAX(I16-0.026,1.5) -> 3.376 | I16: =MAX(J16-0.026,1.5) -> 3.402 | ... K16: =MAX(L16-0.026,1.5) -> 3.454 | L16: 3.48 | M16: 3.56 | N16: 3.6 | O16: 3.56 | P16: 3.63 | Q16: 3.67 | R16: 3.58 | S16: 3.71 | T16: 3.77 | U16: 3.84 | V16: 3.89 | W16: 3.88 | X16: 3.94 | Y16: 3.98 | Z16: 3.99 | AA16: 3.96 | AB16: 3.93 | AC16: 3.93 | AD16: 3.93 | AE16: 3.93 | AF16: 4 | AG16: 3.93 | AH16: 3.96 | AI16: 3.96 | AJ16: 3.97 | AK16: 4.13
A17: Condominiums And Other Apartments | B17: =MAX(C17-0.026,1.5) -> 2.89 | C17: =MAX(D17-0.026,1.5) -> 2.916 | D17: =MAX(E17-0.026,1.5) -> 2.942 | E17: =MAX(F17-0.026,1.5) -> 2.968 | F17: =MAX(G17-0.026,1.5) -> 2.994 | G17: =MAX(H17-0.026,1.5) -> 3.02 | H17: =MAX(I17-0.026,1.5) -> 3.046 | I17: =MAX(J17-0.026,1.5) -> 3.072 | ... K17: =MAX(L17-0.026,1.5) -> 3.124 | L17: 3.15 | M17: 3.14 | N17: 3.17 | O17: 3.11 | P17: 3.11 | Q17: 3.29 | R17: 3.26 | S17: 3.26 | T17: 3.24 | U17: 3.3 | V17: 3.34 | W17: 3.4 | X17: 3.42 | Y17: 3.48 | Z17: 3.43 | AA17: 3.41 | AB17: 3.45 | AC17: 3.46 | AD17: 3.44 | AE17: 3.33 | AF17: 3.52 | AG17: 3.56 | AH17: 3.45 | AI17: 3.48 | AJ17: 3.58 | AK17: 3.67
A18: Landed Properties | B18: =MAX(C18-0.026,1.5) -> 3.87 | C18: =MAX(D18-0.026,1.5) -> 3.896 | D18: =MAX(E18-0.026,1.5) -> 3.922 | E18: =MAX(F18-0.026,1.5) -> 3.948 | F18: =MAX(G18-0.026,1.5) -> 3.974 | G18: =MAX(H18-0.026,1.5) -> 4 | H18: =MAX(I18-0.026,1.5) -> 4.026 | I18: =MAX(J18-0.026,1.5) -> 4.052 | ... K18: =MAX(L18-0.026,1.5) -> 4.104 | L18: 4.13 | M18: 4.13 | N18: 4.07 | O18: 4.12 | P18: 4.2 | Q18: 4.38 | R18: 4.24 | S18: 4.17 | T18: 4.29 | U18: 4.28 | V18: 4.3 | W18: 4.32 | X18: 4.33 | Y18: 4.35 | Z18: 4.38 | AA18: 4.39 | AB18: 4.28 | AC18: 4.32 | AD18: 4.22 | AE18: 4.22 | AF18: 4.54 | AG18: 4.33 | AH18: 4.3 | AI18: 4.19 | AJ18: 4.33 | AK18: 4.65
A19: Other Types Of Dwelling | B19: =MAX(C19-0.026,1.5) -> 1.62 | C19: =MAX(D19-0.026,1.5) -> 1.646 | D19: =MAX(E19-0.026,1.5) -> 1.672 | E19: =MAX(F19-0.026,1.5) -> 1.698 | F19: =MAX(G19-0.026,1.5) -> 1.724 | G19: =MAX(H19-0.026,1.5) -> 1.75 | H19: =MAX(I19-0.026,1.5) -> 1.776 | I19: =MAX(J19-0.026,1.5) -> 1.802 | ... K19: =MAX(L19-0.026,1.5) -> 1.854 | L19: 1.88 | M19: 2.24 | N19: 2.49 | O19: 2.26 | P19: 2.2 | Q19: 2.06 | R19: 2.81 | S19: 2.67 | T19: 2.85 | U19: 2.65 | V19: 2.92 | W19: 3.02 | X19: 3.38 | Y19: 2.99 | Z19: 3.21 | AA19: 2.65 | AB19: 2.98 | AC19: 3.09 | AD19: 3.04 | AE19: 2.94 | AF19: 2.91 | AG19: 2.85 | AH19: 2.98 | AI19: 3.43 | AJ19: 3.17 | AK19: 3.05
A21: Household size 2000 to 2025 historical trend | C21: =(L11-AK11)/25 -> -0.0256 | D21: p.a
A22: No of household 2020 to 2025 recent trend | C22: =(L4/Q4)^(1/5)-1 -> 0.016153309 | D22: p.a
A23: Average and Median Salaries Growth Rate | C23: =(E53/E43)^(1/10)-1 -> 0.046640275 | D23: p.a
A24: (CAGR) 2015-2025
A26: Average and Median Salaries
A27: Dollar | B27: Resident Households Average | C27: Resident Households Median | D27: Resident Employed Households Average | E27: Resident Employed Households Median | F27: Annual Median Employed Household
A28: 2000 | B28: 4988 | C28: 3638 | D28: 5456 | E28: 4000 | F28: =E28*12 -> 48000 | G28: According to nas.gov.sg, between 2000 and 2014, Singapore's
A29: 2001 | B29: 5338 | C29: 3860 | D29: 5736 | E29: 4141 | F29: =E29*12 -> 49692 | G29: economy experienced significant grwoth. Thus, 2000 to 2014 not used to
A30: 2002 | B30: 5069 | C30: 3628 | D30: 5572 | E30: 4038 | F30: =E30*12 -> 48456 | G30: calculate Average and Median Salaries Growth Rate
A31: 2003 | B31: 5075 | C31: 3601 | D31: 5618 | E31: 4050 | F31: =E31*12 -> 48600
A32: 2004 | B32: 5194 | C32: 3689 | D32: 5761 | E32: 4106 | F32: =E32*12 -> 49272
A33: 2005 | B33: 5447 | C33: 3860 | D33: 6052 | E33: 4345 | F33: =E33*12 -> 52140
A34: 2006 | B34: 5715 | C34: 4000 | D34: 6280 | E34: 4495 | F34: =E34*12 -> 53940
A35: 2007 | B35: 6295 | C35: 4375 | D35: 6889 | E35: 4883 | F35: =E35*12 -> 58596
A36: 2008 | B36: 7086 | C36: 4946 | D36: 7752 | E36: 5475 | F36: =E36*12 -> 65700
A37: 2009 | B37: 6826 | C37: 4850 | D37: 7549 | E37: 5398 | F37: =E37*12 -> 64776
A38: 2010 | B38: 7214 | C38: 5000 | D38: 8058 | E38: 5704 | F38: =E38*12 -> 68448
A39: 2011 | B39: 8039 | C39: 5624 | D39: 8864 | E39: 6286 | F39: =E39*12 -> 75432
A40: 2012 | B40: 8637 | C40: 6000 | D40: 9515 | E40: 6712 | F40: =E40*12 -> 80544
A41: 2013 | B41: 8692 | C41: 6257 | D41: 9597 | E41: 7000 | F41: =E41*12 -> 84000
A42: 2014 | B42: 9176 | C42: 6500 | D42: 10244 | E42: 7400 | F42: =E42*12 -> 88800
... A46: 2018 | B46: 9679 | C46: 6984 | D46: 11016 | E46: 8169 | F46: =E46*12 -> 98028
A47: 2019 | B47: 9763 | C47: 7000 | D47: 11250 | E47: 8333 | F47: =E47*12 -> 99996 | J47: 2015-2025 used to calculate CAGR
A48: 2020 | B48: 9634 | C48: 6810 | D48: 11111 | E48: 8092 | F48: =E48*12 -> 97104 | G48: 2020-2022 COVID which caused income to drop in 2020
A49: 2021 | B49: 9827 | C49: 7261 | D49: 11137 | E49: 8421 | F49: =E49*12 -> 101052 | G49: then spike back in 2021-2022 as economy recovered.
A50: 2022 | B50: 10414 | C50: 7585 | D50: 11906 | E50: 8904 | F50: =E50*12 -> 106848 | G50: Not a true reflection of sustainable income growth
A51: 2023 | B51: 11057 | C51: 8196 | D51: 12673 | E51: 9646 | F51: =E51*12 -> 115752
A52: 2024 | B52: 11629 | C52: 8388 | D52: 13188 | E52: 11314 | F52: =E52*12 -> 135768
A53: 2025 | B53: 12157 | C53: 8742 | D53: 13752 | E53: 12027 | F53: =E53*12 -> 144324
A54: 2026 | B54: =B53*1.047 -> 12728.379 | C54: =C53*1.047 -> 9152.874 | D54: =D53*1.047 -> 14398.344 | E54: =E53*1.047 -> 12592.269 | F54: =E54*12 -> 151107.23
A55: 2027 | B55: =B54*1.047 -> 13326.613 | C55: =C54*1.047 -> 9583.0591 | D55: =D54*1.047 -> 15075.066 | E55: =E54*1.047 -> 13184.106 | F55: =E55*12 -> 158209.27
A56: 2028 | B56: =B55*1.047 -> 13952.964 | C56: =C55*1.047 -> 10033.463 | D56: =D55*1.047 -> 15783.594 | E56: =E55*1.047 -> 13803.759 | F56: =E56*12 -> 165645.1
A57: 2029 | B57: =B56*1.047 -> 14608.753 | C57: =C56*1.047 -> 10505.036 | D57: =D56*1.047 -> 16525.423 | E57: =E56*1.047 -> 14452.535 | F57: =E57*12 -> 173430.42
A58: 2030 | B58: =B57*1.047 -> 15295.364 | C58: =C57*1.047 -> 10998.772 | D58: =D57*1.047 -> 17302.118 | E58: =E57*1.047 -> 15131.804 | F58: =E58*12 -> 181581.65
A59: 2031 | B59: =B58*1.047 -> 16014.246 | C59: =C58*1.047 -> 11515.715 | D59: =D58*1.047 -> 18115.318 | E59: =E58*1.047 -> 15842.999 | F59: =E59*12 -> 190115.99
A60: 2032 | B60: =B59*1.047 -> 16766.916 | C60: =C59*1.047 -> 12056.953 | D60: =D59*1.047 -> 18966.738 | E60: =E59*1.047 -> 16587.62 | F60: =E60*12 -> 199051.44
A61: 2033 | B61: =B60*1.047 -> 17554.961 | C61: =C60*1.047 -> 12623.63 | D61: =D60*1.047 -> 19858.174 | E61: =E60*1.047 -> 17367.238 | F61: =E61*12 -> 208406.86
A62: 2034 | B62: =B61*1.047 -> 18380.044 | C62: =C61*1.047 -> 13216.941 | D62: =D61*1.047 -> 20791.508 | E62: =E61*1.047 -> 18183.499 | F62: =E62*12 -> 218201.98
A63: 2035 | B63: =B62*1.047 -> 19243.906 | C63: =C62*1.047 -> 13838.137 | D63: =D62*1.047 -> 21768.709 | E63: =E62*1.047 -> 19038.123 | F63: =E63*12 -> 228457.48
A66: Years | B66: ACTUAL | C66: PROJECTED
A67: 2000 | B67: 4000
A68: 2001 | B68: 4141
A69: 2002 | B69: 4038
A70: 2003 | B70: 4050
A71: 2004 | B71: 4106
A72: 2005 | B72: 4345
A73: 2006 | B73: 4495
A74: 2007 | B74: 4883
A75: 2008 | B75: 5475
A76: 2009 | B76: 5398
A77: 2010 | B77: 5704
A78: 2011 | B78: 6286
... A91: 2024 | B91: 11314
A92: 2025 | B92: 12027 | C92: 12027
A93: 2026 | C93: =C92*1.047 -> 12592.269
A94: 2027 | C94: =C93*1.047 -> 13184.106
A95: 2028 | C95: =C94*1.047 -> 13803.759
A96: 2029 | C96: =C95*1.047 -> 14452.535
A97: 2030 | C97: =C96*1.047 -> 15131.804
A98: 2031 | C98: =C97*1.047 -> 15842.999
A99: 2032 | C99: =C98*1.047 -> 16587.62
A100: 2033 | C100: =C99*1.047 -> 17367.238
A101: 2034 | C101: =C100*1.047 -> 18183.499
A102: 2035 | C102: =C101*1.047 -> 19038.123

Sheet M4 Financing Gap and OOP
A1: Subsidies for Acute Inpatient Care at Public Healthcare Institutions | E1: Assumption Table
A2: Current Acute Inpatient Subsidy Levels (B2/C Ward) | E2: Assumptions
A3: PCHI Range | B3: SC Subsidy Rate | E3: Parameters | F3: Low | G3: Base | H3: High | I3: Unit | J3: Low scenario = government grows slowly + lower subsidies -> bigger household burden, smaller financing gap
A4: No PCHI (AV ≤ $21,000) | B4: 0.8 | E4: Govt Hospital Budget Base Year 2025 (SGD million) | F4: ='M3 Healthcare Budget'!L6 -> 7518.12 | G4: ='M3 Healthcare Budget'!L6 -> 7518.12 | H4: ='M3 Healthcare Budget'!L6 -> 7518.12 | I4: SGD million | J4: Base scenario = most realistic projection based on historical data → your main model output
A5: No PCHI (AV > $21,000) | B5: 0.5 | E5: Govt Budget Growth Rate (p.a.) | F5: 0.04 | G5: =('M3 Healthcare Budget'!B6/'M3 Healthcare Budget'!L6)^(1/10)-1 -> 0.057529959 | H5: 0.09 | I5: % p.a. | J5: High scenario = goverment spending grows fast + higher subsidies → smaller household burden, larger financing gap
A6: $0 < PCHI ≤ $2,100 | B6: 0.8 | E6: Medical Inflation Rate 2025 (from M3) | F6: ='M3 Healthcare Costs'!M5 -> 0.027 | G6: ='M3 Healthcare Costs'!M5 -> 0.027 | H6: ='M3 Healthcare Costs'!M5 -> 0.027 | I6: % p.a.
A7: $2,100 < PCHI ≤ $2,300 | B7: 0.75 | E7: Blended Subsidy Rate | F7: 0.55 | G7: =B13 -> 0.65 | H7: 0.75 | I7: %
A8: $2,300 < PCHI ≤ $2,600 | B8: 0.7 | E8: No. of Resident Households (2025) | F8: ='M4 Household data'!L4 -> 1487100 | G8: ='M4 Household data'!L4 -> 1487100 | H8: ='M4 Household data'!L4 -> 1487100 | I8: Households
A9: $2,600 < PCHI ≤ $3,000 | B9: 0.65 | E9: Household Growth Rate (p.a.) | F9: 0.012 | G9: ='M4 Household data'!C22 -> 0.016153309 | H9: 0.02 | I9: % p.a.
A10: $3,000 < PCHI ≤ $3,300 | B10: 0.6 | E10: Median Monthly Household Income (2025) | F10: ='M4 Household data'!E53 -> 12027 | G10: ='M4 Household data'!E53 -> 12027 | H10: ='M4 Household data'!E53 -> 12027 | I10: SGD/month
A11: $3,300 < PCHI ≤ $3,600 | B11: 0.55 | E11: Income Growth Rate (p.a.) | F11: 0.03 | G11: ='M4 Household data'!C23 -> 0.046640275 | H11: 0.06 | I11: % p.a.
A12: PCHI > $3,600 | B12: 0.5
A13: Weighted Average | B13: =AVERAGE(B4:B12) -> 0.65
A14: According to Ministry of Health (MOH) and CPF data, approximately 7 in 10 of hospitalisations occur in these subsidised wards.
A16: Current Acute Inpatient Subsidy Levels (B2+ Ward)
A17: PCHI Range | B17: SC Subsidy Rate
A18: No PCHI (AV ≤ $21,000) | B18: 0.5
A19: No PCHI (AV > $21,000) | B19: 0.35
A20: $0 < PCHI ≤ $2,100 | B20: 0.5
A21: $2,100 < PCHI ≤ $2,300 | B21: 0.475 | E21: Projection Table
A22: $2,300 < PCHI ≤ $2,600 | B22: 0.45 | E22: Financing Gap (SGD million)
A23: $2,600 < PCHI ≤ $3,000 | B23: 0.425 | E23: Metric | G23: 2026 | H23: 2027 | I23: 2028 | J23: 2029 | K23: 2030 | L23: 2031 | M23: 2032 | N23: 2033 | O23: 2034 | P23: 2035
A24: $3,000 < PCHI ≤ $3,300 | B24: 0.4 | E24: Projected Government Healthcare Budget | G24: ='M3 Healthcare Budget'!K6 -> 8005.52 | H24: ='M3 Healthcare Budget'!J6 -> 8577.5 | I24: ='M3 Healthcare Budget'!I6 -> 9149.48 | J24: ='M3 Healthcare Budget'!H6 -> 9721.46 | K24: ='M3 Healthcare Budget'!G6 -> 10293.44 | L24: ='M3 Healthcare Budget'!F6 -> 10865.42 | M24: ='M3 Healthcare Budget'!E6 -> 11437.4 | N24: ='M3 Healthcare Budget'!D6 -> 12009.38 | O24: ='M3 Healthcare Budget'!C6 -> 12581.36 | P24: ='M3 Healthcare Budget'!B6 -> 13153.34
A25: $3,300 < PCHI ≤ $3,600 | B25: 0.375 | E25: Projected Government Healthcare Cost (M3) | G25: ='M3 Healthcare Costs'!B19 -> 7975.5627 | H25: ='M3 Healthcare Costs'!C19 -> 8463.9816 | I25: ='M3 Healthcare Costs'!D19 -> 8988.1771 | J25: ='M3 Healthcare Costs'!E19 -> 9552.898 | K25: ='M3 Healthcare Costs'!F19 -> 10163.089 | L25: ='M3 Healthcare Costs'!G19 -> 10824.085 | M25: ='M3 Healthcare Costs'!H19 -> 11541.764 | N25: ='M3 Healthcare Costs'!I19 -> 12322.694 | ... P25: ='M3 Healthcare Costs'!K19 -> 14104.814
A26: PCHI > $3,600 | B26: 0.35 | E26: Financing Gap | G26: =G25-G24 -> -29.957272 | H26: =H25-H24 -> -113.51843 | I26: =I25-I24 -> -161.30287 | J26: =J25-J24 -> -168.562 | K26: =K25-K24 -> -130.35059 | L26: =L25-L24 -> -41.335294 | M26: =M25-M24 -> 104.36376 | N26: =N25-N24 -> 313.31363 | ... P26: =P25-P24 -> 951.47416
A27: Weighted Average | B27: =AVERAGE(B18:B26) -> 0.425 | E27: Gap as % of Govt Budget | G27: =(G26/G24) -> -0.003742077 | H27: =(H26/H24) -> -0.013234443 | I27: =(I26/I24) -> -0.017629731 | J27: =(J26/J24) -> -0.017339165 | K27: =(K26/K24) -> -0.012663462 | L27: =(L26/L24) -> -0.0038042978 | M27: =(M26/M24) -> 0.0091247797 | N27: =(N26/N24) -> 0.026089077 | ... P27: =(P26/P24) -> 0.072337076
G28: Surplus | M28: Deficit
A29: Financing Gap = Total Healthcare Expenditure (M3) − Projected Govt Budget (M3)
E30: Household Out-of -Pocket Burden (SGD million)
E31: Metric | G31: 2026 | H31: 2027 | I31: 2028 | J31: 2029 | K31: 2030 | L31: 2031 | M31: 2032 | N31: 2033 | O31: 2034 | P31: 2035
E32: Total Healthcare Expenditure (M3) | G32: =G25 -> 7975.5627 | H32: =H25 -> 8463.9816 | I32: =I25 -> 8988.1771 | J32: =J25 -> 9552.898 | K32: =K25 -> 10163.089 | L32: =L25 -> 10824.085 | M32: =M25 -> 11541.764 | N32: =N25 -> 12322.694 | ... P32: =P25 -> 14104.814
E33: Government Subsidy Rate (Weighted Average) | G33: =IF($Q$33="Low",0.55,IF($Q$33="High",0.75,0.65)) -> 0.75 | H33: =IF($Q$33="Low",0.55,IF($Q$33="High",0.75,0.65)) -> 0.75 | I33: =IF($Q$33="Low",0.55,IF($Q$33="High",0.75,0.65)) -> 0.75 | J33: =IF($Q$33="Low",0.55,IF($Q$33="High",0.75,0.65)) -> 0.75 | K33: =IF($Q$33="Low",0.55,IF($Q$33="High",0.75,0.65)) -> 0.75 | L33: =IF($Q$33="Low",0.55,IF($Q$33="High",0.75,0.65)) -> 0.75 | M33: =IF($Q$33="Low",0.55,IF($Q$33="High",0.75,0.65)) -> 0.75 | N33: =IF($Q$33="Low",0.55,IF($Q$33="High",0.75,0.65)) -> 0.75 | ... P33: =IF($Q$33="Low",0.55,IF($Q$33="High",0.75,0.65)) -> 0.75 | Q33: High | R33: click here to change drop down to Low,Base,High scenarios
E34: Total Out-Of-Pocket Expenditure | G34: =G32/G33*(1-G33) -> 2658.5209 | H34: =H32/H33*(1-H33) -> 2821.3272 | I34: =I32/I33*(1-I33) -> 2996.059 | J34: =J32/J33*(1-J33) -> 3184.2993 | K34: =K32/K33*(1-K33) -> 3387.6965 | L34: =L32/L33*(1-L33) -> 3608.0282 | M34: =M32/M33*(1-M33) -> 3847.2546 | N34: =N32/N33*(1-N33) -> 4107.5645 | ... P34: =P32/P33*(1-P33) -> 4701.6047
E35: Number of Resident Household | G35: ='M4 Household data'!K4 -> 1510893.6 | H35: ='M4 Household data'!J4 -> 1535067.9 | I35: ='M4 Household data'!I4 -> 1559629 | J35: ='M4 Household data'!H4 -> 1584583 | K35: ='M4 Household data'!G4 -> 1609936.4 | L35: ='M4 Household data'!F4 -> 1635695.4 | M35: ='M4 Household data'!E4 -> 1661866.5 | N35: ='M4 Household data'!D4 -> 1688456.3 | O35: ='M4 Household data'!C4 -> 1715471.6 | P35: ='M4 Household data'!B4 -> 1742919.2
E36: Out of Pocket per Household (SGD/year) | G36: =($G$34*1000000)/$G$35 -> 1759.5686 | H36: =($H$34*1000000)/$H$35 -> 1837.9169 | I36: =($I$34*1000000)/$I$35 -> 1921.0075 | J36: =($J$34*1000000)/$J$35 -> 2009.5503 | K36: =($K$34*1000000)/$K$35 -> 2104.2425 | L36: =($L$34*1000000)/$L$35 -> 2205.807 | M36: =($M$34*1000000)/$M$35 -> 2315.0203 | N36: =($N$34*1000000)/$N$35 -> 2432.7336 | O36: =($O$34*1000000)/$O$35 -> 2559.8912 | P36: =(P34*1000000)/P35 -> 2697.546
E37: Median Annual Household Income (SGD/year) | G37: ='M4 Household data'!F54 -> 151107.23 | H37: ='M4 Household data'!F55 -> 158209.27 | I37: ='M4 Household data'!F56 -> 165645.1 | J37: ='M4 Household data'!F57 -> 173430.42 | K37: ='M4 Household data'!F58 -> 181581.65 | L37: ='M4 Household data'!F59 -> 190115.99 | M37: ='M4 Household data'!F60 -> 199051.44 | N37: ='M4 Household data'!F61 -> 208406.86 | O37: ='M4 Household data'!F62 -> 218201.98 | P37: ='M4 Household data'!F63 -> 228457.48
E38: Healthcare as % of Household Income | G38: =G36 / G37 -> 0.011644503 | H38: =H36 / H37 -> 0.011616999 | I38: =I36 / I37 -> 0.011597128 | J38: =J36 / J37 -> 0.011587069 | K38: =K36 / K37 -> 0.011588409 | L38: =L36 / L37 -> 0.011602427 | M38: =M36 / M37 -> 0.011630261 | N38: =N36 / N37 -> 0.011673002 | ... P38: =P36 / P37 -> 0.01180765
E39: Burden Status | G39: Low | H39: Low | I39: Low | J39: Low | K39: Low | L39: Low | M39: Low | N39: Low | O39: Low | P39: Low

Sheet M4 Trade-off Analysis
A1: Trade off analysis (Subsidy rate vs Fiscal Sustainability )
A2: Household share of cost (proxy for out of pocket OOP burden)
A3: 2035
A4: Estimated total hospital cost (government expenditure and household OOP) | B4: ='M4 Financing Gap and OOP'!P25/0.65 -> 21699.714
A5: Projected government hospital budget | B5: ='M4 Financing Gap and OOP'!P24 -> 13153.34
A6: Estimated median household income (annual S$ per household) | B6: ='M4 Financing Gap and OOP'!P37 -> 228457.48
A7: Projected number of resident households | B7: ='M4 Household data'!B4 -> 1742919.2
A8: Subsidy rate | B8: Government healthcare cost projection (S$ million) | C8: Total household OOP (S$ million) | D8: Financing gap (S$ million) | E8: OOP per household (S$ per household) | F8: Household OOP as % of household income
A9: 0.55 | B9: =$B$4*A9 -> 11934.843 | C9: =$B$4*(1-A9) -> 9764.8713 | D9: =B9-$B$5 -> -1218.4972 | E9: =C9/$B$7*1000000 -> 5602.5956 | F9: =E9/$B$6 -> 0.024523582
A10: 0.6 | B10: =$B$4*A10 -> 13019.828 | C10: =$B$4*(1-A10) -> 8679.8856 | D10: =B10-$B$5 -> -133.51154 | E10: =C10/$B$7*1000000 -> 4980.0849 | F10: =E10/$B$6 -> 0.021798739
A11: 0.65 | B11: =$B$4*A11 -> 14104.814 | C11: =$B$4*(1-A11) -> 7594.8999 | D11: =B11-$B$5 -> 951.47416 | E11: =C11/$B$7*1000000 -> 4357.5743 | F11: =E11/$B$6 -> 0.019073897
A12: 0.7 | B12: =$B$4*A12 -> 15189.8 | C12: =$B$4*(1-A12) -> 6509.9142 | D12: =B12-$B$5 -> 2036.4599 | E12: =C12/$B$7*1000000 -> 3735.0637 | F12: =E12/$B$6 -> 0.016349054
A13: 0.75 | B13: =$B$4*A13 -> 16274.786 | C13: =$B$4*(1-A13) -> 5424.9285 | D13: =B13-$B$5 -> 3121.4456 | E13: =C13/$B$7*1000000 -> 3112.5531 | F13: =E13/$B$6 -> 0.013624212
A15: Note
A16: Subsidy rate | B16: Assumed average government subsidy share of total hospital cost

Sheet M4 Ward OOP Calculator 
A1: Select your ward type and Income Bracket | M1: B2/C Ward | N1: SC Subsidy Rate | O1: PCHI -- Per Capita Household Income
A2: Select ward class and monthly per capita household income (PCHI) to project out of pocket cost per admission and household burden through 2035 | M2: No PCHI (AV ≤ $21000) | N2: 0.8 | O2: Household has NO income but owns a property worth ≤ $21,000 annual value e.g. elderly retirees living in HDB with no income Subsidy = 80% (most help needed)
M3: No PCHI (AV > $21000) | N3: 0.5 | O3: Household has NO income but owns a property worth > $21,000 annual value e.g. retirees living in private property — asset rich but income poor Subsidy = 50% (lower help since they own expensive property)
A4: Step 1: Select your scenario | M4: $0 < PCHI ≤ $2100 | N4: 0.8 | O4: Very low income households e.g. family of 4 earning less than $8,400/month total Subsidy = 80%
A5: Ward Type (Based on PCHI) | C5: B2+ Ward | E5: Per Capita Household Income (PCHI) is the total gross monthly income of all household members divided by the number of people in the household | M5: $2100 < PCHI ≤ $2300 | N5: 0.75 | O5: Low income e.g. family of 4 earning $8,400–$9,200/month Subsidy = 75%
A6: Monthly PCHI bracket | C6: $3300 < PCHI ≤ $3600 | M6: $2300 < PCHI ≤ $2600 | N6: 0.7 | O6: Lower middle income Subsidy = 70%
A7: Applied Subsidy Rate | C7: =IF(C5="B2/C Ward",VLOOKUP(C6,$M$2:$N$10,2,FALSE),VLOOKUP(C6,$M$13:$N$22,2,FALSE)) -> 0.375 | M7: $2600 < PCHI ≤ $3000 | N7: 0.65 | O7: Middle income e.g. family of 4 earning $10,400–$12,000/month Subsidy = 65%
M8: $3000 < PCHI ≤ $3300 | N8: 0.6 | O8: Upper middle income Subsidy = 60%
A9: Step 2: Key Assumption | M9: $3300 < PCHI ≤ $3600 | N9: 0.55 | O9: High income Subsidy = 55%
A10: Average Cost per Admission 2025 (SGD) | B10: =(7518.12*1000000)/'M2 BOR & Tradeoff analysis'!K42 -> 12490.06 | C10: Hospital Operating Expenditure 2025 (M3) ÷ Total Admissions 2025 (M2) | M10: PCHI > $3600 | N10: 0.5 | O10: Highest income e.g. family of 4 earning more than $14,400/month Subsidy = 50% (least help needed)
A11: Medical Inflation Rate (from M3) | B11: ='M3 Healthcare Costs'!B8 -> 0.035150772
A12: Household Income Growth Rate | B12: ='M4 Household data'!C23 -> 0.046640275 | M12: B2+ Ward | N12: SC Subsidy Rate
A13: Median Monthly HH Employment Income 2025 (SGD) | B13: ='M4 Household data'!E53 -> 12027 | M13: No PCHI (AV ≤ $21000) | N13: 0.5
M14: No PCHI (AV > $21000) | N14: 0.35
A15: Step 3: Projected Out of Pocket per Admission and Household Burden (2025-2035) | M15: $0 < PCHI ≤ $2100 | N15: 0.5
A16: Year | B16: Cost per Admission (SGD) | C16: Applied Subsidy Rate | D16: OOP per Admission (SGD) | E16: Median Monthly Household Income (SGD) | F16: Median Annual Household Income (SGD) | G16: OOP as % of Annual Income | H16: Burden Status | M16: $2100 < PCHI ≤ $2300 | N16: 0.475
A17: 2025 | B17: =B10 -> 12490.06 | C17: =$C$7 -> 0.375 | D17: =B17*(1-C17) -> 7806.2874 | E17: =B13 -> 12027 | F17: =E17*12 -> 144324 | G17: =D17/F17 -> 0.05408863 | H17: =IF(G17>0.1,"⚠ HIGH",IF(G17>0.05,"⚠ MODERATE","✓ LOW")) -> ⚠ MODERATE | I17: Household burden is classified as Low (< 5% of annual income), Moderate (5–10%) and High (> 10%), based on general financial planning benchmarks. No official MOH threshold exists for household healthcare burden classification. | M17: $2300 < PCHI ≤ $2600 | N17: 0.45
A18: 2026 | B18: =B17*(1+$B$11) -> 12929.095 | C18: =$C$7 -> 0.375 | D18: =B18*(1-C18) -> 8080.6844 | E18: =E17*(1+$B$12) -> 12587.943 | F18: =E18*12 -> 151055.31 | G18: =D18/F18 -> 0.053494871 | H18: =IF(G18>0.1,"⚠ HIGH",IF(G18>0.05,"⚠ MODERATE","✓ LOW")) -> ⚠ MODERATE | M18: $2600 < PCHI ≤ $3000 | N18: 0.425
A19: 2027 | B19: =B18*(1+$B$11) -> 13383.563 | C19: =$C$7 -> 0.375 | D19: =B19*(1-C19) -> 8364.7267 | E19: =E18*(1+$B$12) -> 13175.048 | F19: =E19*12 -> 158100.57 | G19: =D19/F19 -> 0.052907631 | H19: =IF(G19>0.1,"⚠ HIGH",IF(G19>0.05,"⚠ MODERATE","✓ LOW")) -> ⚠ MODERATE | M19: $3000 < PCHI ≤ $3300 | N19: 0.4
A20: 2028 | B20: =B19*(1+$B$11) -> 13854.005 | C20: =$C$7 -> 0.375 | D20: =B20*(1-C20) -> 8658.7533 | E20: =E19*(1+$B$12) -> 13789.536 | F20: =E20*12 -> 165474.43 | G20: =D20/F20 -> 0.052326837 | H20: =IF(G20>0.1,"⚠ HIGH",IF(G20>0.05,"⚠ MODERATE","✓ LOW")) -> ⚠ MODERATE | M20: $3300 < PCHI ≤ $3600 | N20: 0.375
A21: 2029 | B21: =B20*(1+$B$11) -> 14340.984 | C21: =$C$7 -> 0.375 | D21: =B21*(1-C21) -> 8963.1151 | E21: =E20*(1+$B$12) -> 14432.683 | F21: =E21*12 -> 173192.2 | G21: =D21/F21 -> 0.051752418 | H21: =IF(G21>0.1,"⚠ HIGH",IF(G21>0.05,"⚠ MODERATE","✓ LOW")) -> ⚠ MODERATE | M21: PCHI > $3600 | N21: 0.35
A22: 2030 | B22: =B21*(1+$B$11) -> 14845.081 | C22: =$C$7 -> 0.375 | D22: =B22*(1-C22) -> 9278.1756 | E22: =E21*(1+$B$12) -> 15105.828 | F22: =E22*12 -> 181269.93 | G22: =D22/F22 -> 0.051184306 | H22: =IF(G22>0.1,"⚠ HIGH",IF(G22>0.05,"⚠ MODERATE","✓ LOW")) -> ⚠ MODERATE
A23: 2031 | B23: =B22*(1+$B$11) -> 15366.897 | C23: =$C$7 -> 0.375 | D23: =B23*(1-C23) -> 9604.3106 | E23: =E22*(1+$B$12) -> 15810.368 | F23: =E23*12 -> 189724.41 | G23: =D23/F23 -> 0.05062243 | H23: =IF(G23>0.1,"⚠ HIGH",IF(G23>0.05,"⚠ MODERATE","✓ LOW")) -> ⚠ MODERATE
A24: 2032 | B24: =B23*(1+$B$11) -> 15907.055 | C24: =$C$7 -> 0.375 | D24: =B24*(1-C24) -> 9941.9095 | E24: =E23*(1+$B$12) -> 16547.767 | F24: =E24*12 -> 198573.21 | G24: =D24/F24 -> 0.050066721 | H24: =IF(G24>0.1,"⚠ HIGH",IF(G24>0.05,"⚠ MODERATE","✓ LOW")) -> ⚠ MODERATE
A25: 2033 | B25: =B24*(1+$B$11) -> 16466.2 | C25: =$C$7 -> 0.375 | D25: =B25*(1-C25) -> 10291.375 | E25: =E24*(1+$B$12) -> 17319.56 | F25: =E25*12 -> 207834.72 | G25: =D25/F25 -> 0.049517114 | H25: =IF(G25>0.1,"⚠ HIGH",IF(G25>0.05,"⚠ MODERATE","✓ LOW")) -> ✓ LOW
A26: 2034 | B26: =B25*(1+$B$11) -> 17045 | C26: =$C$7 -> 0.375 | D26: =B26*(1-C26) -> 10653.125 | E26: =E25*(1+$B$12) -> 18127.349 | F26: =E26*12 -> 217528.19 | G26: =D26/F26 -> 0.048973539 | H26: =IF(G26>0.1,"⚠ HIGH",IF(G26>0.05,"⚠ MODERATE","✓ LOW")) -> ✓ LOW
A27: 2035 | B27: =B26*(1+$B$11) -> 17644.145 | C27: =$C$7 -> 0.375 | D27: =B27*(1-C27) -> 11027.591 | E27: =E26*(1+$B$12) -> 18972.813 | F27: =E27*12 -> 227673.76 | G27: =D27/F27 -> 0.048435932 | H27: =IF(G27>0.1,"⚠ HIGH",IF(G27>0.05,"⚠ MODERATE","✓ LOW")) -> ✓ LOW

Sheet Data
A1: Data Description | B1: Purpose | C1: Source
A2: Demographic Projection: Population
A3: Singapore Population by Age Group | B3: To analyze population growth trends and project future population by age group through 2035. Base population will be used to forecast hospital demand | C3: https://www.singstat.gov.sg/find-data/search-by-theme/population/population-and-population-structure/latest-data
A4: Hospital Demand and Admission Forecasting
A5: Hospital Admission Rate By Sex And Age, Annually-HAR | B5: Obtain baseline age-specific admission rates. | C5: https://data.gov.sg/datasets/d_e2acb8eaf4eaf1e0a1608af9a9cd2634/view
A6: MOH Bed Expansion Plan | B6: Acute hospital beds in 2024. Annual bed expansion rate. | C6: https://www.moh.gov.sg/newsroom/expanding-healthcare-capacity-and-transforming-the-healthcare-workforce
A7: Beds In Inpatient Facilities | B7: Used to forecast future acute hospital beds. | C7: https://tablebuilder.singstat.gov.sg/table/TS/M870301
A8: Waiting Times for Admissions | B8: ALOS: Average length of stay | C8: https://www.moh.gov.sg/newsroom/waiting-times-for-admissions-at-public-hospitals
A9: Hospital Bed Occupancy Rate | B9: BOR thresholds | C9: https://www.moh.gov.sg/newsroom/hospital-bed-occupancy-rate/
A10: Healthcare Cost Projection
A11: Annual Government Healthcare Expenditure | B11: Used to forecast future expenditure | C11: https://data.gov.sg/datasets/d_a40c83a6f36893fc4611eda91f84eb6b/view
A12: MOH Healthcare Consumer Price Index | B12: Used to calculate healthcare inflation rate | C12: https://www.moh.gov.sg/others/resources-and-statistics/consumer-price-indices--cpi----household-healthcare-expenditure/
A13: Financing and Subsidy Sustainability
A14: Median household Income | B14: Latest median monthly income figure | C14: https://data.gov.sg/datasets/d_ab4f7ecfc45e0a0eafe4ae4397e77059/view
A15: Household employment Income | B15: To calculate key household income trends (KHIT) | C15: https://tablebuilder.singstat.gov.sg/table/TS/M810361
A16: Number of households in Singapore | B16: Total number of residents households | C16: https://data.gov.sg/datasets/d_2bc812dbfd1e485638435fcdf7aac196/view
A17: Subsidies for Acute Inpatient Care at Public Healthcare Institutions | B17: % subsidy for public hospital patients by ward class | C17: https://www.moh.gov.sg/managing-expenses/schemes-and-subsidies/subsidies-for-acute-inpatient-care-at-public-healthcare-institutions/
